Workbook
Name Confidence_Interval: 'Value at Risk (VaR)'!$AB$23
Name Covariance: '[1]Value at Risk (VaR)'!$V$27
Name Covariance: 'Value at Risk (VaR)'!$V$27
Name Days: '[1]Value at Risk (VaR)'!$AB$21
Name Days: 'Value at Risk (VaR)'!$AB$21
Name Expected_Return: '[1]Value at Risk (VaR)'!$V$21
Name Expected_Return: 'Value at Risk (VaR)'!$V$21
Name Portfolio_St._dev.: '[1]Value at Risk (VaR)'!$Y$26
Name Portfolio_St._dev.: 'Value at Risk (VaR)'!$Y$26
Name Portfolio_Value: '[1]Value at Risk (VaR)'!$Y$21
Name Portfolio_Value: 'Value at Risk (VaR)'!$Y$21
Name Portfolio_Variance: 'Value at Risk (VaR)'!$Y$25
Name St._dev.: '[1]Value at Risk (VaR)'!$V$26
Name St._dev.: 'Value at Risk (VaR)'!$V$26
Name St._dev._nifty: '[1]Value at Risk (VaR)'!$V$22
Name St._dev._nifty: 'Value at Risk (VaR)'!$V$22
Name UPDATE: '[2]Data Sheet'!$E$1
Name UPDATE: '[1]Data Sheet'!$E$1
Name UPDATE: 'Data Sheet'!$E$1
Name Weight_of_Nifty_50: '[1]Value at Risk (VaR)'!$Y$22
Name Weight_of_Nifty_50: 'Value at Risk (VaR)'!$Y$22
Name Weight_of_Tata_Power_Ltd.: '[1]Value at Risk (VaR)'!$Y$23
Name Weight_of_Tata_Power_Ltd.: 'Value at Risk (VaR)'!$Y$23
Name Z.score: '[1]Value at Risk (VaR)'!$AB$24
Name Z.score: 'Value at Risk (VaR)'!$AB$24

Sheet Profit & Loss
A1: ='Data Sheet'!B1 -> TATA POWER COMPANY LTD | H1: =UPDATE | M1: SCREENER.IN
A3: Narration | B3: ='Data Sheet'!B16 -> 42825 | C3: ='Data Sheet'!C16 -> 43190 | D3: ='Data Sheet'!D16 -> 43555 | E3: ='Data Sheet'!E16 -> 43921 | F3: ='Data Sheet'!F16 -> 44286 | G3: ='Data Sheet'!G16 -> 44651 | H3: ='Data Sheet'!H16 -> 45016 | I3: ='Data Sheet'!I16 -> 45382 | ... K3: ='Data Sheet'!K16 -> 46112 | L3: Trailing | M3: Best Case | N3: Worst Case
A4: Sales | B4: ='Data Sheet'!B17 -> 27587.59 | C4: ='Data Sheet'!C17 -> 26840.27 | D4: ='Data Sheet'!D17 -> 29881.06 | E4: ='Data Sheet'!E17 -> 29136.37 | F4: ='Data Sheet'!F17 -> 32703.31 | G4: ='Data Sheet'!G17 -> 42815.67 | H4: ='Data Sheet'!H17 -> 55109.08 | I4: ='Data Sheet'!I17 -> 61448.9 | ... K4: ='Data Sheet'!K17 -> 62428.59 | L4: =SUM(Quarters!H4:K4) -> 62428.59 | M4: =$K4+M23*K4 -> 65078.417 | N4: =$K4+N23*L4 -> 62428.59
A5: Expenses | B5: =SUM('Data Sheet'!B18,'Data Sheet'!B20:B24, -1*'Data Sheet'!B19) -> 22114.32 | C5: =SUM('Data Sheet'!C18,'Data Sheet'!C20:C24, -1*'Data Sheet'!C19) -> 21833.12 | D5: =SUM('Data Sheet'!D18,'Data Sheet'!D20:D24, -1*'Data Sheet'!D19) -> 23449.05 | E5: =SUM('Data Sheet'!E18,'Data Sheet'!E20:E24, -1*'Data Sheet'!E19) -> 22331.3 | F5: =SUM('Data Sheet'!F18,'Data Sheet'!F20:F24, -1*'Data Sheet'!F19) -> 25782.41 | G5: =SUM('Data Sheet'!G18,'Data Sheet'!G20:G24, -1*'Data Sheet'!G19) -> 35784.78 | H5: =SUM('Data Sheet'!H18,'Data Sheet'!H20:H24, -1*'Data Sheet'!H19) -> 47381.32 | I5: =SUM('Data Sheet'!I18,'Data Sheet'!I20:I24, -1*'Data Sheet'!I19) -> 50713.62 | ... K5: =SUM('Data Sheet'!K18,'Data Sheet'!K20:K24, -1*'Data Sheet'!K19) -> 49157.32 | L5: =SUM(Quarters!H5:K5) -> 49907.37 | M5: =M4-M6 -> 52025.725 | N5: =N4-N6 -> 51360.879
A6: Operating Profit | B6: =B4-B5 -> 5473.27 | C6: =C4-C5 -> 5007.15 | D6: =D4-D5 -> 6432.01 | E6: =E4-E5 -> 6805.07 | F6: =F4-F5 -> 6920.9 | G6: =G4-G5 -> 7030.89 | H6: =H4-H5 -> 7727.76 | I6: =I4-I5 -> 10735.28 | ... K6: =K4-K5 -> 13271.27 | L6: =SUM(Quarters!H6:K6) -> 12521.22 | M6: =M4*M24 -> 13052.692 | N6: =N4*N24 -> 11067.711
A7: Other Income | B7: ='Data Sheet'!B25 -> 1297.37 | C7: ='Data Sheet'!C25 -> 3873.32 | D7: ='Data Sheet'!D25 -> 3824.37 | E7: ='Data Sheet'!E25 -> 2280.15 | F7: ='Data Sheet'!F25 -> 1774.96 | G7: ='Data Sheet'!G25 -> 2485.5 | H7: ='Data Sheet'!H25 -> 5540.09 | I7: ='Data Sheet'!I25 -> 3416.33 | ... K7: ='Data Sheet'!K25 -> 3432.6 | L7: =SUM(Quarters!H7:K7) -> 4182.65 | M7: 0 | N7: 0
A8: Depreciation | B8: ='Data Sheet'!B26 -> 1955.59 | C8: ='Data Sheet'!C26 -> 2346.17 | D8: ='Data Sheet'!D26 -> 2393.13 | E8: ='Data Sheet'!E26 -> 2633.56 | F8: ='Data Sheet'!F26 -> 2744.94 | G8: ='Data Sheet'!G26 -> 3122.2 | H8: ='Data Sheet'!H26 -> 3439.2 | I8: ='Data Sheet'!I26 -> 3786.37 | ... K8: ='Data Sheet'!K26 -> 4811.09 | L8: =SUM(Quarters!H8:K8) -> 4811.09 | M8: =+$L8 -> 4811.09 | N8: =+$L8 -> 4811.09
A9: Interest | B9: ='Data Sheet'!B27 -> 3364.96 | C9: ='Data Sheet'!C27 -> 3761.48 | D9: ='Data Sheet'!D27 -> 4170 | E9: ='Data Sheet'!E27 -> 4493.73 | F9: ='Data Sheet'!F27 -> 4010.39 | G9: ='Data Sheet'!G27 -> 3859.02 | H9: ='Data Sheet'!H27 -> 4371.65 | I9: ='Data Sheet'!I27 -> 4633.22 | ... K9: ='Data Sheet'!K27 -> 5256.79 | L9: =SUM(Quarters!H9:K9) -> 5256.79 | M9: =+$L9 -> 5256.79 | N9: =+$L9 -> 5256.79
A10: Profit before tax | B10: ='Data Sheet'!B28 -> 1450.09 | C10: ='Data Sheet'!C28 -> 2772.82 | D10: ='Data Sheet'!D28 -> 3693.25 | E10: ='Data Sheet'!E28 -> 1957.93 | F10: ='Data Sheet'!F28 -> 1940.53 | G10: ='Data Sheet'!G28 -> 2535.17 | H10: ='Data Sheet'!H28 -> 5457 | I10: ='Data Sheet'!I28 -> 5732.02 | ... K10: ='Data Sheet'!K28 -> 6635.99 | L10: =SUM(Quarters!H10:K10) -> 6635.99 | M10: =M6+M7-SUM(M8:M9) -> 2984.8123 | N10: =N6+N7-SUM(N8:N9) -> 999.83127
A11: Tax | B11: ='Data Sheet'!B29 -> 350.46 | C11: ='Data Sheet'!C29 -> 161.97 | D11: ='Data Sheet'!D29 -> 1087.59 | E11: ='Data Sheet'!E29 -> 641.49 | F11: ='Data Sheet'!F29 -> 501.88 | G11: ='Data Sheet'!G29 -> 379.56 | H11: ='Data Sheet'!H29 -> 1647.33 | I11: ='Data Sheet'!I29 -> 1451.92 | ... K11: ='Data Sheet'!K29 -> 1518.43 | L11: =SUM(Quarters!H11:K11) -> 1518.43 | M11: =IF($L10>0,$L11/$L10,0) -> 0.2288174 | N11: =IF($L10>0,$L11/$L10,0) -> 0.2288174
A12: Net profit | B12: ='Data Sheet'!B30 -> 896.55 | C12: ='Data Sheet'!C30 -> 2408.3 | D12: ='Data Sheet'!D30 -> 2356.19 | E12: ='Data Sheet'!E30 -> 1017.38 | F12: ='Data Sheet'!F30 -> 1127.38 | G12: ='Data Sheet'!G30 -> 1741.46 | H12: ='Data Sheet'!H30 -> 3336.44 | I12: ='Data Sheet'!I30 -> 3696.25 | ... K12: ='Data Sheet'!K30 -> 3747.19 | L12: =SUM(Quarters!H12:K12) -> 3747.19 | M12: =M10-M11*M10 -> 2301.8353 | N12: =N10-N11*N10 -> 771.05248
A13: EPS | B13: =IF('Data Sheet'!B93>0,B12/'Data Sheet'!B93,0) -> 3.3146628 | C13: =IF('Data Sheet'!C93>0,C12/'Data Sheet'!C93,0) -> 8.9038007 | D13: =IF('Data Sheet'!D93>0,D12/'Data Sheet'!D93,0) -> 8.7111432 | E13: =IF('Data Sheet'!E93>0,E12/'Data Sheet'!E93,0) -> 3.7613872 | F13: =IF('Data Sheet'!F93>0,F12/'Data Sheet'!F93,0) -> 3.5282446 | G13: =IF('Data Sheet'!G93>0,G12/'Data Sheet'!G93,0) -> 5.4500673 | H13: =IF('Data Sheet'!H93>0,H12/'Data Sheet'!H93,0) -> 10.441711 | I13: =IF('Data Sheet'!I93>0,I12/'Data Sheet'!I93,0) -> 11.567771 | ... K13: =IF('Data Sheet'!K93>0,K12/'Data Sheet'!K93,0) -> 11.727193 | L13: =IF('Data Sheet'!$B6>0,'Profit & Loss'!L12/'Data Sheet'!$B6,0) -> 11.727048 | M13: =IF('Data Sheet'!$B6>0,'Profit & Loss'!M12/'Data Sheet'!$B6,0) -> 7.2037267 | N13: =IF('Data Sheet'!$B6>0,'Profit & Loss'!N12/'Data Sheet'!$B6,0) -> 2.4130533
A14: Price to earning | B14: =IF(B15>0,B15/B13,"") -> 27.257674 | C14: =IF(C15>0,C15/C13,"") -> 8.8726155 | D14: =IF(D15>0,D15/D13,"") -> 8.4719076 | E14: =IF(E15>0,E15/E13,"") -> 8.7334801 | F14: =IF(F15>0,F15/F13,"") -> 29.263844 | G14: =IF(G15>0,G15/G13,"") -> 43.78845 | H14: =IF(H15>0,H15/H13,"") -> 18.220194 | I14: =IF(I15>0,I15/I13,"") -> 34.077437 | ... K14: =IF(K15>0,K15/K13,"") -> 32.296731 | L14: =IF(L13>0,L15/L13,0) -> 34.309573 | M14: =M25 -> 34.309573 | N14: =N25 -> 25.045345
A15: Price | B15: ='Data Sheet'!B90 -> 90.35 | C15: ='Data Sheet'!C90 -> 79 | D15: ='Data Sheet'!D90 -> 73.8 | E15: ='Data Sheet'!E90 -> 32.85 | F15: ='Data Sheet'!F90 -> 103.25 | G15: ='Data Sheet'!G90 -> 238.65 | H15: ='Data Sheet'!H90 -> 190.25 | I15: ='Data Sheet'!I90 -> 394.2 | ... K15: ='Data Sheet'!K90 -> 378.75 | L15: ='Data Sheet'!B8 -> 402.35 | M15: =M13*M14 -> 247.15679 | N15: =N13*N14 -> 60.435752
A17: RATIOS:
A18: Dividend Payout | B18: =IF('Data Sheet'!B30>0, 'Data Sheet'!B31/'Data Sheet'!B30, 0) -> 0.39222575 | C18: =IF('Data Sheet'!C30>0, 'Data Sheet'!C31/'Data Sheet'!C30, 0) -> 0.14601586 | D18: =IF('Data Sheet'!D30>0, 'Data Sheet'!D31/'Data Sheet'!D30, 0) -> 0.14924518 | E18: =IF('Data Sheet'!E30>0, 'Data Sheet'!E31/'Data Sheet'!E30, 0) -> 0.4121174 | F18: =IF('Data Sheet'!F30>0, 'Data Sheet'!F31/'Data Sheet'!F30, 0) -> 0.43935496 | G18: =IF('Data Sheet'!G30>0, 'Data Sheet'!G31/'Data Sheet'!G30, 0) -> 0.3211271 | H18: =IF('Data Sheet'!H30>0, 'Data Sheet'!H31/'Data Sheet'!H30, 0) -> 0.19155747 | I18: =IF('Data Sheet'!I30>0, 'Data Sheet'!I31/'Data Sheet'!I30, 0) -> 0.17291038 | ... K18: =IF('Data Sheet'!K30>0, 'Data Sheet'!K31/'Data Sheet'!K30, 0) -> 0.21319976
A19: OPM | B19: =IF(B6>0,B6/B4,0) -> 0.19839609 | C19: =IF(C6>0,C6/C4,0) -> 0.18655364 | D19: =IF(D6>0,D6/D4,0) -> 0.21525374 | E19: =IF(E6>0,E6/E4,0) -> 0.23355929 | F19: =IF(F6>0,F6/F4,0) -> 0.2116269 | G19: =IF(G6>0,G6/G4,0) -> 0.16421301 | H19: =IF(H6>0,H6/H4,0) -> 0.14022662 | I19: =IF(I6>0,I6/I4,0) -> 0.17470256 | ... L19: =IF(L6>0,L6/L4,0) -> 0.20056868
G22: TRENDS: | H22: 10 YEARS | I22: 7 YEARS | J22: 5 YEARS | K22: 3 YEARS | L22: RECENT | M22: BEST | N22: WORST
G23: Sales Growth | H23: =IF(B4=0,"",POWER($K4/B4,1/9)-1) -> 0.094983945 | I23: =IF(D4=0,"",POWER($K4/D4,1/7)-1) -> 0.11099602 | J23: =IF(F4=0,"",POWER($K4/F4,1/5)-1) -> 0.13804219 | K23: =IF(H4=0,"",POWER($K4/H4, 1/3)-1) -> 0.042445731 | L23: =IF(ISERROR(MAX(IF(J4=0,"",(K4-J4)/J4),IF(K4=0,"",(L4-K4)/K4))),"",MAX(IF(J4=0,"",(K4-J4)/J4),IF(K4=0,"",(L4-K4)/K4))) -> 0 | M23: =MAX(K23:L23) -> 0.042445731 | N23: =MIN(H23:L23) -> 0
G24: OPM | H24: =IF(SUM(B4:$K$4)=0,"",SUMPRODUCT(B19:$K$19,B4:$K$4)/SUM(B4:$K$4)) -> 0.18819501 | I24: =IF(SUM(E4:$K$4)=0,"",SUMPRODUCT(E19:$K$19,E4:$K$4)/SUM(E4:$K$4)) -> 0.18519916 | J24: =IF(SUM(G4:$K$4)=0,"",SUMPRODUCT(G19:$K$19,G4:$K$4)/SUM(G4:$K$4)) -> 0.17728594 | K24: =IF(SUM(I4:$K$4)=0, "", SUMPRODUCT(I19:$K$19,I4:$K$4)/SUM(I4:$K$4)) -> 0.19102744 | L24: =L19 -> 0.20056868 | M24: =MAX(K24:L24) -> 0.20056868 | N24: =MIN(H24:L24) -> 0.17728594
G25: Price to Earning | H25: =IF(ISERROR(AVERAGEIF(B14:$L14,">0")),"",AVERAGEIF(B14:$L14,">0")) -> 25.045345 | I25: =IF(ISERROR(AVERAGEIF(E14:$L14,">0")),"",AVERAGEIF(E14:$L14,">0")) -> 28.862075 | J25: =IF(ISERROR(AVERAGEIF(G14:$L14,">0")),"",AVERAGEIF(G14:$L14,">0")) -> 32.149879 | K25: =IF(ISERROR(AVERAGEIF(I14:$L14,">0")),"",AVERAGEIF(I14:$L14,">0")) -> 32.722658 | L25: =L14 -> 34.309573 | M25: =MAX(K25:L25) -> 34.309573 | N25: =MIN(H25:L25) -> 25.045345

Sheet Quarters
A1: ='Profit & Loss'!A1 -> TATA POWER COMPANY LTD | E1: =UPDATE | J1: SCREENER.IN
A3: Narration | B3: ='Data Sheet'!B41 -> 45291 | C3: ='Data Sheet'!C41 -> 45382 | D3: ='Data Sheet'!D41 -> 45473 | E3: ='Data Sheet'!E41 -> 45565 | F3: ='Data Sheet'!F41 -> 45657 | G3: ='Data Sheet'!G41 -> 45747 | H3: ='Data Sheet'!H41 -> 45838 | I3: ='Data Sheet'!I41 -> 45930 | ... K3: ='Data Sheet'!K41 -> 46112
A4: Sales | B4: ='Data Sheet'!B42 -> 14651 | C4: ='Data Sheet'!C42 -> 15846.58 | D4: ='Data Sheet'!D42 -> 17293.62 | E4: ='Data Sheet'!E42 -> 15697.67 | F4: ='Data Sheet'!F42 -> 15391.06 | G4: ='Data Sheet'!G42 -> 17095.88 | H4: ='Data Sheet'!H42 -> 18035.07 | I4: ='Data Sheet'!I42 -> 15544.91 | ... K4: ='Data Sheet'!K42 -> 14900.2
A5: Expenses | B5: ='Data Sheet'!B43 -> 12233.58 | C5: ='Data Sheet'!C43 -> 13539.69 | D5: ='Data Sheet'!D43 -> 14231.87 | E5: ='Data Sheet'!E43 -> 12426.76 | F5: ='Data Sheet'!F43 -> 12312.03 | G5: ='Data Sheet'!G43 -> 13850.28 | H5: ='Data Sheet'!H43 -> 14469.9 | I5: ='Data Sheet'!I43 -> 12242.96 | ... K5: ='Data Sheet'!K43 -> 12301.01
A6: Operating Profit | B6: ='Data Sheet'!B50 -> 2417.42 | C6: ='Data Sheet'!C50 -> 2306.89 | D6: ='Data Sheet'!D50 -> 3061.75 | E6: ='Data Sheet'!E50 -> 3270.91 | F6: ='Data Sheet'!F50 -> 3079.03 | G6: ='Data Sheet'!G50 -> 3245.6 | H6: ='Data Sheet'!H50 -> 3565.17 | I6: ='Data Sheet'!I50 -> 3301.95 | ... K6: ='Data Sheet'!K50 -> 2599.19
A7: Other Income | B7: ='Data Sheet'!B44 -> 1091.87 | C7: ='Data Sheet'!C44 -> 1406.63 | D7: ='Data Sheet'!D44 -> 577.72 | E7: ='Data Sheet'!E44 -> 631.75 | F7: ='Data Sheet'!F44 -> 588.55 | G7: ='Data Sheet'!G44 -> 683.58 | H7: ='Data Sheet'!H44 -> 494.42 | I7: ='Data Sheet'!I44 -> 858.65 | ... K7: ='Data Sheet'!K44 -> 1773.3
A8: Depreciation | B8: ='Data Sheet'!B45 -> 926.27 | C8: ='Data Sheet'!C45 -> 1040.77 | D8: ='Data Sheet'!D45 -> 972.89 | E8: ='Data Sheet'!E45 -> 986.69 | F8: ='Data Sheet'!F45 -> 1040.99 | G8: ='Data Sheet'!G45 -> 1116.28 | H8: ='Data Sheet'!H45 -> 1160.91 | I8: ='Data Sheet'!I45 -> 1162.05 | ... K8: ='Data Sheet'!K45 -> 1280.23
A9: Interest | B9: ='Data Sheet'!B46 -> 1094.26 | C9: ='Data Sheet'!C46 -> 1135.72 | D9: ='Data Sheet'!D46 -> 1176.24 | E9: ='Data Sheet'!E46 -> 1143.1 | F9: ='Data Sheet'!F46 -> 1169.9 | G9: ='Data Sheet'!G46 -> 1213.21 | H9: ='Data Sheet'!H46 -> 1279.22 | I9: ='Data Sheet'!I46 -> 1318.65 | ... K9: ='Data Sheet'!K46 -> 1295.26
A10: Profit before tax | B10: ='Data Sheet'!B47 -> 1488.76 | C10: ='Data Sheet'!C47 -> 1537.03 | D10: ='Data Sheet'!D47 -> 1490.34 | E10: ='Data Sheet'!E47 -> 1772.87 | F10: ='Data Sheet'!F47 -> 1456.69 | G10: ='Data Sheet'!G47 -> 1599.69 | H10: ='Data Sheet'!H47 -> 1619.46 | I10: ='Data Sheet'!I47 -> 1679.9 | ... K10: ='Data Sheet'!K47 -> 1797
A11: Tax | B11: ='Data Sheet'!B48 -> 412.64 | C11: ='Data Sheet'!C48 -> 491.44 | D11: ='Data Sheet'!D48 -> 301.71 | E11: ='Data Sheet'!E48 -> 679.79 | F11: ='Data Sheet'!F48 -> 269.15 | G11: ='Data Sheet'!G48 -> 293.6 | H11: ='Data Sheet'!H48 -> 357.14 | I11: ='Data Sheet'!I48 -> 434.51 | ... K11: ='Data Sheet'!K48 -> 381.48
A12: Net profit | B12: ='Data Sheet'!B49 -> 953.01 | C12: ='Data Sheet'!C49 -> 895.21 | D12: ='Data Sheet'!D49 -> 970.91 | E12: ='Data Sheet'!E49 -> 926.53 | F12: ='Data Sheet'!F49 -> 1030.7 | G12: ='Data Sheet'!G49 -> 1042.83 | H12: ='Data Sheet'!H49 -> 1059.86 | I12: ='Data Sheet'!I49 -> 919.44 | ... K12: ='Data Sheet'!K49 -> 995.91
A14: OPM | B14: =IF(B4>0,B6/B4,"") -> 0.16500034 | C14: =IF(C4>0,C6/C4,"") -> 0.14557652 | D14: =IF(D4>0,D6/D4,"") -> 0.17704506 | E14: =IF(E4>0,E6/E4,"") -> 0.20836914 | F14: =IF(F4>0,F6/F4,"") -> 0.20005315 | G14: =IF(G4>0,G6/G4,"") -> 0.18984691 | H14: =IF(H4>0,H6/H4,"") -> 0.19767985 | I14: =IF(I4>0,I6/I4,"") -> 0.21241358 | ... K14: =IF(K4>0,K6/K4,"") -> 0.17443994

Sheet Balance Sheet
A1: ='Profit & Loss'!A1 -> TATA POWER COMPANY LTD | E1: =UPDATE | J1: SCREENER.IN
A3: Narration | B3: ='Data Sheet'!B56 -> 42825 | C3: ='Data Sheet'!C56 -> 43190 | D3: ='Data Sheet'!D56 -> 43555 | E3: ='Data Sheet'!E56 -> 43921 | F3: ='Data Sheet'!F56 -> 44286 | G3: ='Data Sheet'!G56 -> 44651 | H3: ='Data Sheet'!H56 -> 45016 | I3: ='Data Sheet'!I56 -> 45382 | ... K3: ='Data Sheet'!K56 -> 46112
A4: Equity Share Capital | B4: ='Data Sheet'!B57 -> 270.5 | C4: ='Data Sheet'!C57 -> 270.5 | D4: ='Data Sheet'!D57 -> 270.5 | E4: ='Data Sheet'!E57 -> 270.5 | F4: ='Data Sheet'!F57 -> 319.56 | G4: ='Data Sheet'!G57 -> 319.56 | H4: ='Data Sheet'!H57 -> 319.56 | I4: ='Data Sheet'!I57 -> 319.56 | ... K4: ='Data Sheet'!K57 -> 319.56
A5: Reserves | B5: ='Data Sheet'!B58 -> 12944.05 | C5: ='Data Sheet'!C58 -> 16129.38 | D5: ='Data Sheet'!D58 -> 18035.01 | E5: ='Data Sheet'!E58 -> 19295.52 | F5: ='Data Sheet'!F58 -> 22002.7 | G5: ='Data Sheet'!G58 -> 22122 | H5: ='Data Sheet'!H58 -> 28467.87 | I5: ='Data Sheet'!I58 -> 32035.73 | ... K5: ='Data Sheet'!K58 -> 39147.65
A6: Borrowings | B6: ='Data Sheet'!B59 -> 48815.41 | C6: ='Data Sheet'!C59 -> 48589.24 | D6: ='Data Sheet'!D59 -> 48506.04 | E6: ='Data Sheet'!E59 -> 51936.15 | F6: ='Data Sheet'!F59 -> 46707.95 | G6: ='Data Sheet'!G59 -> 51195.12 | H6: ='Data Sheet'!H59 -> 52923 | I6: ='Data Sheet'!I59 -> 53689.45 | ... K6: ='Data Sheet'!K59 -> 76141.27
A7: Other Liabilities | B7: ='Data Sheet'!B60 -> 20799.3 | C7: ='Data Sheet'!C60 -> 16902.68 | D7: ='Data Sheet'!D60 -> 17261.89 | E7: ='Data Sheet'!E60 -> 18171.74 | F7: ='Data Sheet'!F60 -> 29624.63 | G7: ='Data Sheet'!G60 -> 38913.31 | H7: ='Data Sheet'!H60 -> 46385.71 | I7: ='Data Sheet'!I60 -> 53009.66 | ... K7: ='Data Sheet'!K60 -> 58955.76
A8: Total | B8: ='Data Sheet'!B61 -> 82829.26 | C8: ='Data Sheet'!C61 -> 81891.8 | D8: ='Data Sheet'!D61 -> 84073.44 | E8: ='Data Sheet'!E61 -> 89673.91 | F8: ='Data Sheet'!F61 -> 98654.84 | G8: ='Data Sheet'!G61 -> 112549.99 | H8: ='Data Sheet'!H61 -> 128096.14 | I8: ='Data Sheet'!I61 -> 139054.4 | ... K8: ='Data Sheet'!K61 -> 174564.24
A10: Net Block | B10: ='Data Sheet'!B62 -> 46594.79 | C10: ='Data Sheet'!C62 -> 44656.26 | D10: ='Data Sheet'!D62 -> 44304.89 | E10: ='Data Sheet'!E62 -> 47666.36 | F10: ='Data Sheet'!F62 -> 52179.15 | G10: ='Data Sheet'!G62 -> 57389.44 | H10: ='Data Sheet'!H62 -> 61746.66 | I10: ='Data Sheet'!I62 -> 67209.56 | ... K10: ='Data Sheet'!K62 -> 87292.69
A11: Capital Work in Progress | B11: ='Data Sheet'!B63 -> 2177.92 | C11: ='Data Sheet'!C63 -> 1652.6 | D11: ='Data Sheet'!D63 -> 2575.7 | E11: ='Data Sheet'!E63 -> 1611.52 | F11: ='Data Sheet'!F63 -> 3270.26 | G11: ='Data Sheet'!G63 -> 4635.1 | H11: ='Data Sheet'!H63 -> 5376.36 | I11: ='Data Sheet'!I63 -> 11561.31 | ... K11: ='Data Sheet'!K63 -> 14595.13
A12: Investments | B12: ='Data Sheet'!B64 -> 11873.01 | C12: ='Data Sheet'!C64 -> 12428.93 | D12: ='Data Sheet'!D64 -> 13541.87 | E12: ='Data Sheet'!E64 -> 14534.84 | F12: ='Data Sheet'!F64 -> 13149.05 | G12: ='Data Sheet'!G64 -> 14160.33 | H12: ='Data Sheet'!H64 -> 16669.69 | I12: ='Data Sheet'!I64 -> 16315.99 | ... K12: ='Data Sheet'!K64 -> 16574.54
A13: Other Assets | B13: ='Data Sheet'!B65 -> 22183.54 | C13: ='Data Sheet'!C65 -> 23154.01 | D13: ='Data Sheet'!D65 -> 23650.98 | E13: ='Data Sheet'!E65 -> 25861.19 | F13: ='Data Sheet'!F65 -> 30056.38 | G13: ='Data Sheet'!G65 -> 36365.12 | H13: ='Data Sheet'!H65 -> 44303.43 | I13: ='Data Sheet'!I65 -> 43967.54 | ... K13: ='Data Sheet'!K65 -> 56101.88
A14: Total | B14: ='Data Sheet'!B66 -> 82829.26 | C14: ='Data Sheet'!C66 -> 81891.8 | D14: ='Data Sheet'!D66 -> 84073.44 | E14: ='Data Sheet'!E66 -> 89673.91 | F14: ='Data Sheet'!F66 -> 98654.84 | G14: ='Data Sheet'!G66 -> 112549.99 | H14: ='Data Sheet'!H66 -> 128096.14 | I14: ='Data Sheet'!I66 -> 139054.4 | ... K14: ='Data Sheet'!K66 -> 174564.24
A16: Working Capital | B16: =B13-B7 -> 1384.24 | C16: =C13-C7 -> 6251.33 | D16: =D13-D7 -> 6389.09 | E16: =E13-E7 -> 7689.45 | F16: =F13-F7 -> 431.75 | G16: =G13-G7 -> -2548.19 | H16: =H13-H7 -> -2082.28 | I16: =I13-I7 -> -9042.12 | ... K16: =K13-K7 -> -2853.88
A17: Debtors | B17: ='Data Sheet'!B67 -> 3832.12 | C17: ='Data Sheet'!C67 -> 2788.93 | D17: ='Data Sheet'!D67 -> 4445.26 | E17: ='Data Sheet'!E67 -> 4425.9 | F17: ='Data Sheet'!F67 -> 5200.08 | G17: ='Data Sheet'!G67 -> 5979.74 | H17: ='Data Sheet'!H67 -> 6952.15 | I17: ='Data Sheet'!I67 -> 7401.69 | ... K17: ='Data Sheet'!K67 -> 4423.96
A18: Inventory | B18: ='Data Sheet'!B68 -> 1599.56 | C18: ='Data Sheet'!C68 -> 1623.08 | D18: ='Data Sheet'!D68 -> 1706.42 | E18: ='Data Sheet'!E68 -> 1752.35 | F18: ='Data Sheet'!F68 -> 1885.62 | G18: ='Data Sheet'!G68 -> 4231.52 | H18: ='Data Sheet'!H68 -> 3942.88 | I18: ='Data Sheet'!I68 -> 4419.63 | ... K18: ='Data Sheet'!K68 -> 5107.64
A20: Debtor Days | B20: =IF('Profit & Loss'!B4>0,'Balance Sheet'!B17/('Profit & Loss'!B4/365),0) -> 50.701196 | C20: =IF('Profit & Loss'!C4>0,'Balance Sheet'!C17/('Profit & Loss'!C4/365),0) -> 37.926573 | D20: =IF('Profit & Loss'!D4>0,'Balance Sheet'!D17/('Profit & Loss'!D4/365),0) -> 54.299275 | E20: =IF('Profit & Loss'!E4>0,'Balance Sheet'!E17/('Profit & Loss'!E4/365),0) -> 55.44457 | F20: =IF('Profit & Loss'!F4>0,'Balance Sheet'!F17/('Profit & Loss'!F4/365),0) -> 58.037832 | G20: =IF('Profit & Loss'!G4>0,'Balance Sheet'!G17/('Profit & Loss'!G4/365),0) -> 50.976783 | H20: =IF('Profit & Loss'!H4>0,'Balance Sheet'!H17/('Profit & Loss'!H4/365),0) -> 46.045674 | I20: =IF('Profit & Loss'!I4>0,'Balance Sheet'!I17/('Profit & Loss'!I4/365),0) -> 43.96526 | ... K20: =IF('Profit & Loss'!K4>0,'Balance Sheet'!K17/('Profit & Loss'!K4/365),0) -> 25.865479
A21: Inventory Turnover | B21: =IF('Balance Sheet'!B18>0,'Profit & Loss'!B4/'Balance Sheet'!B18,0) -> 17.246987 | C21: =IF('Balance Sheet'!C18>0,'Profit & Loss'!C4/'Balance Sheet'!C18,0) -> 16.536628 | D21: =IF('Balance Sheet'!D18>0,'Profit & Loss'!D4/'Balance Sheet'!D18,0) -> 17.510964 | E21: =IF('Balance Sheet'!E18>0,'Profit & Loss'!E4/'Balance Sheet'!E18,0) -> 16.627027 | F21: =IF('Balance Sheet'!F18>0,'Profit & Loss'!F4/'Balance Sheet'!F18,0) -> 17.343532 | G21: =IF('Balance Sheet'!G18>0,'Profit & Loss'!G4/'Balance Sheet'!G18,0) -> 10.118272 | H21: =IF('Balance Sheet'!H18>0,'Profit & Loss'!H4/'Balance Sheet'!H18,0) -> 13.97686 | I21: =IF('Balance Sheet'!I18>0,'Profit & Loss'!I4/'Balance Sheet'!I18,0) -> 13.90363 | ... K21: =IF('Balance Sheet'!K18>0,'Profit & Loss'!K4/'Balance Sheet'!K18,0) -> 12.22259
A23: Return on Equity | B23: =IF(SUM('Balance Sheet'!B4:B5)>0,'Profit & Loss'!B12/SUM('Balance Sheet'!B4:B5),"") -> 0.06784567 | C23: =IF(SUM('Balance Sheet'!C4:C5)>0,'Profit & Loss'!C12/SUM('Balance Sheet'!C4:C5),"") -> 0.14684864 | D23: =IF(SUM('Balance Sheet'!D4:D5)>0,'Profit & Loss'!D12/SUM('Balance Sheet'!D4:D5),"") -> 0.1287148 | E23: =IF(SUM('Balance Sheet'!E4:E5)>0,'Profit & Loss'!E12/SUM('Balance Sheet'!E4:E5),"") -> 0.051997289 | F23: =IF(SUM('Balance Sheet'!F4:F5)>0,'Profit & Loss'!F12/SUM('Balance Sheet'!F4:F5),"") -> 0.050504743 | G23: =IF(SUM('Balance Sheet'!G4:G5)>0,'Profit & Loss'!G12/SUM('Balance Sheet'!G4:G5),"") -> 0.077599775 | H23: =IF(SUM('Balance Sheet'!H4:H5)>0,'Profit & Loss'!H12/SUM('Balance Sheet'!H4:H5),"") -> 0.1158992 | I23: =IF(SUM('Balance Sheet'!I4:I5)>0,'Profit & Loss'!I12/SUM('Balance Sheet'!I4:I5),"") -> 0.11423943 | ... K23: =IF(SUM('Balance Sheet'!K4:K5)>0,'Profit & Loss'!K12/SUM('Balance Sheet'!K4:K5),"") -> 0.094944385
A24: Return on Capital Emp | C24: =IF((B4+B5+B6+C4+C5+C6)>0,('Profit & Loss'!C10+'Profit & Loss'!C9)*2/(B4+B5+B6+C4+C5+C6),"") -> 0.1028869 | D24: =IF((C4+C5+C6+D4+D5+D6)>0,('Profit & Loss'!D10+'Profit & Loss'!D9)*2/(C4+C5+C6+D4+D5+D6),"") -> 0.11932033 | E24: =IF((D4+D5+D6+E4+E5+E6)>0,('Profit & Loss'!E10+'Profit & Loss'!E9)*2/(D4+D5+D6+E4+E5+E6),"") -> 0.093290239 | F24: =IF((E4+E5+E6+F4+F5+F6)>0,('Profit & Loss'!F10+'Profit & Loss'!F9)*2/(E4+E5+E6+F4+F5+F6),"") -> 0.084691087 | G24: =IF((F4+F5+F6+G4+G5+G6)>0,('Profit & Loss'!G10+'Profit & Loss'!G9)*2/(F4+F5+F6+G4+G5+G6),"") -> 0.089638037 | H24: =IF((G4+G5+G6+H4+H5+H6)>0,('Profit & Loss'!H10+'Profit & Loss'!H9)*2/(G4+G5+G6+H4+H5+H6),"") -> 0.12653792 | I24: =IF((H4+H5+H6+I4+I5+I6)>0,('Profit & Loss'!I10+'Profit & Loss'!I9)*2/(H4+H5+H6+I4+I5+I6),"") -> 0.1235758 | J24: =IF((I4+I5+I6+J4+J5+J6)>0,('Profit & Loss'!J10+'Profit & Loss'!J9)*2/(I4+I5+I6+J4+J5+J6),"") -> 0.11931787 | K24: =IF((J4+J5+J6+K4+K5+K6)>0,('Profit & Loss'!K10+'Profit & Loss'!K9)*2/(J4+J5+J6+K4+K5+K6),"") -> 0.11098414

Sheet Cash Flow
A1: ='Balance Sheet'!A1 -> TATA POWER COMPANY LTD | E1: =UPDATE | J1: SCREENER.IN
A3: Narration | B3: ='Data Sheet'!B81 -> 42825 | C3: ='Data Sheet'!C81 -> 43190 | D3: ='Data Sheet'!D81 -> 43555 | E3: ='Data Sheet'!E81 -> 43921 | F3: ='Data Sheet'!F81 -> 44286 | G3: ='Data Sheet'!G81 -> 44651 | H3: ='Data Sheet'!H81 -> 45016 | I3: ='Data Sheet'!I81 -> 45382 | ... K3: ='Data Sheet'!K81 -> 46112
A4: Cash from Operating Activity | B4: ='Data Sheet'!B82 -> 7014.18 | C4: ='Data Sheet'!C82 -> 6363.85 | D4: ='Data Sheet'!D82 -> 4573.79 | E4: ='Data Sheet'!E82 -> 7375.32 | F4: ='Data Sheet'!F82 -> 8345.12 | G4: ='Data Sheet'!G82 -> 6692.73 | H4: ='Data Sheet'!H82 -> 7165.59 | I4: ='Data Sheet'!I82 -> 12504.37 | ... K4: ='Data Sheet'!K82 -> 5993.33
A5: Cash from Investing Activity | B5: ='Data Sheet'!B83 -> -7372.73 | C5: ='Data Sheet'!C83 -> -1511.65 | D5: ='Data Sheet'!D83 -> -272.34 | E5: ='Data Sheet'!E83 -> -492.88 | F5: ='Data Sheet'!F83 -> 993.33 | G5: ='Data Sheet'!G83 -> -6250.47 | H5: ='Data Sheet'!H83 -> -7263.1 | I5: ='Data Sheet'!I83 -> -8935.37 | ... K5: ='Data Sheet'!K83 -> -14128.65
A6: Cash from Financing Activity | B6: ='Data Sheet'!B84 -> 937.34 | C6: ='Data Sheet'!C84 -> -4726.26 | D6: ='Data Sheet'!D84 -> -5184.45 | E6: ='Data Sheet'!E84 -> -5109.57 | F6: ='Data Sheet'!F84 -> -7602.88 | G6: ='Data Sheet'!G84 -> -1183.2 | H6: ='Data Sheet'!H84 -> 1340.77 | I6: ='Data Sheet'!I84 -> -4497.43 | ... K6: ='Data Sheet'!K84 -> 7782.63
A7: Net Cash Flow | B7: ='Data Sheet'!B85 -> 578.79 | C7: ='Data Sheet'!C85 -> 125.94 | D7: ='Data Sheet'!D85 -> -883 | E7: ='Data Sheet'!E85 -> 1772.87 | F7: ='Data Sheet'!F85 -> 1735.57 | G7: ='Data Sheet'!G85 -> -740.94 | H7: ='Data Sheet'!H85 -> 1243.26 | I7: ='Data Sheet'!I85 -> -928.43 | ... K7: ='Data Sheet'!K85 -> -352.69

Sheet Customization
A1: How to use it?
A3: You can customize this workbook as you want.
B4: You can add custom formating, add conditional formating, add your own formulas… do ANYTHING.
B5: Please don't edit the "Data Sheet" only.
A7: After customization, you can upload this back on Screener.
B8: Upload on: | C8: https://www.screener.in/excel/
A10: Download your customized workbooks now onwards.
B11: Now whenever you will "Export to excel" from Screener, it will export your customized file.
A14: TESTING:
B15: This is a testing feature currently.
B16: You can report any formula errors on the worksheet at: support@screener.in

Sheet Data Sheet
A1: COMPANY NAME | B1: TATA POWER COMPANY LTD | E1: =IF(B2<>B3, "A NEW VERSION OF THE WORKSHEET IS AVAILABLE", "")
A2: LATEST VERSION | B2: 2.1 | E2: PLEASE DO NOT MAKE ANY CHANGES TO THIS SHEET
A3: CURRENT VERSION | B3: 2.1
A5: META
A6: Number of shares | B6: =IF(B9>0, B9/B8, 0) -> 319.53396
A7: Face Value | B7: 1
A8: Current Price | B8: 402.35
A9: Market Capitalization | B9: 128564.49
A15: PROFIT & LOSS
A16: Report Date | B16: 42825 | C16: 43190 | D16: 43555 | E16: 43921 | F16: 44286 | G16: 44651 | H16: 45016 | I16: 45382 | J16: 45747 | K16: 46112
A17: Sales | B17: 27587.59 | C17: 26840.27 | D17: 29881.06 | E17: 29136.37 | F17: 32703.31 | G17: 42815.67 | H17: 55109.08 | I17: 61448.9 | J17: 65478.24 | K17: 62428.59
A18: Raw Material Cost
A19: Change in Inventory | B19: -28.34 | C19: 8.51 | D19: -24.37 | E19: 15.64 | F19: -0.41 | G19: 199.22 | H19: -43.53 | I19: 51.78 | J19: 440.76 | K19: 84.11
A20: Power and Fuel | B20: 17921.05 | C20: 16356.15 | D20: 18918.9 | E20: 17100.03 | F20: 20037.56 | G20: 26764.37 | H20: 36708.56 | I20: 39584.79 | J20: 39363.54 | K20: 35764.04
A21: Other Mfr. Exp | B21: 1720.75 | C21: 2041.68 | D21: 2056.1 | E21: 2013.68 | F21: 2533.43 | G21: 3942.93 | H21: 5007.21 | I21: 5272.77 | J21: 6306.19 | K21: 6743.03
A22: Employee Cost | B22: 1342.92 | C22: 1475 | D22: 1497.6 | E22: 1541.05 | F22: 2414.24 | G22: 3731.29 | H22: 3801.4 | I22: 4264.99 | J22: 4649.25 | K22: 5099.95
A23: Selling and admin | B23: 481.89 | C23: 511.78 | D23: 466.39 | E23: 401.51 | F23: 523.94 | G23: 730.58 | H23: 1016.41 | I23: 1017.98 | J23: 1055.18 | K23: 1213.37
A24: Other Expenses | B24: 619.37 | C24: 1457.02 | D24: 485.69 | E24: 1290.67 | F24: 272.83 | G24: 814.83 | H24: 804.21 | I24: 624.87 | J24: 2379.25 | K24: 421.04
A25: Other Income | B25: 1297.37 | C25: 3873.32 | D25: 3824.37 | E25: 2280.15 | F25: 1774.96 | G25: 2485.5 | H25: 5540.09 | I25: 3416.33 | J25: 2973.33 | K25: 3432.6
A26: Depreciation | B26: 1955.59 | C26: 2346.17 | D26: 2393.13 | E26: 2633.56 | F26: 2744.94 | G26: 3122.2 | H26: 3439.2 | I26: 3786.37 | J26: 4116.86 | K26: 4811.09
A27: Interest | B27: 3364.96 | C27: 3761.48 | D27: 4170 | E27: 4493.73 | F27: 4010.39 | G27: 3859.02 | H27: 4371.65 | I27: 4633.22 | J27: 4702.44 | K27: 5256.79
A28: Profit before tax | B28: 1450.09 | C28: 2772.82 | D28: 3693.25 | E28: 1957.93 | F28: 1940.53 | G28: 2535.17 | H28: 5457 | I28: 5732.02 | J28: 6319.62 | K28: 6635.99
A29: Tax | B29: 350.46 | C29: 161.97 | D29: 1087.59 | E29: 641.49 | F29: 501.88 | G29: 379.56 | H29: 1647.33 | I29: 1451.92 | J29: 1544.25 | K29: 1518.43
A30: Net profit | B30: 896.55 | C30: 2408.3 | D30: 2356.19 | E30: 1017.38 | F30: 1127.38 | G30: 1741.46 | H30: 3336.44 | I30: 3696.25 | J30: 3971 | K30: 3747.19
A31: Dividend Amount | B31: 351.65 | C31: 351.65 | D31: 351.65 | E31: 419.28 | F31: 495.32 | G31: 559.23 | H31: 639.12 | I31: 639.12 | J31: 719.01 | K31: 798.9
A40: Quarters
A41: Report Date | B41: 45291 | C41: 45382 | D41: 45473 | E41: 45565 | F41: 45657 | G41: 45747 | H41: 45838 | I41: 45930 | J41: 46022 | K41: 46112
A42: Sales | B42: 14651 | C42: 15846.58 | D42: 17293.62 | E42: 15697.67 | F42: 15391.06 | G42: 17095.88 | H42: 18035.07 | I42: 15544.91 | J42: 13948.41 | K42: 14900.2
A43: Expenses | B43: 12233.58 | C43: 13539.69 | D43: 14231.87 | E43: 12426.76 | F43: 12312.03 | G43: 13850.28 | H43: 14469.9 | I43: 12242.96 | J43: 10893.5 | K43: 12301.01
A44: Other Income | B44: 1091.87 | C44: 1406.63 | D44: 577.72 | E44: 631.75 | F44: 588.55 | G44: 683.58 | H44: 494.42 | I44: 858.65 | J44: 1056.28 | K44: 1773.3
A45: Depreciation | B45: 926.27 | C45: 1040.77 | D45: 972.89 | E45: 986.69 | F45: 1040.99 | G45: 1116.28 | H45: 1160.91 | I45: 1162.05 | J45: 1207.9 | K45: 1280.23
A46: Interest | B46: 1094.26 | C46: 1135.72 | D46: 1176.24 | E46: 1143.1 | F46: 1169.9 | G46: 1213.21 | H46: 1279.22 | I46: 1318.65 | J46: 1363.66 | K46: 1295.26
A47: Profit before tax | B47: 1488.76 | C47: 1537.03 | D47: 1490.34 | E47: 1772.87 | F47: 1456.69 | G47: 1599.69 | H47: 1619.46 | I47: 1679.9 | J47: 1539.63 | K47: 1797
A48: Tax | B48: 412.64 | C48: 491.44 | D48: 301.71 | E48: 679.79 | F48: 269.15 | G48: 293.6 | H48: 357.14 | I48: 434.51 | J48: 345.3 | K48: 381.48
A49: Net profit | B49: 953.01 | C49: 895.21 | D49: 970.91 | E49: 926.53 | F49: 1030.7 | G49: 1042.83 | H49: 1059.86 | I49: 919.44 | J49: 771.98 | K49: 995.91
A50: Operating Profit | B50: 2417.42 | C50: 2306.89 | D50: 3061.75 | E50: 3270.91 | F50: 3079.03 | G50: 3245.6 | H50: 3565.17 | I50: 3301.95 | J50: 3054.91 | K50: 2599.19
A55: BALANCE SHEET
A56: Report Date | B56: 42825 | C56: 43190 | D56: 43555 | E56: 43921 | F56: 44286 | G56: 44651 | H56: 45016 | I56: 45382 | J56: 45747 | K56: 46112
A57: Equity Share Capital | B57: 270.5 | C57: 270.5 | D57: 270.5 | E57: 270.5 | F57: 319.56 | G57: 319.56 | H57: 319.56 | I57: 319.56 | J57: 319.56 | K57: 319.56
A58: Reserves | B58: 12944.05 | C58: 16129.38 | D58: 18035.01 | E58: 19295.52 | F58: 22002.7 | G58: 22122 | H58: 28467.87 | I58: 32035.73 | J58: 35521.11 | K58: 39147.65
A59: Borrowings | B59: 48815.41 | C59: 48589.24 | D59: 48506.04 | E59: 51936.15 | F59: 46707.95 | G59: 51195.12 | H59: 52923 | I59: 53689.45 | J59: 62865.8 | K59: 76141.27
A60: Other Liabilities | B60: 20799.3 | C60: 16902.68 | D60: 17261.89 | E60: 18171.74 | F60: 29624.63 | G60: 38913.31 | H60: 46385.71 | I60: 53009.66 | J60: 57486.83 | K60: 58955.76
A61: Total | B61: 82829.26 | C61: 81891.8 | D61: 84073.44 | E61: 89673.91 | F61: 98654.84 | G61: 112549.99 | H61: 128096.14 | I61: 139054.4 | J61: 156193.3 | K61: 174564.24
A62: Net Block | B62: 46594.79 | C62: 44656.26 | D62: 44304.89 | E62: 47666.36 | F62: 52179.15 | G62: 57389.44 | H62: 61746.66 | I62: 67209.56 | J62: 78374.43 | K62: 87292.69
A63: Capital Work in Progress | B63: 2177.92 | C63: 1652.6 | D63: 2575.7 | E63: 1611.52 | F63: 3270.26 | G63: 4635.1 | H63: 5376.36 | I63: 11561.31 | J63: 12678.87 | K63: 14595.13
A64: Investments | B64: 11873.01 | C64: 12428.93 | D64: 13541.87 | E64: 14534.84 | F64: 13149.05 | G64: 14160.33 | H64: 16669.69 | I64: 16315.99 | J64: 16316.39 | K64: 16574.54
A65: Other Assets | B65: 22183.54 | C65: 23154.01 | D65: 23650.98 | E65: 25861.19 | F65: 30056.38 | G65: 36365.12 | H65: 44303.43 | I65: 43967.54 | J65: 48823.61 | K65: 56101.88
A66: Total | B66: 82829.26 | C66: 81891.8 | D66: 84073.44 | E66: 89673.91 | F66: 98654.84 | G66: 112549.99 | H66: 128096.14 | I66: 139054.4 | J66: 156193.3 | K66: 174564.24
A67: Receivables | B67: 3832.12 | C67: 2788.93 | D67: 4445.26 | E67: 4425.9 | F67: 5200.08 | G67: 5979.74 | H67: 6952.15 | I67: 7401.69 | J67: 5709.78 | K67: 4423.96
... A70: No. of Equity Shares | B70: 2706281698 | C70: 2706425810 | D70: 2706425810 | E70: 2706425810 | F70: 3196991847 | G70: 3196991847 | H70: 3196991847 | I70: 3196991847 | J70: 3196991847 | K70: 3196991847
A71: New Bonus Shares
A72: Face value | B72: 1 | C72: 1 | D72: 1 | E72: 1 | F72: 1 | G72: 1 | H72: 1 | I72: 1 | J72: 1 | K72: 1
A80: CASH FLOW:
A81: Report Date | B81: 42825 | C81: 43190 | D81: 43555 | E81: 43921 | F81: 44286 | G81: 44651 | H81: 45016 | I81: 45382 | J81: 45747 | K81: 46112
A82: Cash from Operating Activity | B82: 7014.18 | C82: 6363.85 | D82: 4573.79 | E82: 7375.32 | F82: 8345.12 | G82: 6692.73 | H82: 7165.59 | I82: 12504.37 | J82: 12680.19 | K82: 5993.33
A83: Cash from Investing Activity | B83: -7372.73 | C83: -1511.65 | D83: -272.34 | E83: -492.88 | F83: 993.33 | G83: -6250.47 | H83: -7263.1 | I83: -8935.37 | J83: -15436.29 | K83: -14128.65
A84: Cash from Financing Activity | B84: 937.34 | C84: -4726.26 | D84: -5184.45 | E84: -5109.57 | F84: -7602.88 | G84: -1183.2 | H84: 1340.77 | I84: -4497.43 | J84: 4292.39 | K84: 7782.63
A85: Net Cash Flow | B85: 578.79 | C85: 125.94 | D85: -883 | E85: 1772.87 | F85: 1735.57 | G85: -740.94 | H85: 1243.26 | I85: -928.43 | J85: 1536.29 | K85: -352.69
A90: PRICE: | B90: 90.35 | C90: 79 | D90: 73.8 | E90: 32.85 | F90: 103.25 | G90: 238.65 | H90: 190.25 | I90: 394.2 | J90: 375.4 | K90: 378.75
A92: DERIVED:
A93: Adjusted Equity Shares in Cr | B93: 270.48 | C93: 270.48 | D93: 270.48 | E93: 270.48 | F93: 319.53 | G93: 319.53 | H93: 319.53 | I93: 319.53 | J93: 319.53 | K93: 319.53

Sheet Peer Company Database
B2: COMPANY_NAME | C2: BSE | D2: NSE | E2: Industry
B3: 20 MICRONS LTD | C3: 533022 | D3: 20MICRONS | E3: Mining
B4: 21ST CENTURY MANAGEMENT SERVICES LTD | C4: 526921 | D4: 21STCENMGM | E4: Other Financial Services
B5: 3I INFOTECH LTD | C5: 532628 | D5: 3IINFOTECH | E5: IT Consulting & Software
B6: 3M (INDIA) LTD | C6: 523395 | D6: 3M(INDIA) | E6: Diversified
B7: 3M INDIA LTD | C7: 523395 | D7: 3MINDIA | E7: Diversified
B8: 3P LAND HOLDINGS LTD | C8: 516092 | D8: 3PLAND | E8: Paper & Paper Products
B9: 5PAISA CAPITAL LTD | C9: 540776 | D9: 5PAISA | E9: Other Financial Services
B10: 63 MOONS TECHNOLOGIES LTD | C10: 526881 | D10: 63MOONS | E10: IT Consulting & Software
B11: 7NR RETAIL LTD | C11: 540615 | D11: Not Listed | E11: Specialty Retail
B12: 7SEAS ENTERTAINMENT LTD | C12: 540874 | D12: Not Listed | E12: Movies & Entertainment
B13: 8K MILES SOFTWARE SERVICES LTD | C13: 512161 | D13: 8KMILES | E13: Internet Software & Services
B14: A & M FEBCON LTD | C14: 540697 | D14: Not Listed | E14: Industrial Machinery
B15: A AND M JUMBO BAGS LTD | C15: Not Listed | D15: AMJUMBO | E15: SME
B16: A INFRASTRUCTURE LTD | C16: 539620 | D16: Not Listed | E16: Cement & Cement Products
B17: A K SPINTEX LTD | C17: 539300 | D17: Not Listed | E17: Textiles
B18: A K CAPITAL SERVICES LTD | C18: 530499 | D18: Not Listed | E18: Finance (including NBFCs)
B19: A.F. Enterprises Ltd | C19: 538351 | D19: AFEL | E19: Investment Companies
B20: A-1 ACID LTD | C20: 542012 | D20: Not Listed | E20: Comm.Trading & Distribution
B21: A2Z INFRA ENGINEERING LTD | C21: 533292 | D21: A2ZINFRA | E21: Utilities:Non-Elec.
B22: AADHAAR VENTURES (INDIA) LTD | C22: 531611 | D22: Not Listed | E22: Finance (including NBFCs)
B23: AADHAAR VENTURES INDIA LTD | C23: 531611 | D23: Not Listed | E23: Finance (including NBFCs)
B24: AAKASH EXPLORATION SERVICES LTD | C24: Not Listed | D24: AAKASH | E24: SME
B25: AANANDA LAKSHMI SPINNING MILLS LTD | C25: 539096 | D25: Not Listed | E25: Textiles
B26: AANCHAL ISPAT LTD | C26: 538812 | D26: Not Listed | E26: Iron & Steel/Interm.Products
B27: AAR COMMERCIAL COMPANY LTD | C27: 539632 | D27: Not Listed | E27: Distributors
B28: Aar Shyam India Investment Company Ltd | C28: 542377 | D28: AARSHYAM | E28: Finance (including NBFCs)
B29: AAREY DRUGS & PHARMACEUTICALS LTD | C29: 524412 | D29: Not Listed | E29: Pharmaceuticals
B30: AARON INDUSTRIES LTD | C30: Not Listed | D30: AARON | E30: SME
B31: Aartech Solonics Ltd | C31: 542580 | D31: AARTECH | E31: Heavy Electrical Equipment
B32: AARTI DRUGS LTD | C32: 524348 | D32: AARTIDRUGS | E32: Pharmaceuticals
B33: AARTI INDUSTRIES LTD | C33: 524208 | D33: AARTIIND | E33: Commodity Chemicals
B34: AARV INFRATEL LTD | C34: 526488 | D34: Not Listed | E34: Textiles
B35: AARVEE DENIMS & EXPORTS LTD | C35: 514274 | D35: AARVEEDEN | E35: Textiles
B36: AARVI ENCON LTD | C36: Not Listed | D36: AARVI | E36: SME
B37: AASHEE INFOTECH LTD | C37: 519319 | D37: Not Listed | E37: Internet Software & Services
B38: AASWA TRADING & EXPORTS LTD | C38: 512038 | D38: Not Listed | E38: Comm.Trading & Distribution
B39: AAVAS FINANCIERS LTD | C39: 541988 | D39: AAVAS | E39: Housing Finance
B40: AAYUSH FOOD AND HERBS LTD | C40: 539528 | D40: Not Listed | E40: Packaged Foods
B41: ABAN OFFSHORE LTD | C41: 523204 | D41: ABAN | E41: Exploration & Production
B42: ABANS ENTERPRISES LTD | C42: 512165 | D42: Not Listed | E42: Comm.Trading & Distribution
B43: ABB INDIA LTD | C43: 500002 | D43: ABB | E43: Heavy Electrical Equipment
B44: ABBOTT (INDIA) LTD | C44: 500488 | D44: ABBOT(INDIA) | E44: Pharmaceuticals
B45: ABBOTT INDIA LTD | C45: 500488 | D45: ABBOTINDIA | E45: Pharmaceuticals
B46: ABC (INDIA) LTD | C46: 520123 | D46: Not Listed | E46: Surface Transportation
B47: ABC GAS INTERNATIONAL LTD | C47: 513119 | D47: Not Listed | E47: Copper
B48: ABC INDIA LTD | C48: 520123 | D48: Not Listed | E48: Surface Transportation
... B56: ABIRAMI FINANCIAL SERVICES INDIA LTD | C56: 511756 | D56: Not Listed | E56: Finance (including NBFCs)
B57: ABM INTERNATIONAL LTD | C57: Not Listed | D57: ABMINTLTD | E57: Others
B58: ABM KNOWLEDGEWARE LTD | C58: 531161 | D58: Not Listed | E58: IT Software Products
B59: ACC LTD | C59: 500410 | D59: ACC | E59: Cement & Cement Products
B60: ACCEL LTD | C60: 517494 | D60: Not Listed | E60: Storage Media & Peripherals
B61: ACCELYA KALE SOLUTIONS LTD | C61: 532268 | D61: ACCELYA | E61: IT Consulting & Software
B62: ACCORD SYNERGY LTD | C62: Not Listed | D62: ACCORD | E62: SME
B63: ACCURACY SHIPPING LTD | C63: Not Listed | D63: ACCURACY | E63: SME
B64: ACE EDUTREND LTD | C64: 530093 | D64: Not Listed | E64: Education
B65: ACE INTEGRATED SOLUTIONS LTD | C65: Not Listed | D65: ACEINTEG | E65: SME
B66: ACE MEN ENGG WORKS LTD | C66: 539661 | D66: Not Listed | E66: Distributors
B67: ACE SOFTWARE EXPORTS LTD | C67: 531525 | D67: Not Listed | E67: IT Software Products
B68: Achal Investments Ltd | C68: 538570 | D68: ACHAL | E68: Other Financial Services
B69: ACI INFOCOM LTD | C69: 517356 | D69: Not Listed | E69: Storage Media & Peripherals
B70: ACKNIT INDUSTRIES LTD | C70: 530043 | D70: Not Listed | E70: Other Apparels & Accessories
B71: ACME RESOURCES LTD | C71: 539391 | D71: Not Listed | E71: Finance (including NBFCs)
B72: ACROW INDIA LTD. | C72: 513149 | D72: ACROW | E72: Iron &amp; Steel Products
B73: ACRYSIL LTD | C73: 524091 | D73: Not Listed | E73: Plastic Products
B74: ACTION CONSTRUCTION EQUIPMENT LTD | C74: 532762 | D74: ACE | E74: Transport Related Services
B75: ACTION FINANCIAL SERVICES (INDIA) LTD | C75: 511706 | D75: Not Listed | E75: Other Financial Services
B76: ACTION FINANCIAL SERVICES INDIA LTD | C76: 511706 | D76: Not Listed | E76: Other Financial Services
B77: ACTIVE CLOTHING CO LTD | C77: 541144 | D77: Not Listed | E77: Other Apparels & Accessories
... B135: AGRI-TECH INDIA LTD | C135: 537292 | D135: AGRITECH | E135: Other Agricultural Products
B136: AGRO PHOS (INDIA) LTD | C136: Not Listed | D136: AGROPHOS | E136: SME
B137: AGRO PHOS INDIA LTD | C137: Not Listed | D137: AGROPHOS | E137: SME
B138: AGRO TECH FOODS LTD | C138: 500215 | D138: ATFL | E138: Other Agricultural Products
B139: AHIMSA INDUSTRIES LTD | C139: Not Listed | D139: AHIMSA | E139: SME
B140: AHLADA ENGINEERS LTD | C140: Not Listed | D140: AHLADA | E140: SME
B141: AHLUWALIA CONTRACTS (INDIA) LTD | C141: 532811 | D141: AHLUCONT | E141: Realty
B142: AHLUWALIA CONTRACTS INDIA LTD | C142: 532811 | D142: AHLUCONT | E142: Realty
B143: AHMEDABAD STEELCRAFT LTD | C143: 522273 | D143: Not Listed | E143: Iron & Steel/Interm.Products
B144: AI CHAMPDANY INDUSTRIES LTD | C144: 532806 | D144: Not Listed | E144: Jute & Jute Products
B145: AIA ENGINEERING LTD | C145: 532683 | D145: AIAENG | E145: Other Industrial Goods
B146: AIMCO PESTICIDES LTD | C146: 524288 | D146: Not Listed | E146: Agrochemicals
B147: AIRAN LTD | C147: Not Listed | D147: AIRAN | E147: SME
B148: AIRO LAM LTD | C148: Not Listed | D148: AIROLAM | E148: SME
B149: AISHWARYA TELECOM LTD | C149: 532975 | D149: Not Listed | E149: Telecom Equipment
B150: AJANTA PHARMA LTD | C150: 532331 | D150: AJANTPHARM | E150: Pharmaceuticals
B151: AJANTA SOYA LTD | C151: 519216 | D151: Not Listed | E151: Edible Oils
B152: AJCON GLOBAL SERVICES LTD | C152: 511692 | D152: Not Listed | E152: Other Financial Services
B153: AJEL LTD | C153: 530713 | D153: Not Listed | E153: IT Consulting & Software
B154: AJMERA REALTY & INFRA (INDIA) LTD | C154: 513349 | D154: AJMERA | E154: Realty
B155: AJMERA REALTY & INFRA INDIA LTD | C155: 513349 | D155: AJMERA | E155: Realty
B156: AJOONI BIOTECH LTD | C156: Not Listed | D156: AJOONI | E156: SME
B157: AJWA FUN WORLD & RESORT LTD | C157: 526628 | D157: Not Listed | E157: Other Leisure Facilities
B158: AKAR AUTO INDUSTRIES LTD | C158: 530621 | D158: Not Listed | E158: Industrial Machinery
B159: AKASH INFRA PROJECTS LTD | C159: Not Listed | D159: AKASH | E159: SME
B160: AKASHDEEP METAL INDUSTRIES LTD | C160: 538778 | D160: Not Listed | E160: Finance (including NBFCs)
B161: AKG EXIM LTD | C161: Not Listed | D161: AKG | E161: SME
B162: AKI (INDIA) LTD | C162: 542020 | D162: Not Listed | E162: Other Apparels & Accessories
B163: AKI INDIA LTD | C163: 542020 | D163: Not Listed | E163: Other Apparels & Accessories
B164: AKM LACE AND EMBROTEX LTD | C164: 540718 | D164: Not Listed | E164: Textiles
B165: AKME STAR HOUSING FINANCE LTD | C165: 539017 | D165: Not Listed | E165: Housing Finance
...

Sheet Financials ->

Sheet Historical Financial Statements
B2: ="Historical Financial Statement - "&'Data Sheet'!B1 -> Historical Financial Statement - TATA POWER COMPANY LTD | M2: Seasonality | N2: FORECAST
B3: Year | C3: ='Data Sheet'!B16 -> 42825 | D3: ='Data Sheet'!C16 -> 43190 | E3: ='Data Sheet'!D16 -> 43555 | F3: ='Data Sheet'!E16 -> 43921 | G3: ='Data Sheet'!F16 -> 44286 | H3: ='Data Sheet'!G16 -> 44651 | I3: ='Data Sheet'!H16 -> 45016 | J3: ='Data Sheet'!I16 -> 45382 | ... L3: ='Data Sheet'!K16 -> 46112 | N3: =L3+365 -> 46477 | O3: =N3+365 -> 46842 | P3: =O3+365 -> 47207 | Q3: =P3+365 -> 47572 | R3: =Q3+365 -> 47937
A5: # | B5: Income Statement
B6: Sales | C6: ='Data Sheet'!B17 -> 27587.59 | D6: ='Data Sheet'!C17 -> 26840.27 | E6: ='Data Sheet'!D17 -> 29881.06 | F6: ='Data Sheet'!E17 -> 29136.37 | G6: ='Data Sheet'!F17 -> 32703.31 | H6: ='Data Sheet'!G17 -> 42815.67 | I6: ='Data Sheet'!H17 -> 55109.08 | J6: ='Data Sheet'!I17 -> 61448.9 | ... L6: ='Data Sheet'!K17 -> 62428.59 | M6: =IFERROR(_xlfn.FORECAST.ETS.SEASONALITY($C6:$L6,$C$3:$L$3),"") -> 0 | N6: =IFERROR(_xlfn.FORECAST.ETS(N$3,$C6:$L6,$C$3:$L$3,$M$6),"") -> 67458.314 | O6: =IFERROR(_xlfn.FORECAST.ETS(O$3,$C6:$L6,$C$3:$L$3,$M$6),"") -> 72474.296 | P6: =IFERROR(_xlfn.FORECAST.ETS(P$3,$C6:$L6,$C$3:$L$3,$M$6),"") -> 77503.982 | Q6: =IFERROR(_xlfn.FORECAST.ETS(Q$3,$C6:$L6,$C$3:$L$3,$M$6),"") -> 82533.706 | R6: =IFERROR(_xlfn.FORECAST.ETS(R$3,$C6:$L6,$C$3:$L$3,$M$6),"") -> 87563.431
B7: Sales Growth | C7: 0 | D7: =D6/C6-1 -> -0.027088992 | E7: =E6/D6-1 -> 0.11329208 | F7: =F6/E6-1 -> -0.024921807 | G7: =G6/F6-1 -> 0.12242225 | H7: =H6/G6-1 -> 0.30921518 | I7: =I6/H6-1 -> 0.28712408 | J7: =J6/I6-1 -> 0.1150413 | K7: =K6/J6-1 -> 0.065572207 | L7: =L6/K6-1 -> -0.046575015 | M7: =IFERROR(_xlfn.FORECAST.ETS.SEASONALITY($C7:$L7,$C$3:$L$3),"") -> 0 | N7: =N6/L6-1 -> 0.080567639 | O7: =O6/N6-1 -> 0.07435676 | P7: =P6/O6-1 -> 0.069399591 | Q7: =Q6/P6-1 -> 0.064896331 | R7: =R6/Q6-1 -> 0.060941455
M8: =IFERROR(_xlfn.FORECAST.ETS.SEASONALITY($C8:$L8,$C$3:$L$3),"") | N8: =IFERROR(_xlfn.FORECAST.ETS(N$3,$C8:$L8,$C$3:$L$3,$M$6),"") | O8: =IFERROR(_xlfn.FORECAST.ETS(O$3,$C8:$L8,$C$3:$L$3,$M$6),"") | P8: =IFERROR(_xlfn.FORECAST.ETS(P$3,$C8:$L8,$C$3:$L$3,$M$6),"") | Q8: =IFERROR(_xlfn.FORECAST.ETS(Q$3,$C8:$L8,$C$3:$L$3,$M$6),"") | R8: =IFERROR(_xlfn.FORECAST.ETS(R$3,$C8:$L8,$C$3:$L$3,$M$6),"")
B9: COGS | C9: =IFERROR(SUM('Data Sheet'!B18,'Data Sheet'!B20:B22)-1*'Data Sheet'!B19,0) -> 21013.06 | D9: =IFERROR(SUM('Data Sheet'!C18,'Data Sheet'!C20:C22)-1*'Data Sheet'!C19,0) -> 19864.32 | E9: =IFERROR(SUM('Data Sheet'!D18,'Data Sheet'!D20:D22)-1*'Data Sheet'!D19,0) -> 22496.97 | F9: =IFERROR(SUM('Data Sheet'!E18,'Data Sheet'!E20:E22)-1*'Data Sheet'!E19,0) -> 20639.12 | G9: =IFERROR(SUM('Data Sheet'!F18,'Data Sheet'!F20:F22)-1*'Data Sheet'!F19,0) -> 24985.64 | H9: =IFERROR(SUM('Data Sheet'!G18,'Data Sheet'!G20:G22)-1*'Data Sheet'!G19,0) -> 34239.37 | I9: =IFERROR(SUM('Data Sheet'!H18,'Data Sheet'!H20:H22)-1*'Data Sheet'!H19,0) -> 45560.7 | J9: =IFERROR(SUM('Data Sheet'!I18,'Data Sheet'!I20:I22)-1*'Data Sheet'!I19,0) -> 49070.77 | ... L9: =IFERROR(SUM('Data Sheet'!K18,'Data Sheet'!K20:K22)-1*'Data Sheet'!K19,0) -> 47522.91
B10: COGS % Sales | C10: =C9/C6 -> 0.76168524 | D10: =D9/D6 -> 0.7400939 | E10: =E9/E6 -> 0.75288393 | F10: =F9/F6 -> 0.70836278 | G10: =G9/G6 -> 0.76400951 | H10: =H9/H6 -> 0.7996925 | I10: =I9/I6 -> 0.82673672 | J10: =J9/J6 -> 0.79856222 | ... L10: =L9/L6 -> 0.76123632
B12: Gross Profit | C12: =C6-C9 -> 6574.53 | D12: =D6-D9 -> 6975.95 | E12: =E6-E9 -> 7384.09 | F12: =F6-F9 -> 8497.25 | G12: =G6-G9 -> 7717.67 | H12: =H6-H9 -> 8576.3 | I12: =I6-I9 -> 9548.38 | J12: =J6-J9 -> 12378.13 | ... L12: =L6-L9 -> 14905.68
B13: Gross Margin | C13: =C12/C6 -> 0.23831476 | D13: =D12/D6 -> 0.2599061 | E13: =E12/E6 -> 0.24711607 | F13: =F12/F6 -> 0.29163722 | G13: =G12/G6 -> 0.23599049 | H13: =H12/H6 -> 0.2003075 | I13: =I12/I6 -> 0.17326328 | J13: =J12/J6 -> 0.20143778 | ... L13: =L12/L6 -> 0.23876368
B15: Selling & General Expenses | C15: =IFERROR('Data Sheet'!B23,0) -> 481.89 | D15: =IFERROR('Data Sheet'!C23,0) -> 511.78 | E15: =IFERROR('Data Sheet'!D23,0) -> 466.39 | F15: =IFERROR('Data Sheet'!E23,0) -> 401.51 | G15: =IFERROR('Data Sheet'!F23,0) -> 523.94 | H15: =IFERROR('Data Sheet'!G23,0) -> 730.58 | I15: =IFERROR('Data Sheet'!H23,0) -> 1016.41 | J15: =IFERROR('Data Sheet'!I23,0) -> 1017.98 | ... L15: =IFERROR('Data Sheet'!K23,0) -> 1213.37
B16: S&G Exp % Sales | C16: =C15/C6 -> 0.017467637 | D16: =D15/D6 -> 0.019067617 | E16: =E15/E6 -> 0.015608215 | F16: =F15/F6 -> 0.013780371 | G16: =G15/G6 -> 0.016021008 | H16: =H15/H6 -> 0.017063379 | I16: =I15/I6 -> 0.018443603 | J16: =J15/J6 -> 0.016566285 | ... L16: =L15/L6 -> 0.019436127
B18: EBITDA | C18: =C12-C15 -> 6092.64 | D18: =D12-D15 -> 6464.17 | E18: =E12-E15 -> 6917.7 | F18: =F12-F15 -> 8095.74 | G18: =G12-G15 -> 7193.73 | H18: =H12-H15 -> 7845.72 | I18: =I12-I15 -> 8531.97 | J18: =J12-J15 -> 11360.15 | ... L18: =L12-L15 -> 13692.31
B19: EBITDA Margin | C19: =C18/C6 -> 0.22084713 | D19: =D18/D6 -> 0.24083849 | E19: =E18/E6 -> 0.23150785 | F19: =F18/F6 -> 0.27785685 | G19: =G18/G6 -> 0.21996948 | H19: =H18/H6 -> 0.18324413 | I19: =I18/I6 -> 0.15481968 | J19: =J18/J6 -> 0.18487149 | ... L19: =L18/L6 -> 0.21932755
B21: Depreciation | C21: ='Data Sheet'!B26 -> 1955.59 | D21: ='Data Sheet'!C26 -> 2346.17 | E21: ='Data Sheet'!D26 -> 2393.13 | F21: ='Data Sheet'!E26 -> 2633.56 | G21: ='Data Sheet'!F26 -> 2744.94 | H21: ='Data Sheet'!G26 -> 3122.2 | I21: ='Data Sheet'!H26 -> 3439.2 | J21: ='Data Sheet'!I26 -> 3786.37 | ... L21: ='Data Sheet'!K26 -> 4811.09
B22: Depreciation % Sales | C22: =C21/C6 -> 0.070886583 | D22: =D21/D6 -> 0.08741231 | E22: =E21/E6 -> 0.080088524 | F22: =F21/F6 -> 0.090387375 | G22: =G21/G6 -> 0.083934623 | H22: =H21/H6 -> 0.0729219 | I22: =I21/I6 -> 0.062407139 | J22: =J21/J6 -> 0.06161819 | ... L22: =L21/L6 -> 0.077065492
B24: EBIT | C24: =C18-C21 -> 4137.05 | D24: =D18-D21 -> 4118 | E24: =E18-E21 -> 4524.57 | F24: =F18-F21 -> 5462.18 | G24: =G18-G21 -> 4448.79 | H24: =H18-H21 -> 4723.52 | I24: =I18-I21 -> 5092.77 | J24: =J18-J21 -> 7573.78 | ... L24: =L18-L21 -> 8881.22
B25: EBIT % Sales | C25: =C24/C6 -> 0.14996054 | D25: =D24/D6 -> 0.15342618 | E25: =E24/E6 -> 0.15141933 | F25: =F24/F6 -> 0.18746948 | G25: =G24/G6 -> 0.13603485 | H25: =H24/H6 -> 0.11032223 | I25: =I24/I6 -> 0.092412539 | J25: =J24/J6 -> 0.1232533 | ... L25: =L24/L6 -> 0.14226206
B27: Other Income/Expences | C27: ='Data Sheet'!B25-'Data Sheet'!B24 -> 678 | D27: ='Data Sheet'!C25-'Data Sheet'!C24 -> 2416.3 | E27: ='Data Sheet'!D25-'Data Sheet'!D24 -> 3338.68 | F27: ='Data Sheet'!E25-'Data Sheet'!E24 -> 989.48 | G27: ='Data Sheet'!F25-'Data Sheet'!F24 -> 1502.13 | H27: ='Data Sheet'!G25-'Data Sheet'!G24 -> 1670.67 | I27: ='Data Sheet'!H25-'Data Sheet'!H24 -> 4735.88 | J27: ='Data Sheet'!I25-'Data Sheet'!I24 -> 2791.46 | ... L27: ='Data Sheet'!K25-'Data Sheet'!K24 -> 3011.56
B28: OI/E % of Sales | C28: =C27/C6 -> 0.024576268 | D28: =D27/D6 -> 0.090025175 | E28: =E27/E6 -> 0.11173231 | F28: =F27/F6 -> 0.033960305 | G28: =G27/G6 -> 0.045932048 | H28: =H27/H6 -> 0.03902006 | I28: =I27/I6 -> 0.085936474 | J28: =J27/J6 -> 0.045427339 | ... L28: =L27/L6 -> 0.048240077
B30: Interest | C30: ='Data Sheet'!B27 -> 3364.96 | D30: ='Data Sheet'!C27 -> 3761.48 | E30: ='Data Sheet'!D27 -> 4170 | F30: ='Data Sheet'!E27 -> 4493.73 | G30: ='Data Sheet'!F27 -> 4010.39 | H30: ='Data Sheet'!G27 -> 3859.02 | I30: ='Data Sheet'!H27 -> 4371.65 | J30: ='Data Sheet'!I27 -> 4633.22 | ... L30: ='Data Sheet'!K27 -> 5256.79
B31: Interest % of Sales | C31: =C30/C6 -> 0.12197368 | D31: =D30/D6 -> 0.14014315 | E31: =E30/E6 -> 0.13955328 | F31: =F30/F6 -> 0.15423095 | G31: =G30/G6 -> 0.12262948 | H31: =H30/H6 -> 0.09013102 | I31: =I30/I6 -> 0.079327218 | J31: =J30/J6 -> 0.07539956 | ... L31: =L30/L6 -> 0.084204849
B33: EBT | C33: =C24+C27-C30 -> 1450.09 | D33: =D24+D27-D30 -> 2772.82 | E33: =E24+E27-E30 -> 3693.25 | F33: =F24+F27-F30 -> 1957.93 | G33: =G24+G27-G30 -> 1940.53 | H33: =H24+H27-H30 -> 2535.17 | I33: =I24+I27-I30 -> 5457 | J33: =J24+J27-J30 -> 5732.02 | ... L33: =L24+L27-L30 -> 6635.99
B34: EBT % of Sales | C34: =C33/C6 -> 0.052563127 | D34: =D33/D6 -> 0.1033082 | E34: =E33/E6 -> 0.12359836 | F34: =F33/F6 -> 0.067198831 | G34: =G33/G6 -> 0.059337419 | H34: =H33/H6 -> 0.059211265 | I34: =I33/I6 -> 0.099021795 | J34: =J33/J6 -> 0.093281084 | ... L34: =L33/L6 -> 0.10629729
B36: Tax | C36: ='Data Sheet'!B29 -> 350.46 | D36: ='Data Sheet'!C29 -> 161.97 | E36: ='Data Sheet'!D29 -> 1087.59 | F36: ='Data Sheet'!E29 -> 641.49 | G36: ='Data Sheet'!F29 -> 501.88 | H36: ='Data Sheet'!G29 -> 379.56 | I36: ='Data Sheet'!H29 -> 1647.33 | J36: ='Data Sheet'!I29 -> 1451.92 | ... L36: ='Data Sheet'!K29 -> 1518.43
B37: Tax % of EBT | C37: =C36/C33 -> 0.24168155 | D37: =D36/D33 -> 0.058413456 | E37: =E36/E33 -> 0.29448047 | F37: =F36/F33 -> 0.32763684 | G37: =G36/G33 -> 0.25863037 | H37: =H36/H33 -> 0.14971777 | I37: =I36/I33 -> 0.30187466 | J37: =J36/J33 -> 0.25329988 | ... L37: =L36/L33 -> 0.2288174
B39: Net Profit | C39: =C33-C36 -> 1099.63 | D39: =D33-D36 -> 2610.85 | E39: =E33-E36 -> 2605.66 | F39: =F33-F36 -> 1316.44 | G39: =G33-G36 -> 1438.65 | H39: =H33-H36 -> 2155.61 | I39: =I33-I36 -> 3809.67 | J39: =J33-J36 -> 4280.1 | ... L39: =L33-L36 -> 5117.56
B40: Net Margin (%) | C40: =C39/C6 -> 0.039859589 | D40: =D39/D6 -> 0.097273612 | E40: =E39/E6 -> 0.087201056 | F40: =F39/F6 -> 0.045182018 | G40: =G39/G6 -> 0.04399096 | H40: =H39/H6 -> 0.050346287 | I40: =I39/I6 -> 0.069129624 | J40: =J39/J6 -> 0.069652996 | ... L40: =L39/L6 -> 0.081974621
B42: No. of Equity Shares | C42: ='Data Sheet'!B93 -> 270.48 | D42: ='Data Sheet'!C93 -> 270.48 | E42: ='Data Sheet'!D93 -> 270.48 | F42: ='Data Sheet'!E93 -> 270.48 | G42: ='Data Sheet'!F93 -> 319.53 | H42: ='Data Sheet'!G93 -> 319.53 | I42: ='Data Sheet'!H93 -> 319.53 | J42: ='Data Sheet'!I93 -> 319.53 | ... L42: ='Data Sheet'!K93 -> 319.53
B44: Price of Share | C44: ='Data Sheet'!B90 -> 90.35 | D44: ='Data Sheet'!C90 -> 79 | E44: ='Data Sheet'!D90 -> 73.8 | F44: ='Data Sheet'!E90 -> 32.85 | G44: ='Data Sheet'!F90 -> 103.25 | H44: ='Data Sheet'!G90 -> 238.65 | I44: ='Data Sheet'!H90 -> 190.25 | J44: ='Data Sheet'!I90 -> 394.2 | ... L44: ='Data Sheet'!K90 -> 378.75
B45: Price Growth% | C45: 0 | D45: =D44/C44-1 -> -0.12562258 | E45: =E44/D44-1 -> -0.065822785 | F45: =F44/E44-1 -> -0.55487805 | G45: =G44/F44-1 -> 2.1430746 | H45: =H44/G44-1 -> 1.3113801 | I45: =I44/H44-1 -> -0.20280746 | J45: =J44/I44-1 -> 1.0720105 | K45: =K44/J44-1 -> -0.047691527 | L45: =L44/K44-1 -> 0.0089238146
B47: Earning per Share | C47: =IFERROR(C39/C42,0) -> 4.0654762 | D47: =IFERROR(D39/D42,0) -> 9.6526545 | E47: =IFERROR(E39/E42,0) -> 9.6334664 | F47: =IFERROR(F39/F42,0) -> 4.8670512 | G47: =IFERROR(G39/G42,0) -> 4.5023941 | H47: =IFERROR(H39/H42,0) -> 6.7461897 | I47: =IFERROR(I39/I42,0) -> 11.92273 | J47: =IFERROR(J39/J42,0) -> 13.394986 | ... L47: =IFERROR(L39/L42,0) -> 16.015898
B48: EPS Growth % | C48: 0 | D48: =D47/C47-1 -> 1.3742986 | E48: =E47/D47-1 -> -0.0019878584 | F48: =F47/E47-1 -> -0.49477676 | G48: =G47/F47-1 -> -0.074923607 | H48: =H47/G47-1 -> 0.4983561 | I48: =I47/H47-1 -> 0.76732804 | J48: =J47/I47-1 -> 0.12348314 | K48: =K47/J47-1 -> 0.11571459 | L48: =L47/K47-1 -> 0.071657275
B50: Dividend | C50: ='Data Sheet'!B31 -> 351.65 | D50: ='Data Sheet'!C31 -> 351.65 | E50: ='Data Sheet'!D31 -> 351.65 | F50: ='Data Sheet'!E31 -> 419.28 | G50: ='Data Sheet'!F31 -> 495.32 | H50: ='Data Sheet'!G31 -> 559.23 | I50: ='Data Sheet'!H31 -> 639.12 | J50: ='Data Sheet'!I31 -> 639.12 | ... L50: ='Data Sheet'!K31 -> 798.9
B51: Dividend per Share | C51: =IFERROR(C50/C42,0) -> 1.3000961 | D51: =IFERROR(D50/D42,0) -> 1.3000961 | E51: =IFERROR(E50/E42,0) -> 1.3000961 | F51: =IFERROR(F50/F42,0) -> 1.5501331 | G51: =IFERROR(G50/G42,0) -> 1.5501518 | H51: =IFERROR(H50/H42,0) -> 1.7501643 | I51: =IFERROR(I50/I42,0) -> 2.0001878 | J51: =IFERROR(J50/J42,0) -> 2.0001878 | ... L51: =IFERROR(L50/L42,0) -> 2.5002347
B52: Dividend payout ratio | C52: =IFERROR(C51/C47,0) -> 0.31978938 | D52: =IFERROR(D51/D47,0) -> 0.13468794 | E52: =IFERROR(E51/E47,0) -> 0.13495621 | F52: =IFERROR(F51/F47,0) -> 0.31849534 | G52: =IFERROR(G51/G47,0) -> 0.344295 | H52: =IFERROR(H51/H47,0) -> 0.25943005 | I52: =IFERROR(I51/I47,0) -> 0.16776256 | J52: =IFERROR(J51/J47,0) -> 0.14932361 | ... L52: =IFERROR(L51/L47,0) -> 0.15610955
B54: Retaioned Earning | C54: =IFERROR(IF(C47>C51,1-C52,0),0) -> 0.68021062 | D54: =IFERROR(IF(D47>D51,1-D52,0),0) -> 0.86531206 | E54: =IFERROR(IF(E47>E51,1-E52,0),0) -> 0.86504379 | F54: =IFERROR(IF(F47>F51,1-F52,0),0) -> 0.68150466 | G54: =IFERROR(IF(G47>G51,1-G52,0),0) -> 0.655705 | H54: =IFERROR(IF(H47>H51,1-H52,0),0) -> 0.74056995 | I54: =IFERROR(IF(I47>I51,1-I52,0),0) -> 0.83223744 | J54: =IFERROR(IF(J47>J51,1-J52,0),0) -> 0.85067639 | ... L54: =IFERROR(IF(L47>L51,1-L52,0),0) -> 0.84389045
A56: # | B56: Balance Sheet
B58: Equity | C58: 270 | D58: 270 | E58: 270 | F58: 270 | G58: 320 | H58: 320 | I58: 320 | J58: 320 | K58: 320 | L58: 320
B59: Reservbes | C59: 12944 | D59: 16130 | E59: 18035 | F59: 19297 | G59: 22003 | H59: 22122 | I59: 28468 | J59: 32037 | K59: 35521 | L59: 39148
B60: NON Current Liability
B61: Borrowings | C61: 48815 | D61: 48589 | E61: 48506 | F61: 51936 | G61: 46708 | H61: 51195 | I61: 52923 | J61: 53689 | K61: 62866 | L61: 76141
B62: non Contolling Int | C62: 1869 | D62: 2015 | E62: 2167 | F62: 2332 | G62: 2927 | H62: 3587 | I62: 5417 | J62: 5977 | K62: 6765 | L62: 8071
B63: Total Non current Liability | C63: =SUM(C61:C62) -> 50684 | D63: =SUM(D61:D62) -> 50604 | E63: =SUM(E61:E62) -> 50673 | F63: =SUM(F61:F62) -> 54268 | G63: =SUM(G61:G62) -> 49635 | H63: =SUM(H61:H62) -> 54782 | I63: =SUM(I61:I62) -> 58340 | J63: =SUM(J61:J62) -> 59666 | ... L63: =SUM(L61:L62) -> 84212
B65: Current Liabilities
B66: Trade Payables | C66: 5529 | D66: 5610 | E66: 5481 | F66: 5095 | G66: 7146 | H66: 10460 | I66: 7407 | J66: 14093 | K66: 13984 | L66: 10786
B67: Advance from Customers | C67: 413 | D67: 559 | E67: 485 | F67: 782 | G67: 1209 | H67: 1180 | I67: 2458 | J67: 2197 | K67: 1579 | L67: 1580
B68: Other liability items | C68: 12989 | D68: 8718 | E68: 9129 | F68: 9962 | G68: 18342 | H68: 23687 | I68: 31104 | J68: 30742 | K68: 35158 | L68: 38518
B69: Total Current Liabilities | C69: =SUM(C66:C68) -> 18931 | D69: =SUM(D66:D68) -> 14887 | E69: =SUM(E66:E68) -> 15095 | F69: =SUM(F66:F68) -> 15839 | G69: =SUM(G66:G68) -> 26697 | H69: =SUM(H66:H68) -> 35327 | I69: =SUM(I66:I68) -> 40969 | J69: =SUM(J66:J68) -> 47032 | ... L69: =SUM(L66:L68) -> 50884
B71: Total Liability | C71: =C69+C63+C59+C58 -> 82829 | D71: =D69+D63+SUM(D58:D59) -> 81891 | E71: =E69+E63+SUM(E58:E59) -> 84073 | F71: =F69+F63+SUM(F58:F59) -> 89674 | G71: =G69+G63+SUM(G58:G59) -> 98655 | H71: =H69+H63+SUM(H58:H59) -> 112551 | I71: =I69+I63+SUM(I58:I59) -> 128097 | J71: =J69+J63+SUM(J58:J59) -> 139055 | K71: =K69+K63+SUM(K58:K59) -> 156193 | L71: =L69+L63+SUM(L58:L59) -> 174564
B73: Current Assets
B74: Inventories | C74: 1600 | D74: 1623 | E74: 1706 | F74: 1752 | G74: 1886 | H74: 4232 | I74: 3943 | J74: 4420 | K74: 4572 | L74: 5108
B75: Trade receivables | C75: 3832 | D75: 2789 | E75: 4445 | F75: 4426 | G75: 5200 | H75: 5980 | I75: 6952 | J75: 7402 | K75: 5710 | L75: 4424
B76: Loans n Advances | C76: 395 | D76: 490 | E76: 501 | F76: 552 | G76: 609 | H76: 887 | I76: 1079 | J76: 1134 | K76: 994 | L76: 461
B77: Other asset items | C77: 15402 | D77: 17066 | E77: 16211 | F77: 17037 | G77: 16491 | H77: 18627 | I77: 21123 | J77: 21861 | K77: 25797 | L77: 32465
B78: Cash Equivalents | C78: 954 | D78: 1186 | E78: 787 | F78: 2094 | G78: 5871 | H78: 6641 | I78: 11207 | J78: 9152 | K78: 11751 | L78: 13644
B79: Total Current Assets | C79: =SUM(C74:C78) -> 22183 | D79: =SUM(D74:D78) -> 23154 | E79: =SUM(E74:E78) -> 23650 | F79: =SUM(F74:F78) -> 25861 | G79: =SUM(G74:G78) -> 30057 | H79: =SUM(H74:H78) -> 36367 | I79: =SUM(I74:I78) -> 44304 | J79: =SUM(J74:J78) -> 43969 | ... L79: =SUM(L74:L78) -> 56102
B81: NON Current Assets
B82: Land | C82: 1079 | D82: 974 | E82: 1032 | F82: 2071 | G82: 2186 | H82: 2284 | I82: 2672 | J82: 3352 | K82: 4087 | L82: 4798
B83: Building | C83: 2792 | D83: 2906 | E83: 2938 | F83: 3058 | G83: 3826 | H83: 4043 | I83: 4432 | J83: 4503 | K83: 5615 | L83: 6228
B84: Plant Machinery | C84: 44014 | D84: 43914 | E84: 44924 | F84: 47425 | G84: 48607 | H84: 52664 | I84: 55799 | J84: 59919 | K84: 68397 | L84: 74140
B85: Equipments | C85: 5317 | D85: 5812 | E85: 6364 | F85: 6967 | G85: 11790 | H85: 15200 | I85: 18485 | J85: 22097 | K85: 26523 | L85: 32524
B86: Furniture n fittings | C86: 137 | D86: 122 | E86: 120 | F86: 118 | G86: 134 | H86: 144 | I86: 167 | J86: 187 | K86: 207 | L86: 212
B87: Railway sidings | C87: 96 | D87: 99 | E87: 103 | F87: 104 | G87: 0 | H87: 0 | I87: 0 | J87: 0 | K87: 0 | L87: 0
B88: Vehicles | C88: 220 | D88: 250 | E88: 245 | F88: 235 | G88: 228 | H88: 225 | I88: 247 | J88: 300 | K88: 327 | L88: 353
B89: Intangible Assets | C89: 1768 | D89: 1666 | E89: 1654 | F89: 1646 | G89: 1800 | H89: 1864 | I89: 1865 | J89: 1903 | K89: 1807 | L89: 1698
B90: Other fixed assets | C90: 4211 | D90: 4265 | E90: 4233 | F90: 5441 | G90: 5584 | H90: 5876 | I90: 6229 | J90: 6519 | K90: 6722 | L90: 6959
B91: Gross Block | C91: =SUM(C82:C90) -> 59634 | D91: =SUM(D82:D90) -> 60008 | E91: =SUM(E82:E90) -> 61613 | F91: =SUM(F82:F90) -> 67065 | G91: =SUM(G82:G90) -> 74155 | H91: =SUM(H82:H90) -> 82300 | I91: =SUM(I82:I90) -> 89896 | J91: =SUM(J82:J90) -> 98780 | ... L91: =SUM(L82:L90) -> 126912
B92: Accumulated Depreciation | C92: 13040 | D92: 15352 | E92: 17308 | F92: 19398 | G92: 21976 | H92: 24911 | I92: 28150 | J92: 31571 | K92: 35311 | L92: 39620
B93: Fixed Assetcs net Block | C93: =C91-C92 -> 46594 | D93: =D91-D92 -> 44656 | E93: =E91-E92 -> 44305 | F93: =F91-F92 -> 47667 | G93: =G91-G92 -> 52179 | H93: =H91-H92 -> 57389 | I93: =I91-I92 -> 61746 | J93: =J91-J92 -> 67209 | ... L93: =L91-L92 -> 87292
B94: CWIP | C94: 2179 | D94: 1652 | E94: 2576 | F94: 1611 | G94: 3270 | H94: 4635 | I94: 5377 | J94: 11561 | K94: 12679 | L94: 14595
B95: Investments | C95: 11873 | D95: 12429 | E95: 13542 | F95: 14535 | G95: 13149 | H95: 14160 | I95: 16670 | J95: 16316 | K95: 16316 | L95: 16575
B96: Total Non current Assets | C96: 60646 | D96: 58737 | E96: 60423 | F96: 63813 | G96: 68598 | H96: 76184 | I96: 83793 | J96: 95086 | K96: 107369 | L96: 118462
B98: Total Assets | C98: =IFERROR(C79+C96,0) -> 82829 | D98: =IFERROR(D79+D96,0) -> 81891 | E98: =IFERROR(E79+E96,0) -> 84073 | F98: =IFERROR(F79+F96,0) -> 89674 | G98: =IFERROR(G79+G96,0) -> 98655 | H98: =IFERROR(H79+H96,0) -> 112551 | I98: =IFERROR(I79+I96,0) -> 128097 | J98: =IFERROR(J79+J96,0) -> 139055 | ... L98: =IFERROR(L79+L96,0) -> 174564
B100: Check | C100: =C98=C71 -> TRUE | D100: =D98=D71 -> TRUE | E100: =E98=E71 -> TRUE | F100: =F98=F71 -> TRUE | G100: =G98=G71 -> TRUE | H100: =H98=H71 -> TRUE | I100: =I98=I71 -> TRUE | J100: =J98=J71 -> TRUE | ... L100: =L98=L71 -> TRUE
A102: # | B102: Cash Flow Statement
B104: Cash from Operating Activity - | C104: 7014 | D104: 6364 | E104: 4574 | F104: 7375 | G104: 8345 | H104: 6693 | I104: 7166 | J104: 12504 | K104: 12680 | L104: 5993
B105: Profit from operations | C105: 5958 | D105: 6007 | E105: 6895 | F105: 7310 | G105: 7651 | H105: 7576 | I105: 9016 | J105: 11258 | K105: 13195 | L105: 13411
B106: Receivables | C106: -52 | D106: 715 | E106: -1649 | F106: -97 | G106: -1104 | H106: -888 | I106: -1070 | J106: -859 | K106: 275 | L106: 751
B107: Inventory | C107: -205 | D107: -147 | E107: -85 | F107: -21 | G107: -93 | H107: -2308 | I107: 310 | J107: -445 | K107: -140 | L107: -536
B108: Payables | C108: 1108 | D108: 86 | E108: -43 | F108: -797 | G108: 1710 | H108: 3222 | I108: -3018 | J108: 4022 | K108: 516 | L108: -3153
B109: Loans Advances | C109: 54 | D109: -32 | E109: 22 | F109: -5 | G109: -1 | H109: -1 | I109: 0 | J109: 1 | K109: 0 | L109: -43
B110: Operating investments | C110: 147 | D110: 37 | E110: 117 | F110: -136 | G110: 158 | H110: 0 | I110: 0 | J110: 0 | K110: 0 | L110: 0
B111: Other WC items | C111: 584 | D111: 299 | E111: -177 | F111: 1729 | G111: 472 | H111: -214 | I111: 2799 | J111: -884 | K111: -579 | L111: -3273
B112: Working capital changes | C112: 1636 | D112: 958 | E112: -1815 | F112: 674 | G112: 1141 | H112: -189 | I112: -979 | J112: 1836 | K112: 72 | L112: -6253
B113: Direct taxes | C113: -580 | D113: -602 | E113: -506 | F113: -609 | G113: -447 | H113: -695 | I113: -871 | J113: -589 | K113: -587 | L113: -1164
B114: Cash from Investing Activity - | C114: -7373 | D114: -1512 | E114: -272 | F114: -493 | G114: 993 | H114: -6250 | I114: -7263 | J114: -8935 | K114: -15436 | L114: -14129
B115: Fixed assets purchased | C115: -3322 | D115: -3560 | E115: -3576 | F115: -2226 | G115: -3336 | H115: -7268 | I115: -7656 | J115: -13241 | K115: -17273 | L115: 0
... B134: Free Cash Flow | C134: 3708 | D134: 2860 | E134: 1040 | F134: 5186 | G134: 6558 | H134: -540 | I134: -440 | J134: -590 | K134: -4357 | L134: 5993

Sheet Ratio Analysis
B2: ="Historical Financial Statement - "&'Data Sheet'!B1 -> Historical Financial Statement - TATA POWER COMPANY LTD
B3: Year | C3: ='Historical Financial Statements'!C3 -> 42825 | D3: ='Historical Financial Statements'!D3 -> 43190 | E3: ='Historical Financial Statements'!E3 -> 43555 | F3: ='Historical Financial Statements'!F3 -> 43921 | G3: ='Historical Financial Statements'!G3 -> 44286 | H3: ='Historical Financial Statements'!H3 -> 44651 | I3: ='Historical Financial Statements'!I3 -> 45016 | J3: ='Historical Financial Statements'!J3 -> 45382 | ... L3: ='Historical Financial Statements'!L3 -> 46112 | N3: Mean | O3: Median
B5: Sales Growth | D5: =IFERROR('Historical Financial Statements'!D7,0) -> -0.027088992 | E5: =IFERROR('Historical Financial Statements'!E7,0) -> 0.11329208 | F5: =IFERROR('Historical Financial Statements'!F7,0) -> -0.024921807 | G5: =IFERROR('Historical Financial Statements'!G7,0) -> 0.12242225 | H5: =IFERROR('Historical Financial Statements'!H7,0) -> 0.30921518 | I5: =IFERROR('Historical Financial Statements'!I7,0) -> 0.28712408 | J5: =IFERROR('Historical Financial Statements'!J7,0) -> 0.1150413 | K5: =IFERROR('Historical Financial Statements'!K7,0) -> 0.065572207 | L5: =IFERROR('Historical Financial Statements'!L7,0) -> -0.046575015 | N5: =IFERROR(AVERAGE(D5:L5),0) -> 0.10156459 | O5: =IFERROR(MEDIAN(D5:L5),0) -> 0.11329208
B6: EBITDA Growth | D6: =IFERROR('Historical Financial Statements'!D18/'Historical Financial Statements'!C18-1,0) -> 0.060980133 | E6: =IFERROR('Historical Financial Statements'!E18/'Historical Financial Statements'!D18-1,0) -> 0.070160593 | F6: =IFERROR('Historical Financial Statements'!F18/'Historical Financial Statements'!E18-1,0) -> 0.17029359 | G6: =IFERROR('Historical Financial Statements'!G18/'Historical Financial Statements'!F18-1,0) -> -0.11141786 | H6: =IFERROR('Historical Financial Statements'!H18/'Historical Financial Statements'!G18-1,0) -> 0.090633093 | I6: =IFERROR('Historical Financial Statements'!I18/'Historical Financial Statements'!H18-1,0) -> 0.087468072 | J6: =IFERROR('Historical Financial Statements'!J18/'Historical Financial Statements'!I18-1,0) -> 0.3314803 | K6: =IFERROR('Historical Financial Statements'!K18/'Historical Financial Statements'!J18-1,0) -> 0.28033873 | L6: =IFERROR('Historical Financial Statements'!L18/'Historical Financial Statements'!K18-1,0) -> -0.058613914 | N6: =IFERROR(AVERAGE(D6:L6),0) -> 0.10236919 | O6: =IFERROR(MEDIAN(D6:L6),0) -> 0.087468072
B7: EBIT Growth | D7: =IFERROR('Historical Financial Statements'!D24/'Historical Financial Statements'!C24-1,0) -> -0.0046047304 | E7: =IFERROR('Historical Financial Statements'!E24/'Historical Financial Statements'!D24-1,0) -> 0.098729966 | F7: =IFERROR('Historical Financial Statements'!F24/'Historical Financial Statements'!E24-1,0) -> 0.20722632 | G7: =IFERROR('Historical Financial Statements'!G24/'Historical Financial Statements'!F24-1,0) -> -0.18552849 | H7: =IFERROR('Historical Financial Statements'!H24/'Historical Financial Statements'!G24-1,0) -> 0.06175387 | I7: =IFERROR('Historical Financial Statements'!I24/'Historical Financial Statements'!H24-1,0) -> 0.078172634 | J7: =IFERROR('Historical Financial Statements'!J24/'Historical Financial Statements'!I24-1,0) -> 0.48716317 | K7: =IFERROR('Historical Financial Statements'!K24/'Historical Financial Statements'!J24-1,0) -> 0.37685277 | L7: =IFERROR('Historical Financial Statements'!L24/'Historical Financial Statements'!K24-1,0) -> -0.14832786 | N7: =IFERROR(AVERAGE(D7:L7),0) -> 0.10793752 | O7: =IFERROR(MEDIAN(D7:L7),0) -> 0.078172634
B8: Net Profit Growth | D8: =IFERROR('Historical Financial Statements'!D39/'Historical Financial Statements'!C39-1,0) -> 1.3742986 | E8: =IFERROR('Historical Financial Statements'!E39/'Historical Financial Statements'!D39-1,0) -> -0.0019878584 | F8: =IFERROR('Historical Financial Statements'!F39/'Historical Financial Statements'!E39-1,0) -> -0.49477676 | G8: =IFERROR('Historical Financial Statements'!G39/'Historical Financial Statements'!F39-1,0) -> 0.092833703 | H8: =IFERROR('Historical Financial Statements'!H39/'Historical Financial Statements'!G39-1,0) -> 0.4983561 | I8: =IFERROR('Historical Financial Statements'!I39/'Historical Financial Statements'!H39-1,0) -> 0.76732804 | J8: =IFERROR('Historical Financial Statements'!J39/'Historical Financial Statements'!I39-1,0) -> 0.12348314 | K8: =IFERROR('Historical Financial Statements'!K39/'Historical Financial Statements'!J39-1,0) -> 0.11571459 | L8: =IFERROR('Historical Financial Statements'!L39/'Historical Financial Statements'!K39-1,0) -> 0.071657275 | N8: =IFERROR(AVERAGE(D8:L8),0) -> 0.28298965 | O8: =IFERROR(MEDIAN(D8:L8),0) -> 0.11571459
B9: Dividend Growth | D9: ='Historical Financial Statements'!D50/'Historical Financial Statements'!C50-1 -> 0 | E9: ='Historical Financial Statements'!E50/'Historical Financial Statements'!D50-1 -> 0 | F9: ='Historical Financial Statements'!F50/'Historical Financial Statements'!E50-1 -> 0.19232191 | G9: ='Historical Financial Statements'!G50/'Historical Financial Statements'!F50-1 -> 0.18135852 | H9: ='Historical Financial Statements'!H50/'Historical Financial Statements'!G50-1 -> 0.1290277 | I9: ='Historical Financial Statements'!I50/'Historical Financial Statements'!H50-1 -> 0.14285714 | J9: ='Historical Financial Statements'!J50/'Historical Financial Statements'!I50-1 -> 0 | K9: ='Historical Financial Statements'!K50/'Historical Financial Statements'!J50-1 -> 0.125 | L9: ='Historical Financial Statements'!L50/'Historical Financial Statements'!K50-1 -> 0.11111111 | N9: =IFERROR(AVERAGE(D9:L9),0) -> 0.097964043 | O9: =IFERROR(MEDIAN(D9:L9),0) -> 0.125
B11: Gross Margin | C11: =IFERROR('Historical Financial Statements'!C13,0) -> 0.23831476 | D11: =IFERROR('Historical Financial Statements'!D13,0) -> 0.2599061 | E11: =IFERROR('Historical Financial Statements'!E13,0) -> 0.24711607 | F11: =IFERROR('Historical Financial Statements'!F13,0) -> 0.29163722 | G11: =IFERROR('Historical Financial Statements'!G13,0) -> 0.23599049 | H11: =IFERROR('Historical Financial Statements'!H13,0) -> 0.2003075 | I11: =IFERROR('Historical Financial Statements'!I13,0) -> 0.17326328 | J11: =IFERROR('Historical Financial Statements'!J13,0) -> 0.20143778 | ... L11: =IFERROR('Historical Financial Statements'!L13,0) -> 0.23876368 | N11: =IFERROR(AVERAGE(C11:L11),0) -> 0.23249843 | O11: =IFERROR(MEDIAN(C11:L11),0) -> 0.23828108
B12: EBITDA Margin | C12: =IFERROR('Historical Financial Statements'!C19,0) -> 0.22084713 | D12: =IFERROR('Historical Financial Statements'!D19,0) -> 0.24083849 | E12: =IFERROR('Historical Financial Statements'!E19,0) -> 0.23150785 | F12: =IFERROR('Historical Financial Statements'!F19,0) -> 0.27785685 | G12: =IFERROR('Historical Financial Statements'!G19,0) -> 0.21996948 | H12: =IFERROR('Historical Financial Statements'!H19,0) -> 0.18324413 | I12: =IFERROR('Historical Financial Statements'!I19,0) -> 0.15481968 | J12: =IFERROR('Historical Financial Statements'!J19,0) -> 0.18487149 | ... L12: =IFERROR('Historical Financial Statements'!L19,0) -> 0.21932755 | N12: =IFERROR(AVERAGE(C12:L12),0) -> 0.21554151 | O12: =IFERROR(MEDIAN(C12:L12),0) -> 0.2204083
B13: EBIT Margin | C13: =IFERROR('Historical Financial Statements'!C25,0) -> 0.14996054 | D13: =IFERROR('Historical Financial Statements'!D25,0) -> 0.15342618 | E13: =IFERROR('Historical Financial Statements'!E25,0) -> 0.15141933 | F13: =IFERROR('Historical Financial Statements'!F25,0) -> 0.18746948 | G13: =IFERROR('Historical Financial Statements'!G25,0) -> 0.13603485 | H13: =IFERROR('Historical Financial Statements'!H25,0) -> 0.11032223 | I13: =IFERROR('Historical Financial Statements'!I25,0) -> 0.092412539 | J13: =IFERROR('Historical Financial Statements'!J25,0) -> 0.1232533 | ... L13: =IFERROR('Historical Financial Statements'!L25,0) -> 0.14226206 | N13: =IFERROR(AVERAGE(C13:L13),0) -> 0.14058192 | O13: =IFERROR(MEDIAN(C13:L13),0) -> 0.1461113
B14: EBT Margin | C14: =IFERROR('Historical Financial Statements'!C34,0) -> 0.052563127 | D14: =IFERROR('Historical Financial Statements'!D34,0) -> 0.1033082 | E14: =IFERROR('Historical Financial Statements'!E34,0) -> 0.12359836 | F14: =IFERROR('Historical Financial Statements'!F34,0) -> 0.067198831 | G14: =IFERROR('Historical Financial Statements'!G34,0) -> 0.059337419 | H14: =IFERROR('Historical Financial Statements'!H34,0) -> 0.059211265 | I14: =IFERROR('Historical Financial Statements'!I34,0) -> 0.099021795 | J14: =IFERROR('Historical Financial Statements'!J34,0) -> 0.093281084 | ... L14: =IFERROR('Historical Financial Statements'!L34,0) -> 0.10629729 | N14: =IFERROR(AVERAGE(C14:L14),0) -> 0.086033218 | O14: =IFERROR(MEDIAN(C14:L14),0) -> 0.094897948
B15: Net Profit Margin | C15: =IFERROR('Historical Financial Statements'!C40,0) -> 0.039859589 | D15: =IFERROR('Historical Financial Statements'!D40,0) -> 0.097273612 | E15: =IFERROR('Historical Financial Statements'!E40,0) -> 0.087201056 | F15: =IFERROR('Historical Financial Statements'!F40,0) -> 0.045182018 | G15: =IFERROR('Historical Financial Statements'!G40,0) -> 0.04399096 | H15: =IFERROR('Historical Financial Statements'!H40,0) -> 0.050346287 | I15: =IFERROR('Historical Financial Statements'!I40,0) -> 0.069129624 | J15: =IFERROR('Historical Financial Statements'!J40,0) -> 0.069652996 | ... L15: =IFERROR('Historical Financial Statements'!L40,0) -> 0.081974621 | N15: =IFERROR(AVERAGE(C15:L15),0) -> 0.06575414 | O15: =IFERROR(MEDIAN(C15:L15),0) -> 0.06939131
B17: Sales_Expenses % Sales | C17: =IFERROR('Historical Financial Statements'!C16,0) -> 0.017467637 | D17: =IFERROR('Historical Financial Statements'!D16,0) -> 0.019067617 | E17: =IFERROR('Historical Financial Statements'!E16,0) -> 0.015608215 | F17: =IFERROR('Historical Financial Statements'!F16,0) -> 0.013780371 | G17: =IFERROR('Historical Financial Statements'!G16,0) -> 0.016021008 | H17: =IFERROR('Historical Financial Statements'!H16,0) -> 0.017063379 | I17: =IFERROR('Historical Financial Statements'!I16,0) -> 0.018443603 | J17: =IFERROR('Historical Financial Statements'!J16,0) -> 0.016566285 | ... L17: =IFERROR('Historical Financial Statements'!L16,0) -> 0.019436127 | N17: =IFERROR(AVERAGE(C17:L17),0) -> 0.016956921 | O17: =IFERROR(MEDIAN(C17:L17),0) -> 0.016814832
B18: Depreciation % Sales | C18: =IFERROR('Historical Financial Statements'!C22,0) -> 0.070886583 | D18: =IFERROR('Historical Financial Statements'!D22,0) -> 0.08741231 | E18: =IFERROR('Historical Financial Statements'!E22,0) -> 0.080088524 | F18: =IFERROR('Historical Financial Statements'!F22,0) -> 0.090387375 | G18: =IFERROR('Historical Financial Statements'!G22,0) -> 0.083934623 | H18: =IFERROR('Historical Financial Statements'!H22,0) -> 0.0729219 | I18: =IFERROR('Historical Financial Statements'!I22,0) -> 0.062407139 | J18: =IFERROR('Historical Financial Statements'!J22,0) -> 0.06161819 | ... L18: =IFERROR('Historical Financial Statements'!L22,0) -> 0.077065492 | N18: =IFERROR(AVERAGE(C18:L18),0) -> 0.074959585 | O18: =IFERROR(MEDIAN(C18:L18),0) -> 0.074993696
B19: Operating_Income % Sales | C19: =IFERROR('Historical Financial Statements'!C25,0) -> 0.14996054 | D19: =IFERROR('Historical Financial Statements'!D25,0) -> 0.15342618 | E19: =IFERROR('Historical Financial Statements'!E25,0) -> 0.15141933 | F19: =IFERROR('Historical Financial Statements'!F25,0) -> 0.18746948 | G19: =IFERROR('Historical Financial Statements'!G25,0) -> 0.13603485 | H19: =IFERROR('Historical Financial Statements'!H25,0) -> 0.11032223 | I19: =IFERROR('Historical Financial Statements'!I25,0) -> 0.092412539 | J19: =IFERROR('Historical Financial Statements'!J25,0) -> 0.1232533 | ... L19: =IFERROR('Historical Financial Statements'!L25,0) -> 0.14226206 | N19: =IFERROR(AVERAGE(C19:L19),0) -> 0.14058192 | O19: =IFERROR(MEDIAN(C19:L19),0) -> 0.1461113
B21: Return On Capital Employed(ROCE) | C21: =IFERROR('Historical Financial Statements'!C24/SUM('Historical Financial Statements'!C58:C59,'Historical Financial Statements'!C61),0) -> 0.066695417 | D21: =IFERROR('Historical Financial Statements'!D24/SUM('Historical Financial Statements'!D58:D59,'Historical Financial Statements'!D61),0) -> 0.063364569 | E21: =IFERROR('Historical Financial Statements'!E24/SUM('Historical Financial Statements'!E58:E59,'Historical Financial Statements'!E61),0) -> 0.067721932 | F21: =IFERROR('Historical Financial Statements'!F24/SUM('Historical Financial Statements'!F58:F59,'Historical Financial Statements'!F61),0) -> 0.076390921 | G21: =IFERROR('Historical Financial Statements'!G24/SUM('Historical Financial Statements'!G58:G59,'Historical Financial Statements'!G61),0) -> 0.064446263 | H21: =IFERROR('Historical Financial Statements'!H24/SUM('Historical Financial Statements'!H58:H59,'Historical Financial Statements'!H61),0) -> 0.064146014 | I21: =IFERROR('Historical Financial Statements'!I24/SUM('Historical Financial Statements'!I58:I59,'Historical Financial Statements'!I61),0) -> 0.062326615 | J21: =IFERROR('Historical Financial Statements'!J24/SUM('Historical Financial Statements'!J58:J59,'Historical Financial Statements'!J61),0) -> 0.088020129 | ... L21: =IFERROR('Historical Financial Statements'!L24/SUM('Historical Financial Statements'!L58:L59,'Historical Financial Statements'!L61),0) -> 0.076821182 | N21: =IFERROR(AVERAGE(C21:L21),0) -> 0.073557884 | O21: =IFERROR(MEDIAN(C21:L21),0) -> 0.067208674
B22: Retained Earning% | C22: =IFERROR('Historical Financial Statements'!C54,0) -> 0.68021062 | D22: =IFERROR('Historical Financial Statements'!D54,0) -> 0.86531206 | E22: =IFERROR('Historical Financial Statements'!E54,0) -> 0.86504379 | F22: =IFERROR('Historical Financial Statements'!F54,0) -> 0.68150466 | G22: =IFERROR('Historical Financial Statements'!G54,0) -> 0.655705 | H22: =IFERROR('Historical Financial Statements'!H54,0) -> 0.74056995 | I22: =IFERROR('Historical Financial Statements'!I54,0) -> 0.83223744 | J22: =IFERROR('Historical Financial Statements'!J54,0) -> 0.85067639 | ... L22: =IFERROR('Historical Financial Statements'!L54,0) -> 0.84389045 | N22: =IFERROR(AVERAGE(C22:L22),0) -> 0.7864584 | O22: =IFERROR(MEDIAN(C22:L22),0) -> 0.83806394
B23: Return on Equity% (ROE) | C23: =IFERROR('Historical Financial Statements'!C39/SUM('Historical Financial Statements'!C58:C59),0) -> 0.083217043 | D23: =IFERROR('Historical Financial Statements'!D39/SUM('Historical Financial Statements'!D58:D59),0) -> 0.15919817 | E23: =IFERROR('Historical Financial Statements'!E39/SUM('Historical Financial Statements'!E58:E59),0) -> 0.1423469 | F23: =IFERROR('Historical Financial Statements'!F39/SUM('Historical Financial Statements'!F58:F59),0) -> 0.067278581 | G23: =IFERROR('Historical Financial Statements'!G39/SUM('Historical Financial Statements'!G58:G59),0) -> 0.064446983 | H23: =IFERROR('Historical Financial Statements'!H39/SUM('Historical Financial Statements'!H58:H59),0) -> 0.096052491 | I23: =IFERROR('Historical Financial Statements'!I39/SUM('Historical Financial Statements'!I58:I59),0) -> 0.13233535 | J23: =IFERROR('Historical Financial Statements'!J39/SUM('Historical Financial Statements'!J58:J59),0) -> 0.13227741 | ... L23: =IFERROR('Historical Financial Statements'!L39/SUM('Historical Financial Statements'!L58:L59),0) -> 0.12966352 | N23: =IFERROR(AVERAGE(C23:L23),0) -> 0.11400541 | O23: =IFERROR(MEDIAN(C23:L23),0) -> 0.13097047
B24: Self Sustained Growth Rate | C24: =IFERROR(C22*C23,0) -> 0.056605116 | D24: =IFERROR(D22*D23,0) -> 0.1377561 | E24: =IFERROR(E22*E23,0) -> 0.1231363 | F24: =IFERROR(F22*F23,0) -> 0.045850667 | G24: =IFERROR(G22*G23,0) -> 0.042258209 | H24: =IFERROR(H22*H23,0) -> 0.071133589 | I24: =IFERROR(I22*I23,0) -> 0.11013443 | J24: =IFERROR(J22*J23,0) -> 0.11252527 | ... L24: =IFERROR(L22*L23,0) -> 0.10942181 | N24: =IFERROR(AVERAGE(C24:L24),0) -> 0.092199802 | O24: =IFERROR(MEDIAN(C24:L24),0) -> 0.10977812
B25: Interest Covarage Ratio | C25: =IFERROR('Historical Financial Statements'!C24/'Historical Financial Statements'!C30-1,0) -> 0.22944998 | D25: =IFERROR('Historical Financial Statements'!D24/'Historical Financial Statements'!D30-1,0) -> 0.094781841 | E25: =IFERROR('Historical Financial Statements'!E24/'Historical Financial Statements'!E30-1,0) -> 0.085028777 | F25: =IFERROR('Historical Financial Statements'!F24/'Historical Financial Statements'!F30-1,0) -> 0.21551139 | G25: =IFERROR('Historical Financial Statements'!G24/'Historical Financial Statements'!G30-1,0) -> 0.10931605 | H25: =IFERROR('Historical Financial Statements'!H24/'Historical Financial Statements'!H30-1,0) -> 0.22402061 | I25: =IFERROR('Historical Financial Statements'!I24/'Historical Financial Statements'!I30-1,0) -> 0.16495374 | J25: =IFERROR('Historical Financial Statements'!J24/'Historical Financial Statements'!J30-1,0) -> 0.63466876 | ... L25: =IFERROR('Historical Financial Statements'!L24/'Historical Financial Statements'!L30-1,0) -> 0.6894759 | N25: =IFERROR(AVERAGE(C25:L25),0) -> 0.36647749 | O25: =IFERROR(MEDIAN(C25:L25),0) -> 0.219766
B27: Debtor Turnover Ratio | C27: =IFERROR('Historical Financial Statements'!C6/'Historical Financial Statements'!C75,0) -> 7.1992667 | D27: =IFERROR('Historical Financial Statements'!D6/'Historical Financial Statements'!D75,0) -> 9.6236178 | E27: =IFERROR('Historical Financial Statements'!E6/'Historical Financial Statements'!E75,0) -> 6.7223982 | F27: =IFERROR('Historical Financial Statements'!F6/'Historical Financial Statements'!F75,0) -> 6.5830027 | G27: =IFERROR('Historical Financial Statements'!G6/'Historical Financial Statements'!G75,0) -> 6.2890981 | H27: =IFERROR('Historical Financial Statements'!H6/'Historical Financial Statements'!H75,0) -> 7.159811 | I27: =IFERROR('Historical Financial Statements'!I6/'Historical Financial Statements'!I75,0) -> 7.9270829 | J27: =IFERROR('Historical Financial Statements'!J6/'Historical Financial Statements'!J75,0) -> 8.3016617 | ... L27: =IFERROR('Historical Financial Statements'!L6/'Historical Financial Statements'!L75,0) -> 14.111345 | N27: =IFERROR(AVERAGE(C27:L27),0) -> 8.5384576 | O27: =IFERROR(MEDIAN(C27:L27),0) -> 7.5631748
B28: Creditor Turnover Ratio | C28: =IFERROR('Historical Financial Statements'!C9/'Historical Financial Statements'!C66,0) -> 3.8005173 | D28: =IFERROR('Historical Financial Statements'!D9/'Historical Financial Statements'!D66,0) -> 3.540877 | E28: =IFERROR('Historical Financial Statements'!E9/'Historical Financial Statements'!E66,0) -> 4.1045375 | F28: =IFERROR('Historical Financial Statements'!F9/'Historical Financial Statements'!F66,0) -> 4.0508577 | G28: =IFERROR('Historical Financial Statements'!G9/'Historical Financial Statements'!G66,0) -> 3.4964512 | H28: =IFERROR('Historical Financial Statements'!H9/'Historical Financial Statements'!H66,0) -> 3.2733623 | I28: =IFERROR('Historical Financial Statements'!I9/'Historical Financial Statements'!I66,0) -> 6.1510328 | J28: =IFERROR('Historical Financial Statements'!J9/'Historical Financial Statements'!J66,0) -> 3.4819251 | ... L28: =IFERROR('Historical Financial Statements'!L9/'Historical Financial Statements'!L66,0) -> 4.4059809 | N28: =IFERROR(AVERAGE(C28:L28),0) -> 3.9872348 | O28: =IFERROR(MEDIAN(C28:L28),0) -> 3.6836618
B29: Inventory Turnover | C29: =IFERROR('Historical Financial Statements'!C9/'Historical Financial Statements'!C74,0) -> 13.133163 | D29: =IFERROR('Historical Financial Statements'!D9/'Historical Financial Statements'!D74,0) -> 12.239261 | E29: =IFERROR('Historical Financial Statements'!E9/'Historical Financial Statements'!E74,0) -> 13.18697 | F29: =IFERROR('Historical Financial Statements'!F9/'Historical Financial Statements'!F74,0) -> 11.78032 | G29: =IFERROR('Historical Financial Statements'!G9/'Historical Financial Statements'!G74,0) -> 13.247953 | H29: =IFERROR('Historical Financial Statements'!H9/'Historical Financial Statements'!H74,0) -> 8.0905884 | I29: =IFERROR('Historical Financial Statements'!I9/'Historical Financial Statements'!I74,0) -> 11.554831 | J29: =IFERROR('Historical Financial Statements'!J9/'Historical Financial Statements'!J74,0) -> 11.101984 | ... L29: =IFERROR('Historical Financial Statements'!L9/'Historical Financial Statements'!L74,0) -> 9.3036237 | N29: =IFERROR(AVERAGE(C29:L29),0) -> 11.454819 | O29: =IFERROR(MEDIAN(C29:L29),0) -> 11.667575
B30: Fixed Asset Turnover | C30: =IFERROR('Historical Financial Statements'!C6/'Historical Financial Statements'!C93,0) -> 0.5920846 | D30: =IFERROR('Historical Financial Statements'!D6/'Historical Financial Statements'!D93,0) -> 0.6010451 | E30: =IFERROR('Historical Financial Statements'!E6/'Historical Financial Statements'!E93,0) -> 0.67443991 | F30: =IFERROR('Historical Financial Statements'!F6/'Historical Financial Statements'!F93,0) -> 0.61124824 | G30: =IFERROR('Historical Financial Statements'!G6/'Historical Financial Statements'!G93,0) -> 0.62675233 | H30: =IFERROR('Historical Financial Statements'!H6/'Historical Financial Statements'!H93,0) -> 0.74606057 | I30: =IFERROR('Historical Financial Statements'!I6/'Historical Financial Statements'!I93,0) -> 0.89251255 | J30: =IFERROR('Historical Financial Statements'!J6/'Historical Financial Statements'!J93,0) -> 0.9142957 | ... L30: =IFERROR('Historical Financial Statements'!L6/'Historical Financial Statements'!L93,0) -> 0.71516966 | N30: =IFERROR(AVERAGE(C30:L30),0) -> 0.72090674 | O30: =IFERROR(MEDIAN(C30:L30),0) -> 0.69480478
B31: Capital Turnover Ratio | C31: =IFERROR('Historical Financial Statements'!C6/SUM('Historical Financial Statements'!C58:C59),0) -> 2.0877547 | D31: =IFERROR('Historical Financial Statements'!D6/SUM('Historical Financial Statements'!D58:D59),0) -> 1.6366018 | E31: =IFERROR('Historical Financial Statements'!E6/SUM('Historical Financial Statements'!E58:E59),0) -> 1.6323988 | F31: =IFERROR('Historical Financial Statements'!F6/SUM('Historical Financial Statements'!F58:F59),0) -> 1.4890566 | G31: =IFERROR('Historical Financial Statements'!G6/SUM('Historical Financial Statements'!G58:G59),0) -> 1.4650052 | H31: =IFERROR('Historical Financial Statements'!H6/SUM('Historical Financial Statements'!H58:H59),0) -> 1.9078366 | I31: =IFERROR('Historical Financial Statements'!I6/SUM('Historical Financial Statements'!I58:I59),0) -> 1.9143074 | J31: =IFERROR('Historical Financial Statements'!J6/SUM('Historical Financial Statements'!J58:J59),0) -> 1.8990914 | ... L31: =IFERROR('Historical Financial Statements'!L6/SUM('Historical Financial Statements'!L58:L59),0) -> 1.5817521 | N31: =IFERROR(AVERAGE(C31:L31),0) -> 1.7440713 | O31: =IFERROR(MEDIAN(C31:L31),0) -> 1.7317553
B33: Debtor Days (DSO) | C33: =IFERROR('Historical Financial Statements'!C75/'Historical Financial Statements'!C6*360,0) -> 50.005093 | D33: =IFERROR('Historical Financial Statements'!D75/'Historical Financial Statements'!D6*360,0) -> 37.407969 | E33: =IFERROR('Historical Financial Statements'!E75/'Historical Financial Statements'!E6*360,0) -> 53.552317 | F33: =IFERROR('Historical Financial Statements'!F75/'Historical Financial Statements'!F6*360,0) -> 54.686291 | G33: =IFERROR('Historical Financial Statements'!G75/'Historical Financial Statements'!G6*360,0) -> 57.241912 | H33: =IFERROR('Historical Financial Statements'!H75/'Historical Financial Statements'!H6*360,0) -> 50.280657 | I33: =IFERROR('Historical Financial Statements'!I75/'Historical Financial Statements'!I6*360,0) -> 45.413932 | J33: =IFERROR('Historical Financial Statements'!J75/'Historical Financial Statements'!J6*360,0) -> 43.364812 | ... L33: =IFERROR('Historical Financial Statements'!L75/'Historical Financial Statements'!L6*360,0) -> 25.511388 | N33: =IFERROR(AVERAGE(C33:L33),0) -> 44.885801 | O33: =IFERROR(MEDIAN(C33:L33),0) -> 47.709512
B34: Payable Days (DPO) | C34: =IFERROR('Historical Financial Statements'!C66/'Historical Financial Statements'!C9*360,0) -> 94.723948 | D34: =IFERROR('Historical Financial Statements'!D66/'Historical Financial Statements'!D9*360,0) -> 101.66973 | E34: =IFERROR('Historical Financial Statements'!E66/'Historical Financial Statements'!E9*360,0) -> 87.707811 | F34: =IFERROR('Historical Financial Statements'!F66/'Historical Financial Statements'!F9*360,0) -> 88.870068 | G34: =IFERROR('Historical Financial Statements'!G66/'Historical Financial Statements'!G9*360,0) -> 102.96154 | H34: =IFERROR('Historical Financial Statements'!H66/'Historical Financial Statements'!H9*360,0) -> 109.97866 | I34: =IFERROR('Historical Financial Statements'!I66/'Historical Financial Statements'!I9*360,0) -> 58.526757 | J34: =IFERROR('Historical Financial Statements'!J66/'Historical Financial Statements'!J9*360,0) -> 103.39108 | ... L34: =IFERROR('Historical Financial Statements'!L66/'Historical Financial Statements'!L9*360,0) -> 81.707118 | N34: =IFERROR(AVERAGE(C34:L34),0) -> 93.046734 | O34: =IFERROR(MEDIAN(C34:L34),0) -> 97.827287
B35: Inventory Days (DIO) | C35: =IFERROR('Historical Financial Statements'!C74/'Historical Financial Statements'!C9*360,0) -> 27.411524 | D35: =IFERROR('Historical Financial Statements'!D74/'Historical Financial Statements'!D9*360,0) -> 29.413541 | E35: =IFERROR('Historical Financial Statements'!E74/'Historical Financial Statements'!E9*360,0) -> 27.299676 | F35: =IFERROR('Historical Financial Statements'!F74/'Historical Financial Statements'!F9*360,0) -> 30.559442 | G35: =IFERROR('Historical Financial Statements'!G74/'Historical Financial Statements'!G9*360,0) -> 27.174009 | H35: =IFERROR('Historical Financial Statements'!H74/'Historical Financial Statements'!H9*360,0) -> 44.496146 | I35: =IFERROR('Historical Financial Statements'!I74/'Historical Financial Statements'!I9*360,0) -> 31.155799 | J35: =IFERROR('Historical Financial Statements'!J74/'Historical Financial Statements'!J9*360,0) -> 32.426636 | ... L35: =IFERROR('Historical Financial Statements'!L74/'Historical Financial Statements'!L9*360,0) -> 38.6946 | N35: =IFERROR(AVERAGE(C35:L35),0) -> 32.163015 | O35: =IFERROR(MEDIAN(C35:L35),0) -> 30.857621
B36: Cash Convertion Cycle (CCC)(in Days) | C36: =IFERROR(SUM(C35,C33)-C34,0) -> -17.307331 | D36: =IFERROR(SUM(D35,D33)-D34,0) -> -34.848217 | E36: =IFERROR(SUM(E35,E33)-E34,0) -> -6.8558179 | F36: =IFERROR(SUM(F35,F33)-F34,0) -> -3.6243349 | G36: =IFERROR(SUM(G35,G33)-G34,0) -> -18.54562 | H36: =IFERROR(SUM(H35,H33)-H34,0) -> -15.201857 | I36: =IFERROR(SUM(I35,I33)-I34,0) -> 18.042974 | J36: =IFERROR(SUM(J35,J33)-J34,0) -> -27.599634 | ... L36: =IFERROR(SUM(L35,L33)-L34,0) -> -17.501129 | N36: =IFERROR(AVERAGE(C36:L36),0) -> -15.997919 | O36: =IFERROR(MEDIAN(C36:L36),0) -> -17.40423
B38: CFO/Sales | C38: =IFERROR('Historical Financial Statements'!C104/'Historical Financial Statements'!C6,0) -> 0.25424475 | D38: =IFERROR('Historical Financial Statements'!D104/'Historical Financial Statements'!D6,0) -> 0.23710641 | E38: =IFERROR('Historical Financial Statements'!E104/'Historical Financial Statements'!E6,0) -> 0.15307355 | F38: =IFERROR('Historical Financial Statements'!F104/'Historical Financial Statements'!F6,0) -> 0.25312007 | G38: =IFERROR('Historical Financial Statements'!G104/'Historical Financial Statements'!G6,0) -> 0.25517295 | H38: =IFERROR('Historical Financial Statements'!H104/'Historical Financial Statements'!H6,0) -> 0.15632127 | I38: =IFERROR('Historical Financial Statements'!I104/'Historical Financial Statements'!I6,0) -> 0.13003302 | J38: =IFERROR('Historical Financial Statements'!J104/'Historical Financial Statements'!J6,0) -> 0.20348615 | ... L38: =IFERROR('Historical Financial Statements'!L104/'Historical Financial Statements'!L6,0) -> 0.095997683 | N38: =IFERROR(AVERAGE(C38:L38),0) -> 0.1932208 | O38: =IFERROR(MEDIAN(C38:L38),0) -> 0.19856913
B39: CFO/Total Assets | C39: =IFERROR('Historical Financial Statements'!C104/'Historical Financial Statements'!C98,0) -> 0.084680486 | D39: =IFERROR('Historical Financial Statements'!D104/'Historical Financial Statements'!D98,0) -> 0.077713058 | E39: =IFERROR('Historical Financial Statements'!E104/'Historical Financial Statements'!E98,0) -> 0.0544051 | F39: =IFERROR('Historical Financial Statements'!F104/'Historical Financial Statements'!F98,0) -> 0.082242344 | G39: =IFERROR('Historical Financial Statements'!G104/'Historical Financial Statements'!G98,0) -> 0.084587705 | H39: =IFERROR('Historical Financial Statements'!H104/'Historical Financial Statements'!H98,0) -> 0.059466375 | I39: =IFERROR('Historical Financial Statements'!I104/'Historical Financial Statements'!I98,0) -> 0.055941981 | J39: =IFERROR('Historical Financial Statements'!J104/'Historical Financial Statements'!J98,0) -> 0.089921254 | ... L39: =IFERROR('Historical Financial Statements'!L104/'Historical Financial Statements'!L98,0) -> 0.034331248 | N39: =IFERROR(AVERAGE(C39:L39),0) -> 0.070447117 | O39: =IFERROR(MEDIAN(C39:L39),0) -> 0.079447336
B40: CFO/Total Debt | C40: =IFERROR('Historical Financial Statements'!C104/'Historical Financial Statements'!C61,0) -> 0.14368534 | D40: =IFERROR('Historical Financial Statements'!D104/'Historical Financial Statements'!D61,0) -> 0.13097615 | E40: =IFERROR('Historical Financial Statements'!E104/'Historical Financial Statements'!E61,0) -> 0.094297613 | F40: =IFERROR('Historical Financial Statements'!F104/'Historical Financial Statements'!F61,0) -> 0.14200169 | G40: =IFERROR('Historical Financial Statements'!G104/'Historical Financial Statements'!G61,0) -> 0.17866318 | H40: =IFERROR('Historical Financial Statements'!H104/'Historical Financial Statements'!H61,0) -> 0.13073542 | I40: =IFERROR('Historical Financial Statements'!I104/'Historical Financial Statements'!I61,0) -> 0.13540427 | J40: =IFERROR('Historical Financial Statements'!J104/'Historical Financial Statements'!J61,0) -> 0.23289687 | ... L40: =IFERROR('Historical Financial Statements'!L104/'Historical Financial Statements'!L61,0) -> 0.078709237 | N40: =IFERROR(AVERAGE(C40:L40),0) -> 0.14690686 | O40: =IFERROR(MEDIAN(C40:L40),0) -> 0.13870298
B42: Debt to Market Equity | C42: ='Historical Financial Statements'!C61/(('Data Sheet'!B70*'Data Sheet'!B90)/10000000) -> 1.996421 | D42: ='Historical Financial Statements'!D61/(('Data Sheet'!C70*'Data Sheet'!C90)/10000000) -> 2.2725568 | E42: ='Historical Financial Statements'!E61/(('Data Sheet'!D70*'Data Sheet'!D90)/10000000) -> 2.4285272 | F42: ='Historical Financial Statements'!F61/(('Data Sheet'!E70*'Data Sheet'!E90)/10000000) -> 5.8416697 | G42: ='Historical Financial Statements'!G61/(('Data Sheet'!F70*'Data Sheet'!F90)/10000000) -> 1.4150106 | H42: ='Historical Financial Statements'!H61/(('Data Sheet'!G70*'Data Sheet'!G90)/10000000) -> 0.67100318 | I42: ='Historical Financial Statements'!I61/(('Data Sheet'!H70*'Data Sheet'!H90)/10000000) -> 0.87011822 | J42: ='Historical Financial Statements'!J61/(('Data Sheet'!I70*'Data Sheet'!I90)/10000000) -> 0.42601723 | ... L42: ='Historical Financial Statements'!L61/(('Data Sheet'!K70*'Data Sheet'!K90)/10000000) -> 0.62881719 | N42: =IFERROR(AVERAGE(C42:L42),0) -> 1.7073959 | O42: =IFERROR(MEDIAN(C42:L42),0) -> 1.1425644

Sheet Common Size Statement
B2: ="Common Size Statement - "& 'Data Sheet'!B1 -> Common Size Statement - TATA POWER COMPANY LTD
B4: Perticulers | C4: ='Data Sheet'!B16 -> 42825 | D4: ='Data Sheet'!C16 -> 43190 | E4: ='Data Sheet'!D16 -> 43555 | F4: ='Data Sheet'!E16 -> 43921 | G4: ='Data Sheet'!F16 -> 44286 | H4: ='Data Sheet'!G16 -> 44651 | I4: ='Data Sheet'!H16 -> 45016 | J4: ='Data Sheet'!I16 -> 45382 | ... L4: ='Data Sheet'!K16 -> 46112
B6: ='Data Sheet'!A17 -> Sales | C6: ='Data Sheet'!B17/'Data Sheet'!B$17 -> 1 | D6: ='Data Sheet'!C17/'Data Sheet'!C$17 -> 1 | E6: ='Data Sheet'!D17/'Data Sheet'!D$17 -> 1 | F6: ='Data Sheet'!E17/'Data Sheet'!E$17 -> 1 | G6: ='Data Sheet'!F17/'Data Sheet'!F$17 -> 1 | H6: ='Data Sheet'!G17/'Data Sheet'!G$17 -> 1 | I6: ='Data Sheet'!H17/'Data Sheet'!H$17 -> 1 | J6: ='Data Sheet'!I17/'Data Sheet'!I$17 -> 1 | ... L6: ='Data Sheet'!K17/'Data Sheet'!K$17 -> 1
B7: ='Data Sheet'!A18 -> Raw Material Cost | C7: ='Data Sheet'!B18/'Data Sheet'!B$17 -> 0 | D7: ='Data Sheet'!C18/'Data Sheet'!C$17 -> 0 | E7: ='Data Sheet'!D18/'Data Sheet'!D$17 -> 0 | F7: ='Data Sheet'!E18/'Data Sheet'!E$17 -> 0 | G7: ='Data Sheet'!F18/'Data Sheet'!F$17 -> 0 | H7: ='Data Sheet'!G18/'Data Sheet'!G$17 -> 0 | I7: ='Data Sheet'!H18/'Data Sheet'!H$17 -> 0 | J7: ='Data Sheet'!I18/'Data Sheet'!I$17 -> 0 | ... L7: ='Data Sheet'!K18/'Data Sheet'!K$17 -> 0
B8: ='Data Sheet'!A19 -> Change in Inventory | C8: ='Data Sheet'!B19/'Data Sheet'!B$17 -> -0.0010272735 | D8: ='Data Sheet'!C19/'Data Sheet'!C$17 -> 0.00031706089 | E8: ='Data Sheet'!D19/'Data Sheet'!D$17 -> -0.00081556678 | F8: ='Data Sheet'!E19/'Data Sheet'!E$17 -> 0.00053678615 | G8: ='Data Sheet'!F19/'Data Sheet'!F$17 -> -1.2536957e-05 | H8: ='Data Sheet'!G19/'Data Sheet'!G$17 -> 0.0046529693 | I8: ='Data Sheet'!H19/'Data Sheet'!H$17 -> -0.00078988798 | J8: ='Data Sheet'!I19/'Data Sheet'!I$17 -> 0.00084265137 | ... L8: ='Data Sheet'!K19/'Data Sheet'!K$17 -> 0.0013472994
B9: ='Data Sheet'!A20 -> Power and Fuel | C9: ='Data Sheet'!B20/'Data Sheet'!B$17 -> 0.64960549 | D9: ='Data Sheet'!C20/'Data Sheet'!C$17 -> 0.60938843 | E9: ='Data Sheet'!D20/'Data Sheet'!D$17 -> 0.63314019 | F9: ='Data Sheet'!E20/'Data Sheet'!E$17 -> 0.58689638 | G9: ='Data Sheet'!F20/'Data Sheet'!F$17 -> 0.6127074 | H9: ='Data Sheet'!G20/'Data Sheet'!G$17 -> 0.62510688 | I9: ='Data Sheet'!H20/'Data Sheet'!H$17 -> 0.66610729 | J9: ='Data Sheet'!I20/'Data Sheet'!I$17 -> 0.64419038 | ... L9: ='Data Sheet'!K20/'Data Sheet'!K$17 -> 0.57287919
B10: ='Data Sheet'!A21 -> Other Mfr. Exp | C10: ='Data Sheet'!B21/'Data Sheet'!B$17 -> 0.06237406 | D10: ='Data Sheet'!C21/'Data Sheet'!C$17 -> 0.076067789 | E10: ='Data Sheet'!D21/'Data Sheet'!D$17 -> 0.068809473 | F10: ='Data Sheet'!E21/'Data Sheet'!E$17 -> 0.069112247 | G10: ='Data Sheet'!F21/'Data Sheet'!F$17 -> 0.077467082 | H10: ='Data Sheet'!G21/'Data Sheet'!G$17 -> 0.092090816 | I10: ='Data Sheet'!H21/'Data Sheet'!H$17 -> 0.090859982 | J10: ='Data Sheet'!I21/'Data Sheet'!I$17 -> 0.085807394 | ... L10: ='Data Sheet'!K21/'Data Sheet'!K$17 -> 0.10801189
B11: ='Data Sheet'!A22 -> Employee Cost | C11: ='Data Sheet'!B22/'Data Sheet'!B$17 -> 0.048678409 | D11: ='Data Sheet'!C22/'Data Sheet'!C$17 -> 0.054954738 | E11: ='Data Sheet'!D22/'Data Sheet'!D$17 -> 0.050118704 | F11: ='Data Sheet'!E22/'Data Sheet'!E$17 -> 0.05289094 | G11: ='Data Sheet'!F22/'Data Sheet'!F$17 -> 0.073822497 | H11: ='Data Sheet'!G22/'Data Sheet'!G$17 -> 0.087147766 | I11: ='Data Sheet'!H22/'Data Sheet'!H$17 -> 0.068979558 | J11: ='Data Sheet'!I22/'Data Sheet'!I$17 -> 0.069407101 | ... L11: ='Data Sheet'!K22/'Data Sheet'!K$17 -> 0.081692539
B12: ='Data Sheet'!A23 -> Selling and admin | C12: ='Data Sheet'!B23/'Data Sheet'!B$17 -> 0.017467637 | D12: ='Data Sheet'!C23/'Data Sheet'!C$17 -> 0.019067617 | E12: ='Data Sheet'!D23/'Data Sheet'!D$17 -> 0.015608215 | F12: ='Data Sheet'!E23/'Data Sheet'!E$17 -> 0.013780371 | G12: ='Data Sheet'!F23/'Data Sheet'!F$17 -> 0.016021008 | H12: ='Data Sheet'!G23/'Data Sheet'!G$17 -> 0.017063379 | I12: ='Data Sheet'!H23/'Data Sheet'!H$17 -> 0.018443603 | J12: ='Data Sheet'!I23/'Data Sheet'!I$17 -> 0.016566285 | ... L12: ='Data Sheet'!K23/'Data Sheet'!K$17 -> 0.019436127
B13: ='Data Sheet'!A24 -> Other Expenses | C13: ='Data Sheet'!B24/'Data Sheet'!B$17 -> 0.022451037 | D13: ='Data Sheet'!C24/'Data Sheet'!C$17 -> 0.054284849 | E13: ='Data Sheet'!D24/'Data Sheet'!D$17 -> 0.016254109 | F13: ='Data Sheet'!E24/'Data Sheet'!E$17 -> 0.044297557 | G13: ='Data Sheet'!F24/'Data Sheet'!F$17 -> 0.0083425806 | H13: ='Data Sheet'!G24/'Data Sheet'!G$17 -> 0.019031116 | I13: ='Data Sheet'!H24/'Data Sheet'!H$17 -> 0.014593058 | J13: ='Data Sheet'!I24/'Data Sheet'!I$17 -> 0.010168937 | ... L13: ='Data Sheet'!K24/'Data Sheet'!K$17 -> 0.0067443458
B14: ='Data Sheet'!A25 -> Other Income | C14: ='Data Sheet'!B25/'Data Sheet'!B$17 -> 0.047027305 | D14: ='Data Sheet'!C25/'Data Sheet'!C$17 -> 0.14431002 | E14: ='Data Sheet'!D25/'Data Sheet'!D$17 -> 0.12798642 | F14: ='Data Sheet'!E25/'Data Sheet'!E$17 -> 0.078257861 | G14: ='Data Sheet'!F25/'Data Sheet'!F$17 -> 0.054274628 | H14: ='Data Sheet'!G25/'Data Sheet'!G$17 -> 0.058051176 | I14: ='Data Sheet'!H25/'Data Sheet'!H$17 -> 0.10052953 | J14: ='Data Sheet'!I25/'Data Sheet'!I$17 -> 0.055596276 | ... L14: ='Data Sheet'!K25/'Data Sheet'!K$17 -> 0.054984423
B15: ='Data Sheet'!A26 -> Depreciation | C15: ='Data Sheet'!B26/'Data Sheet'!B$17 -> 0.070886583 | D15: ='Data Sheet'!C26/'Data Sheet'!C$17 -> 0.08741231 | E15: ='Data Sheet'!D26/'Data Sheet'!D$17 -> 0.080088524 | F15: ='Data Sheet'!E26/'Data Sheet'!E$17 -> 0.090387375 | G15: ='Data Sheet'!F26/'Data Sheet'!F$17 -> 0.083934623 | H15: ='Data Sheet'!G26/'Data Sheet'!G$17 -> 0.0729219 | I15: ='Data Sheet'!H26/'Data Sheet'!H$17 -> 0.062407139 | J15: ='Data Sheet'!I26/'Data Sheet'!I$17 -> 0.06161819 | ... L15: ='Data Sheet'!K26/'Data Sheet'!K$17 -> 0.077065492
B16: ='Data Sheet'!A27 -> Interest | C16: ='Data Sheet'!B27/'Data Sheet'!B$17 -> 0.12197368 | D16: ='Data Sheet'!C27/'Data Sheet'!C$17 -> 0.14014315 | E16: ='Data Sheet'!D27/'Data Sheet'!D$17 -> 0.13955328 | F16: ='Data Sheet'!E27/'Data Sheet'!E$17 -> 0.15423095 | G16: ='Data Sheet'!F27/'Data Sheet'!F$17 -> 0.12262948 | H16: ='Data Sheet'!G27/'Data Sheet'!G$17 -> 0.09013102 | I16: ='Data Sheet'!H27/'Data Sheet'!H$17 -> 0.079327218 | J16: ='Data Sheet'!I27/'Data Sheet'!I$17 -> 0.07539956 | ... L16: ='Data Sheet'!K27/'Data Sheet'!K$17 -> 0.084204849
B17: ='Data Sheet'!A28 -> Profit before tax | C17: ='Data Sheet'!B28/'Data Sheet'!B$17 -> 0.052563127 | D17: ='Data Sheet'!C28/'Data Sheet'!C$17 -> 0.1033082 | E17: ='Data Sheet'!D28/'Data Sheet'!D$17 -> 0.12359836 | F17: ='Data Sheet'!E28/'Data Sheet'!E$17 -> 0.067198831 | G17: ='Data Sheet'!F28/'Data Sheet'!F$17 -> 0.059337419 | H17: ='Data Sheet'!G28/'Data Sheet'!G$17 -> 0.059211265 | I17: ='Data Sheet'!H28/'Data Sheet'!H$17 -> 0.099021795 | J17: ='Data Sheet'!I28/'Data Sheet'!I$17 -> 0.093281084 | ... L17: ='Data Sheet'!K28/'Data Sheet'!K$17 -> 0.10629729
... B20: ='Data Sheet'!A31 -> Dividend Amount | C20: ='Data Sheet'!B31/'Data Sheet'!B$17 -> 0.012746673 | D20: ='Data Sheet'!C31/'Data Sheet'!C$17 -> 0.013101582 | E20: ='Data Sheet'!D31/'Data Sheet'!D$17 -> 0.011768324 | F20: ='Data Sheet'!E31/'Data Sheet'!E$17 -> 0.014390262 | G20: ='Data Sheet'!F31/'Data Sheet'!F$17 -> 0.015145867 | H20: ='Data Sheet'!G31/'Data Sheet'!G$17 -> 0.013061339 | I20: ='Data Sheet'!H31/'Data Sheet'!H$17 -> 0.011597363 | J20: ='Data Sheet'!I31/'Data Sheet'!I$17 -> 0.010400837 | ... L20: ='Data Sheet'!K31/'Data Sheet'!K$17 -> 0.012797021
B23: ="Common Size Balance Sheet - "& 'Data Sheet'!$B$1 -> Common Size Balance Sheet - TATA POWER COMPANY LTD
B25: Equity | C25: ='Historical Financial Statements'!C58/'Historical Financial Statements'!C$71 -> 0.0032597279 | D25: ='Historical Financial Statements'!D58/'Historical Financial Statements'!D$71 -> 0.0032970656 | E25: ='Historical Financial Statements'!E58/'Historical Financial Statements'!E$71 -> 0.0032114948 | F25: ='Historical Financial Statements'!F58/'Historical Financial Statements'!F$71 -> 0.0030109062 | G25: ='Historical Financial Statements'!G58/'Historical Financial Statements'!G$71 -> 0.0032436268 | H25: ='Historical Financial Statements'!H58/'Historical Financial Statements'!H$71 -> 0.0028431555 | I25: ='Historical Financial Statements'!I58/'Historical Financial Statements'!I$71 -> 0.0024981069 | J25: ='Historical Financial Statements'!J58/'Historical Financial Statements'!J$71 -> 0.0023012477 | ... L25: ='Historical Financial Statements'!L58/'Historical Financial Statements'!L$71 -> 0.0018331386
B26: Reservbes | C26: ='Historical Financial Statements'!C59/'Historical Financial Statements'!C$71 -> 0.15627377 | D26: ='Historical Financial Statements'!D59/'Historical Financial Statements'!D$71 -> 0.19696914 | E26: ='Historical Financial Statements'!E59/'Historical Financial Statements'!E$71 -> 0.21451596 | F26: ='Historical Financial Statements'!F59/'Historical Financial Statements'!F$71 -> 0.21519058 | G26: ='Historical Financial Statements'!G59/'Historical Financial Statements'!G$71 -> 0.22302975 | H26: ='Historical Financial Statements'!H59/'Historical Financial Statements'!H$71 -> 0.1965509 | I26: ='Historical Financial Statements'!I59/'Historical Financial Statements'!I$71 -> 0.22223784 | J26: ='Historical Financial Statements'!J59/'Historical Financial Statements'!J$71 -> 0.23039085 | ... L26: ='Historical Financial Statements'!L59/'Historical Financial Statements'!L$71 -> 0.22426159
B27: NON Current Liability
B28: Borrowings | C28: ='Historical Financial Statements'!C61/'Historical Financial Statements'!C$71 -> 0.58934673 | D28: ='Historical Financial Statements'!D61/'Historical Financial Statements'!D$71 -> 0.59333749 | E28: ='Historical Financial Statements'!E61/'Historical Financial Statements'!E$71 -> 0.57695098 | F28: ='Historical Financial Statements'!F61/'Historical Financial Statements'!F$71 -> 0.57916453 | G28: ='Historical Financial Statements'!G61/'Historical Financial Statements'!G$71 -> 0.47344787 | H28: ='Historical Financial Statements'!H61/'Historical Financial Statements'!H$71 -> 0.45486046 | I28: ='Historical Financial Statements'!I61/'Historical Financial Statements'!I$71 -> 0.41314785 | J28: ='Historical Financial Statements'!J61/'Historical Financial Statements'!J$71 -> 0.38609903 | ... L28: ='Historical Financial Statements'!L61/'Historical Financial Statements'!L$71 -> 0.43617814
B29: non Contolling Int | C29: ='Historical Financial Statements'!C62/'Historical Financial Statements'!C$71 -> 0.022564561 | D29: ='Historical Financial Statements'!D62/'Historical Financial Statements'!D$71 -> 0.024605879 | E29: ='Historical Financial Statements'!E62/'Historical Financial Statements'!E$71 -> 0.025775219 | F29: ='Historical Financial Statements'!F62/'Historical Financial Statements'!F$71 -> 0.026005308 | G29: ='Historical Financial Statements'!G62/'Historical Financial Statements'!G$71 -> 0.029669049 | H29: ='Historical Financial Statements'!H62/'Historical Financial Statements'!H$71 -> 0.031869997 | I29: ='Historical Financial Statements'!I62/'Historical Financial Statements'!I$71 -> 0.042288266 | J29: ='Historical Financial Statements'!J62/'Historical Financial Statements'!J$71 -> 0.042982992 | ... L29: ='Historical Financial Statements'!L62/'Historical Financial Statements'!L$71 -> 0.046235192
B30: Total Non current Liability | C30: ='Historical Financial Statements'!C63/'Historical Financial Statements'!C$71 -> 0.61191129 | D30: ='Historical Financial Statements'!D63/'Historical Financial Statements'!D$71 -> 0.61794336 | E30: ='Historical Financial Statements'!E63/'Historical Financial Statements'!E$71 -> 0.6027262 | F30: ='Historical Financial Statements'!F63/'Historical Financial Statements'!F$71 -> 0.60516984 | G30: ='Historical Financial Statements'!G63/'Historical Financial Statements'!G$71 -> 0.50311692 | H30: ='Historical Financial Statements'!H63/'Historical Financial Statements'!H$71 -> 0.48673046 | I30: ='Historical Financial Statements'!I63/'Historical Financial Statements'!I$71 -> 0.45543611 | J30: ='Historical Financial Statements'!J63/'Historical Financial Statements'!J$71 -> 0.42908202 | ... L30: ='Historical Financial Statements'!L63/'Historical Financial Statements'!L$71 -> 0.48241333
B32: Current Liabilities
B33: Trade Payables | C33: ='Historical Financial Statements'!C66/'Historical Financial Statements'!C$71 -> 0.066751983 | D33: ='Historical Financial Statements'!D66/'Historical Financial Statements'!D$71 -> 0.068505697 | E33: ='Historical Financial Statements'!E66/'Historical Financial Statements'!E$71 -> 0.065193344 | F33: ='Historical Financial Statements'!F66/'Historical Financial Statements'!F$71 -> 0.056816915 | G33: ='Historical Financial Statements'!G66/'Historical Financial Statements'!G$71 -> 0.072434241 | H33: ='Historical Financial Statements'!H66/'Historical Financial Statements'!H$71 -> 0.092935647 | I33: ='Historical Financial Statements'!I66/'Historical Financial Statements'!I$71 -> 0.057823368 | J33: ='Historical Financial Statements'!J66/'Historical Financial Statements'!J$71 -> 0.10134839 | ... L33: ='Historical Financial Statements'!L66/'Historical Financial Statements'!L$71 -> 0.061788227
B34: Advance from Customers | C34: ='Historical Financial Statements'!C67/'Historical Financial Statements'!C$71 -> 0.0049861763 | D34: ='Historical Financial Statements'!D67/'Historical Financial Statements'!D$71 -> 0.006826147 | E34: ='Historical Financial Statements'!E67/'Historical Financial Statements'!E$71 -> 0.0057687962 | F34: ='Historical Financial Statements'!F67/'Historical Financial Statements'!F$71 -> 0.0087204764 | G34: ='Historical Financial Statements'!G67/'Historical Financial Statements'!G$71 -> 0.012254827 | H34: ='Historical Financial Statements'!H67/'Historical Financial Statements'!H$71 -> 0.010484136 | I34: ='Historical Financial Statements'!I67/'Historical Financial Statements'!I$71 -> 0.019188584 | J34: ='Historical Financial Statements'!J67/'Historical Financial Statements'!J$71 -> 0.015799504 | ... L34: ='Historical Financial Statements'!L67/'Historical Financial Statements'!L$71 -> 0.0090511217
B35: Other liability items | C35: ='Historical Financial Statements'!C68/'Historical Financial Statements'!C$71 -> 0.15681706 | D35: ='Historical Financial Statements'!D68/'Historical Financial Statements'!D$71 -> 0.10645859 | E35: ='Historical Financial Statements'!E68/'Historical Financial Statements'!E$71 -> 0.10858421 | F35: ='Historical Financial Statements'!F68/'Historical Financial Statements'!F$71 -> 0.11109129 | G35: ='Historical Financial Statements'!G68/'Historical Financial Statements'!G$71 -> 0.18592063 | H35: ='Historical Financial Statements'!H68/'Historical Financial Statements'!H$71 -> 0.2104557 | I35: ='Historical Financial Statements'!I68/'Historical Financial Statements'!I$71 -> 0.24281599 | J35: ='Historical Financial Statements'!J68/'Historical Financial Statements'!J$71 -> 0.22107799 | ... L35: ='Historical Financial Statements'!L68/'Historical Financial Statements'!L$71 -> 0.2206526
B36: Total Current Liabilities | C36: ='Historical Financial Statements'!C69/'Historical Financial Statements'!C$71 -> 0.22855522 | D36: ='Historical Financial Statements'!D69/'Historical Financial Statements'!D$71 -> 0.18179043 | E36: ='Historical Financial Statements'!E69/'Historical Financial Statements'!E$71 -> 0.17954635 | F36: ='Historical Financial Statements'!F69/'Historical Financial Statements'!F$71 -> 0.17662868 | G36: ='Historical Financial Statements'!G69/'Historical Financial Statements'!G$71 -> 0.2706097 | H36: ='Historical Financial Statements'!H69/'Historical Financial Statements'!H$71 -> 0.31387549 | I36: ='Historical Financial Statements'!I69/'Historical Financial Statements'!I$71 -> 0.31982794 | J36: ='Historical Financial Statements'!J69/'Historical Financial Statements'!J$71 -> 0.33822588 | ... L36: ='Historical Financial Statements'!L69/'Historical Financial Statements'!L$71 -> 0.29149195
B38: Total Liability | C38: ='Historical Financial Statements'!C71/'Historical Financial Statements'!C71 -> 1 | D38: ='Historical Financial Statements'!D71/'Historical Financial Statements'!D71 -> 1 | E38: ='Historical Financial Statements'!E71/'Historical Financial Statements'!E71 -> 1 | F38: ='Historical Financial Statements'!F71/'Historical Financial Statements'!F71 -> 1 | G38: ='Historical Financial Statements'!G71/'Historical Financial Statements'!G71 -> 1 | H38: ='Historical Financial Statements'!H71/'Historical Financial Statements'!H71 -> 1 | I38: ='Historical Financial Statements'!I71/'Historical Financial Statements'!I71 -> 1 | J38: ='Historical Financial Statements'!J71/'Historical Financial Statements'!J71 -> 1 | ... L38: ='Historical Financial Statements'!L71/'Historical Financial Statements'!L71 -> 1
B40: Current Assets
B41: Inventories | C41: ='Historical Financial Statements'!C74/'Historical Financial Statements'!C$98 -> 0.019316906 | D41: ='Historical Financial Statements'!D74/'Historical Financial Statements'!D$98 -> 0.019819028 | E41: ='Historical Financial Statements'!E74/'Historical Financial Statements'!E$98 -> 0.020291889 | F41: ='Historical Financial Statements'!F74/'Historical Financial Statements'!F$98 -> 0.019537436 | G41: ='Historical Financial Statements'!G74/'Historical Financial Statements'!G$98 -> 0.019117125 | H41: ='Historical Financial Statements'!H74/'Historical Financial Statements'!H$98 -> 0.037600732 | I41: ='Historical Financial Statements'!I74/'Historical Financial Statements'!I$98 -> 0.030781361 | J41: ='Historical Financial Statements'!J74/'Historical Financial Statements'!J$98 -> 0.031785984 | ... L41: ='Historical Financial Statements'!L74/'Historical Financial Statements'!L$98 -> 0.029261474
B42: Trade receivables | C42: ='Historical Financial Statements'!C75/'Historical Financial Statements'!C$98 -> 0.04626399 | D42: ='Historical Financial Statements'!D75/'Historical Financial Statements'!D$98 -> 0.034057467 | E42: ='Historical Financial Statements'!E75/'Historical Financial Statements'!E$98 -> 0.052870719 | F42: ='Historical Financial Statements'!F75/'Historical Financial Statements'!F$98 -> 0.049356558 | G42: ='Historical Financial Statements'!G75/'Historical Financial Statements'!G$98 -> 0.052708935 | H42: ='Historical Financial Statements'!H75/'Historical Financial Statements'!H$98 -> 0.053131469 | I42: ='Historical Financial Statements'!I75/'Historical Financial Statements'!I$98 -> 0.054271372 | J42: ='Historical Financial Statements'!J75/'Historical Financial Statements'!J$98 -> 0.053230736 | ... L42: ='Historical Financial Statements'!L75/'Historical Financial Statements'!L$98 -> 0.025343141
B43: Loans n Advances | C43: ='Historical Financial Statements'!C76/'Historical Financial Statements'!C$98 -> 0.0047688611 | D43: ='Historical Financial Statements'!D76/'Historical Financial Statements'!D$98 -> 0.0059835635 | E43: ='Historical Financial Statements'!E76/'Historical Financial Statements'!E$98 -> 0.005959107 | F43: ='Historical Financial Statements'!F76/'Historical Financial Statements'!F$98 -> 0.0061556304 | G43: ='Historical Financial Statements'!G76/'Historical Financial Statements'!G$98 -> 0.0061730272 | H43: ='Historical Financial Statements'!H76/'Historical Financial Statements'!H$98 -> 0.0078808718 | I43: ='Historical Financial Statements'!I76/'Historical Financial Statements'!I$98 -> 0.0084233042 | J43: ='Historical Financial Statements'!J76/'Historical Financial Statements'!J$98 -> 0.0081550466 | ... L43: ='Historical Financial Statements'!L76/'Historical Financial Statements'!L$98 -> 0.0026408652
B44: Other asset items | C44: ='Historical Financial Statements'!C77/'Historical Financial Statements'!C$98 -> 0.18594937 | D44: ='Historical Financial Statements'!D77/'Historical Financial Statements'!D$98 -> 0.20839897 | E44: ='Historical Financial Statements'!E77/'Historical Financial Statements'!E$98 -> 0.19282053 | F44: ='Historical Financial Statements'!F77/'Historical Financial Statements'!F$98 -> 0.18998818 | G44: ='Historical Financial Statements'!G77/'Historical Financial Statements'!G$98 -> 0.16715828 | H44: ='Historical Financial Statements'!H77/'Historical Financial Statements'!H$98 -> 0.16549831 | I44: ='Historical Financial Statements'!I77/'Historical Financial Statements'!I$98 -> 0.16489848 | J44: ='Historical Financial Statements'!J77/'Historical Financial Statements'!J$98 -> 0.15721118 | ... L44: ='Historical Financial Statements'!L77/'Historical Financial Statements'!L$98 -> 0.18597764
B45: Cash Equivalents | C45: ='Historical Financial Statements'!C78/'Historical Financial Statements'!C$98 -> 0.011517705 | D45: ='Historical Financial Statements'!D78/'Historical Financial Statements'!D$98 -> 0.014482666 | E45: ='Historical Financial Statements'!E78/'Historical Financial Statements'!E$98 -> 0.0093609125 | F45: ='Historical Financial Statements'!F78/'Historical Financial Statements'!F$98 -> 0.02335125 | G45: ='Historical Financial Statements'!G78/'Historical Financial Statements'!G$98 -> 0.059510415 | H45: ='Historical Financial Statements'!H78/'Historical Financial Statements'!H$98 -> 0.059004362 | I45: ='Historical Financial Statements'!I78/'Historical Financial Statements'!I$98 -> 0.087488388 | J45: ='Historical Financial Statements'!J78/'Historical Financial Statements'!J$98 -> 0.065815684 | ... L45: ='Historical Financial Statements'!L78/'Historical Financial Statements'!L$98 -> 0.078160445
B46: Total Current Assets | C46: ='Historical Financial Statements'!C79/'Historical Financial Statements'!C$98 -> 0.26781683 | D46: ='Historical Financial Statements'!D79/'Historical Financial Statements'!D$98 -> 0.28274169 | E46: ='Historical Financial Statements'!E79/'Historical Financial Statements'!E$98 -> 0.28130315 | F46: ='Historical Financial Statements'!F79/'Historical Financial Statements'!F$98 -> 0.28838905 | G46: ='Historical Financial Statements'!G79/'Historical Financial Statements'!G$98 -> 0.30466778 | H46: ='Historical Financial Statements'!H79/'Historical Financial Statements'!H$98 -> 0.32311574 | I46: ='Historical Financial Statements'!I79/'Historical Financial Statements'!I$98 -> 0.3458629 | J46: ='Historical Financial Statements'!J79/'Historical Financial Statements'!J$98 -> 0.31619863 | ... L46: ='Historical Financial Statements'!L79/'Historical Financial Statements'!L$98 -> 0.32138356
B48: NON Current Assets
B49: Land | C49: ='Historical Financial Statements'!C82/'Historical Financial Statements'!C$98 -> 0.013026838 | D49: ='Historical Financial Statements'!D82/'Historical Financial Statements'!D$98 -> 0.011893859 | E49: ='Historical Financial Statements'!E82/'Historical Financial Statements'!E$98 -> 0.012275047 | F49: ='Historical Financial Statements'!F82/'Historical Financial Statements'!F$98 -> 0.023094765 | G49: ='Historical Financial Statements'!G82/'Historical Financial Statements'!G$98 -> 0.022158025 | H49: ='Historical Financial Statements'!H82/'Historical Financial Statements'!H$98 -> 0.020293023 | I49: ='Historical Financial Statements'!I82/'Historical Financial Statements'!I$98 -> 0.020859193 | J49: ='Historical Financial Statements'!J82/'Historical Financial Statements'!J$98 -> 0.02410557 | ... L49: ='Historical Financial Statements'!L82/'Historical Financial Statements'!L$98 -> 0.027485621
B50: Building | C50: ='Historical Financial Statements'!C83/'Historical Financial Statements'!C$98 -> 0.033708001 | D50: ='Historical Financial Statements'!D83/'Historical Financial Statements'!D$98 -> 0.035486195 | E50: ='Historical Financial Statements'!E83/'Historical Financial Statements'!E$98 -> 0.034945821 | F50: ='Historical Financial Statements'!F83/'Historical Financial Statements'!F$98 -> 0.0341013 | G50: ='Historical Financial Statements'!G83/'Historical Financial Statements'!G$98 -> 0.038781613 | H50: ='Historical Financial Statements'!H83/'Historical Financial Statements'!H$98 -> 0.035921493 | I50: ='Historical Financial Statements'!I83/'Historical Financial Statements'!I$98 -> 0.034598781 | J50: ='Historical Financial Statements'!J83/'Historical Financial Statements'!J$98 -> 0.03238287 | ... L50: ='Historical Financial Statements'!L83/'Historical Financial Statements'!L$98 -> 0.035677459
B51: Plant Machinery | C51: ='Historical Financial Statements'!C84/'Historical Financial Statements'!C$98 -> 0.53138394 | D51: ='Historical Financial Statements'!D84/'Historical Financial Statements'!D$98 -> 0.5362494 | E51: ='Historical Financial Statements'!E84/'Historical Financial Statements'!E$98 -> 0.53434515 | F51: ='Historical Financial Statements'!F84/'Historical Financial Statements'!F$98 -> 0.52886009 | G51: ='Historical Financial Statements'!G84/'Historical Financial Statements'!G$98 -> 0.49269677 | H51: ='Historical Financial Statements'!H84/'Historical Financial Statements'!H$98 -> 0.46791232 | I51: ='Historical Financial Statements'!I84/'Historical Financial Statements'!I$98 -> 0.43559958 | J51: ='Historical Financial Statements'!J84/'Historical Financial Statements'!J$98 -> 0.43090144 | ... L51: ='Historical Financial Statements'!L84/'Historical Financial Statements'!L$98 -> 0.42471529
B52: Equipments | C52: ='Historical Financial Statements'!C85/'Historical Financial Statements'!C$98 -> 0.064192493 | D52: ='Historical Financial Statements'!D85/'Historical Financial Statements'!D$98 -> 0.07097239 | E52: ='Historical Financial Statements'!E85/'Historical Financial Statements'!E$98 -> 0.075696121 | F52: ='Historical Financial Statements'!F85/'Historical Financial Statements'!F$98 -> 0.077692531 | G52: ='Historical Financial Statements'!G85/'Historical Financial Statements'!G$98 -> 0.11950737 | H52: ='Historical Financial Statements'!H85/'Historical Financial Statements'!H$98 -> 0.13504989 | I52: ='Historical Financial Statements'!I85/'Historical Financial Statements'!I$98 -> 0.14430471 | J52: ='Historical Financial Statements'!J85/'Historical Financial Statements'!J$98 -> 0.15890835 | ... L52: ='Historical Financial Statements'!L85/'Historical Financial Statements'!L$98 -> 0.18631562
B53: Furniture n fittings | C53: ='Historical Financial Statements'!C86/'Historical Financial Statements'!C$98 -> 0.0016540101 | D53: ='Historical Financial Statements'!D86/'Historical Financial Statements'!D$98 -> 0.0014897852 | E53: ='Historical Financial Statements'!E86/'Historical Financial Statements'!E$98 -> 0.001427331 | F53: ='Historical Financial Statements'!F86/'Historical Financial Statements'!F$98 -> 0.0013158775 | G53: ='Historical Financial Statements'!G86/'Historical Financial Statements'!G$98 -> 0.0013582687 | H53: ='Historical Financial Statements'!H86/'Historical Financial Statements'!H$98 -> 0.00127942 | I53: ='Historical Financial Statements'!I86/'Historical Financial Statements'!I$98 -> 0.0013036995 | J53: ='Historical Financial Statements'!J86/'Historical Financial Statements'!J$98 -> 0.0013447916 | ... L53: ='Historical Financial Statements'!L86/'Historical Financial Statements'!L$98 -> 0.0012144543
B54: Railway sidings | C54: ='Historical Financial Statements'!C87/'Historical Financial Statements'!C$98 -> 0.0011590144 | D54: ='Historical Financial Statements'!D87/'Historical Financial Statements'!D$98 -> 0.0012089241 | E54: ='Historical Financial Statements'!E87/'Historical Financial Statements'!E$98 -> 0.0012251258 | F54: ='Historical Financial Statements'!F87/'Historical Financial Statements'!F$98 -> 0.0011597565 | G54: ='Historical Financial Statements'!G87/'Historical Financial Statements'!G$98 -> 0 | H54: ='Historical Financial Statements'!H87/'Historical Financial Statements'!H$98 -> 0 | I54: ='Historical Financial Statements'!I87/'Historical Financial Statements'!I$98 -> 0 | J54: ='Historical Financial Statements'!J87/'Historical Financial Statements'!J$98 -> 0 | ... L54: ='Historical Financial Statements'!L87/'Historical Financial Statements'!L$98 -> 0
B55: Vehicles | C55: ='Historical Financial Statements'!C88/'Historical Financial Statements'!C$98 -> 0.0026560746 | D55: ='Historical Financial Statements'!D88/'Historical Financial Statements'!D$98 -> 0.0030528385 | E55: ='Historical Financial Statements'!E88/'Historical Financial Statements'!E$98 -> 0.0029141341 | F55: ='Historical Financial Statements'!F88/'Historical Financial Statements'!F$98 -> 0.0026206035 | G55: ='Historical Financial Statements'!G88/'Historical Financial Statements'!G$98 -> 0.0023110841 | H55: ='Historical Financial Statements'!H88/'Historical Financial Statements'!H$98 -> 0.0019990937 | I55: ='Historical Financial Statements'!I88/'Historical Financial Statements'!I$98 -> 0.0019282263 | J55: ='Historical Financial Statements'!J88/'Historical Financial Statements'!J$98 -> 0.0021574197 | ... L55: ='Historical Financial Statements'!L88/'Historical Financial Statements'!L$98 -> 0.002022181
B56: Intangible Assets | C56: ='Historical Financial Statements'!C89/'Historical Financial Statements'!C$98 -> 0.021345181 | D56: ='Historical Financial Statements'!D89/'Historical Financial Statements'!D$98 -> 0.020344116 | E56: ='Historical Financial Statements'!E89/'Historical Financial Statements'!E$98 -> 0.019673379 | F56: ='Historical Financial Statements'!F89/'Historical Financial Statements'!F$98 -> 0.018355376 | G56: ='Historical Financial Statements'!G89/'Historical Financial Statements'!G$98 -> 0.018245401 | H56: ='Historical Financial Statements'!H89/'Historical Financial Statements'!H$98 -> 0.016561381 | I56: ='Historical Financial Statements'!I89/'Historical Financial Statements'!I$98 -> 0.014559279 | J56: ='Historical Financial Statements'!J89/'Historical Financial Statements'!J$98 -> 0.013685232 | ... L56: ='Historical Financial Statements'!L89/'Historical Financial Statements'!L$98 -> 0.0097270915
B57: Other fixed assets | C57: ='Historical Financial Statements'!C90/'Historical Financial Statements'!C$98 -> 0.050839682 | D57: ='Historical Financial Statements'!D90/'Historical Financial Statements'!D$98 -> 0.052081425 | E57: ='Historical Financial Statements'!E90/'Historical Financial Statements'!E$98 -> 0.050349101 | F57: ='Historical Financial Statements'!F90/'Historical Financial Statements'!F$98 -> 0.060675335 | G57: ='Historical Financial Statements'!G90/'Historical Financial Statements'!G$98 -> 0.056601287 | H57: ='Historical Financial Statements'!H90/'Historical Financial Statements'!H$98 -> 0.052207444 | I57: ='Historical Financial Statements'!I90/'Historical Financial Statements'!I$98 -> 0.048627212 | J57: ='Historical Financial Statements'!J90/'Historical Financial Statements'!J$98 -> 0.046880731 | ... L57: ='Historical Financial Statements'!L90/'Historical Financial Statements'!L$98 -> 0.039865035
B58: Gross Block | C58: ='Historical Financial Statements'!C91/'Historical Financial Statements'!C$98 -> 0.71996523 | D58: ='Historical Financial Statements'!D91/'Historical Financial Statements'!D$98 -> 0.73277894 | E58: ='Historical Financial Statements'!E91/'Historical Financial Statements'!E$98 -> 0.73285121 | F58: ='Historical Financial Statements'!F91/'Historical Financial Statements'!F$98 -> 0.74787564 | G58: ='Historical Financial Statements'!G91/'Historical Financial Statements'!G$98 -> 0.75165982 | H58: ='Historical Financial Statements'!H91/'Historical Financial Statements'!H$98 -> 0.73122407 | I58: ='Historical Financial Statements'!I91/'Historical Financial Statements'!I$98 -> 0.70178068 | J58: ='Historical Financial Statements'!J91/'Historical Financial Statements'!J$98 -> 0.7103664 | ... L58: ='Historical Financial Statements'!L91/'Historical Financial Statements'!L$98 -> 0.72702275
B59: Accumulated Depreciation | C59: ='Historical Financial Statements'!C92/'Historical Financial Statements'!C$98 -> 0.15743278 | D59: ='Historical Financial Statements'!D92/'Historical Financial Statements'!D$98 -> 0.18746871 | E59: ='Historical Financial Statements'!E92/'Historical Financial Statements'!E$98 -> 0.20586871 | F59: ='Historical Financial Statements'!F92/'Historical Financial Statements'!F$98 -> 0.21631688 | G59: ='Historical Financial Statements'!G92/'Historical Financial Statements'!G$98 -> 0.22275607 | H59: ='Historical Financial Statements'!H92/'Historical Financial Statements'!H$98 -> 0.22133077 | I59: ='Historical Financial Statements'!I92/'Historical Financial Statements'!I$98 -> 0.21975534 | J59: ='Historical Financial Statements'!J92/'Historical Financial Statements'!J$98 -> 0.22703966 | ... L59: ='Historical Financial Statements'!L92/'Historical Financial Statements'!L$98 -> 0.22696547
B60: Fixed Assetcs net Block | C60: ='Historical Financial Statements'!C93/'Historical Financial Statements'!C$98 -> 0.56253245 | D60: ='Historical Financial Statements'!D93/'Historical Financial Statements'!D$98 -> 0.54531023 | E60: ='Historical Financial Statements'!E93/'Historical Financial Statements'!E$98 -> 0.5269825 | F60: ='Historical Financial Statements'!F93/'Historical Financial Statements'!F$98 -> 0.53155876 | G60: ='Historical Financial Statements'!G93/'Historical Financial Statements'!G$98 -> 0.52890376 | H60: ='Historical Financial Statements'!H93/'Historical Financial Statements'!H$98 -> 0.50989329 | I60: ='Historical Financial Statements'!I93/'Historical Financial Statements'!I$98 -> 0.48202534 | J60: ='Historical Financial Statements'!J93/'Historical Financial Statements'!J$98 -> 0.48332674 | ... L60: ='Historical Financial Statements'!L93/'Historical Financial Statements'!L$98 -> 0.50005729
... B63: Total Non current Assets | C63: ='Historical Financial Statements'!C96/'Historical Financial Statements'!C$98 -> 0.73218317 | D63: ='Historical Financial Statements'!D96/'Historical Financial Statements'!D$98 -> 0.71725831 | E63: ='Historical Financial Statements'!E96/'Historical Financial Statements'!E$98 -> 0.71869685 | F63: ='Historical Financial Statements'!F96/'Historical Financial Statements'!F$98 -> 0.71161095 | G63: ='Historical Financial Statements'!G96/'Historical Financial Statements'!G$98 -> 0.69533222 | H63: ='Historical Financial Statements'!H96/'Historical Financial Statements'!H$98 -> 0.67688426 | I63: ='Historical Financial Statements'!I96/'Historical Financial Statements'!I$98 -> 0.6541371 | J63: ='Historical Financial Statements'!J96/'Historical Financial Statements'!J$98 -> 0.68380137 | ... L63: ='Historical Financial Statements'!L96/'Historical Financial Statements'!L$98 -> 0.67861644
B65: Total Assets | C65: ='Historical Financial Statements'!C98/'Historical Financial Statements'!C98 -> 1 | D65: ='Historical Financial Statements'!D98/'Historical Financial Statements'!D98 -> 1 | E65: ='Historical Financial Statements'!E98/'Historical Financial Statements'!E98 -> 1 | F65: ='Historical Financial Statements'!F98/'Historical Financial Statements'!F98 -> 1 | G65: ='Historical Financial Statements'!G98/'Historical Financial Statements'!G98 -> 1 | H65: ='Historical Financial Statements'!H98/'Historical Financial Statements'!H98 -> 1 | I65: ='Historical Financial Statements'!I98/'Historical Financial Statements'!I98 -> 1 | J65: ='Historical Financial Statements'!J98/'Historical Financial Statements'!J98 -> 1 | ... L65: ='Historical Financial Statements'!L98/'Historical Financial Statements'!L98 -> 1

Sheet DCF ->

Sheet Beta Regression Historical Data
B2: Nifty 50 | K2: Tata Power Ltd.
B3: Date | C3: Price | D3: Open | E3: High | F3: Low | G3: Vol. | H3: Change % | K3: Date | L3: Price | M3: Open | N3: High | O3: Low | P3: Volume | Q3: Change %
B4: 46187 | C4: 24013.1 | D4: 23984.85 | E4: 24189.25 | F4: 23817.8 | G4: 1.87B | H4: 0.0165 | K4: 46187 | L4: 402.35 | M4: 397.75 | N4: 405.6 | O4: 395.55 | P4: 32.8 | Q4: 0.0224
B5: 46180 | C5: 23622.9 | D5: 23080.7 | E5: 23645.35 | F5: 23070.15 | G5: 1.87B | H5: 0.011 | K5: 46180 | L5: 393.55 | M5: 404.05 | N5: 409.1 | O5: 388 | P5: 23.94 | Q5: -0.0382
B6: 46173 | C6: 23366.7 | D6: 23654.5 | E6: 23733.7 | F6: 23151.5 | G6: 2.16B | H6: -0.0077 | K6: 46173 | L6: 409.2 | M6: 421.7 | N6: 423.75 | O6: 406.55 | P6: 20.9 | Q6: -0.0275
B7: 46166 | C7: 23547.75 | D7: 23940.25 | E7: 24089.8 | F7: 23484.75 | G7: 2.47B | H7: -0.0072 | K7: 46166 | L7: 420.75 | M7: 411.25 | N7: 434 | O7: 409.4 | P7: 27.34 | Q7: 0.029 | S7: Beta | T7: =V36 -> 1.2649327
B8: 46159 | C8: 23719.3 | D8: 23482.2 | E8: 23859.9 | F8: 23317.1 | G8: 1.86B | H8: 0.0032 | K8: 46159 | L8: 408.9 | M8: 404.6 | N8: 418.5 | O8: 395.95 | P8: 27.27 | Q8: 0.0047 | S8: Correlation | T8: =V22 -> 0.60117531
B9: 46152 | C9: 23643.5 | D9: 23970.1 | E9: 23997.45 | F9: 23262.55 | G9: 2.09B | H9: -0.022 | K9: 46152 | L9: 407 | M9: 434 | N9: 437.95 | O9: 390.8 | P9: 42.08 | Q9: -0.0665
B10: 46145 | C10: 24176.15 | D10: 24063.55 | E10: 24482.1 | F10: 23882.05 | G10: 1.99B | H10: 0.0074 | K10: 46145 | L10: 436 | M10: 445.5 | N10: 448 | O10: 434.7 | P10: 25.5 | Q10: -0.0192
B11: 46138 | C11: 23997.55 | D11: 23945.45 | E11: 24334.7 | F11: 23796.85 | G11: 2.02B | H11: 0.0042 | K11: 46138 | L11: 444.55 | M11: 436.6 | N11: 464.9 | O11: 435.2 | P11: 46.09 | Q11: 0.022
B12: 46131 | C12: 23897.95 | D12: 24391.5 | E12: 24601.7 | F12: 23813.65 | G12: 2.19B | H12: -0.0187 | K12: 46131 | L12: 435 | M12: 427.5 | N12: 440.8 | O12: 424.45 | P12: 42.75 | Q12: 0.0173
B13: 46124 | C13: 24353.55 | D13: 23589.6 | E13: 24400.95 | F13: 23555.6 | G13: 1.96B | H13: 0.0126 | K13: 46124 | L13: 427.6 | M13: 394.95 | N13: 432 | O13: 390.25 | P13: 59.7 | Q13: 0.0707
B14: 46117 | C14: 24050.6 | D14: 22780.3 | E14: 24074.05 | F14: 22542.95 | G14: 2.49B | H14: 0.0589 | K14: 46117 | L14: 399.35 | M14: 385.05 | N14: 401.35 | O14: 378.45 | P14: 33.04 | Q14: 0.0373
B15: 46110 | C15: 22713.1 | D15: 22549.65 | E15: 22941.3 | F15: 22182.55 | G15: 1.71B | H15: -0.0047 | K15: 46110 | L15: 385 | M15: 381 | N15: 390.9 | O15: 368 | P15: 25.05 | Q15: -0.0018
B16: 46103 | C16: 22819.6 | D16: 22824.35 | E16: 23465.35 | F16: 22471.25 | G16: 2.21B | H16: -0.0128 | K16: 46103 | L16: 385.7 | M16: 402.7 | N16: 403.3 | O16: 373 | P16: 41.8 | Q16: -0.0415
B17: 46096 | C17: 23114.5 | D17: 23116.1 | E17: 23862.25 | F17: 22930.35 | G17: 2.60B | H17: -0.0016 | K17: 46096 | L17: 402.4 | M17: 395.55 | N17: 418.45 | O17: 385 | P17: 60.74 | Q17: 0.0189
B18: 46089 | C18: 23151.1 | D18: 23868.05 | E18: 24303.8 | F18: 23112 | G18: 2.40B | H18: -0.0531 | K18: 46089 | L18: 394.95 | M18: 366.5 | N18: 407.35 | O18: 365.15 | P18: 56.5 | Q18: 0.0518
B19: 46082 | C19: 24450.45 | D19: 24659.25 | E19: 24989.35 | F19: 24305.4 | G19: 2.06B | H19: -0.0289 | K19: 46082 | L19: 375.5 | M19: 356 | N19: 385.25 | O19: 356 | P19: 21.08 | Q19: -0.0054 | U19: SUMMARY OUTPUT
B20: 46075 | C20: 25178.65 | D20: 25678.4 | E20: 25771.45 | F20: 25141.3 | G20: 2.01B | H20: -0.0154 | K20: 46075 | L20: 377.55 | M20: 379 | N20: 385.4 | O20: 372.5 | P20: 15.75 | Q20: -0.0012
B21: 46068 | C21: 25571.25 | D21: 25423.6 | E21: 25885.3 | F21: 25372.7 | G21: 1.52B | H21: 0.0039 | K21: 46068 | L21: 378 | M21: 372 | N21: 384.25 | O21: 368.3 | P21: 15.88 | Q21: 0.0104 | U21: Regression Statistics
B22: 46061 | C22: 25471.1 | D22: 25888.7 | E22: 26009.4 | F22: 25444.3 | G22: 2.02B | H22: -0.0087 | K22: 46061 | L22: 374.1 | M22: 367 | N22: 381.5 | O22: 365.1 | P22: 18.7 | Q22: 0.0223 | U22: Multiple R | V22: 0.60117531
B23: 46054 | C23: 25693.7 | D23: 25333.75 | E23: 26341.2 | F23: 24571.75 | G23: 2.61B | H23: 0.0147 | K23: 46054 | L23: 365.95 | M23: 367.7 | N23: 372.25 | O23: 348.4 | P23: 22.76 | Q23: -0.001 | U23: R Square | V23: 0.36141175
B24: 46047 | C24: 25320.65 | D24: 25063.35 | E24: 25458.15 | F24: 24932.55 | G24: 2.28B | H24: 0.0109 | K24: 46047 | L24: 366.3 | M24: 345.7 | N24: 367.5 | O24: 342.5 | P24: 21.13 | Q24: 0.061 | U24: Adjusted R Square | V24: 0.35515108
B25: 46040 | C25: 25048.65 | D25: 25653.1 | E25: 25653.3 | F25: 24919.8 | G25: 2.13B | H25: -0.0251 | K25: 46040 | L25: 345.25 | M25: 366.1 | N25: 368.7 | O25: 344.1 | P25: 16.05 | Q25: -0.057 | U25: Standard Error | V25: 0.030878343
B26: 46033 | C26: 25694.35 | D26: 25669.05 | E26: 25899.8 | F26: 25473.4 | G26: 1.44B | H26: 0.0004 | K26: 46033 | L26: 366.1 | M26: 364.8 | N26: 372.35 | O26: 360.1 | P26: 15.64 | Q26: 0.0036 | U26: Observations | V26: 104
B27: 46026 | C27: 25683.3 | D27: 26333.7 | E27: 26373.2 | F27: 25623 | G27: 1.74B | H27: -0.0245 | K27: 46026 | L27: 364.8 | M27: 392.5 | N27: 393 | O27: 362.95 | P27: 21.46 | Q27: -0.072
B28: 46019 | C28: 26328.55 | D28: 26063.35 | E28: 26340 | F28: 25878 | G28: 1.66B | H28: 0.011 | K28: 46019 | L28: 393.1 | M28: 379 | N28: 393.65 | O28: 372.7 | P28: 20.97 | Q28: 0.0357 | U28: ANOVA
B29: 46012 | C29: 26042.3 | D29: 26055.85 | E29: 26236.4 | F29: 26008.6 | G29: 800.63M | H29: 0.0029 | K29: 46012 | L29: 379.55 | M29: 381 | N29: 383.7 | O29: 378.1 | P29: 13.29 | Q29: -0.0026 | V29: df | W29: SS | X29: MS | Y29: F | Z29: Significance F
B30: 46005 | C30: 25966.4 | D30: 25930.05 | E30: 26047.15 | F30: 25726.3 | G30: 1.23B | H30: -0.0031 | K30: 46005 | L30: 380.55 | M30: 380 | N30: 383.3 | O30: 373 | P30: 15.42 | Q30: -0.0037 | U30: Regression | V30: 1 | W30: 0.055041403 | X30: 0.055041403 | Y30: 57.727336 | Z30: 1.5022671e-11
B31: 45998 | C31: 26046.95 | D31: 26159.8 | E31: 26178.7 | F31: 25693.25 | G31: 1.23B | H31: -0.0053 | K31: 45998 | L31: 381.95 | M31: 383.2 | N31: 385.25 | O31: 369.8 | P31: 25.51 | Q31: -0.0066 | U31: Residual | V31: 102 | W31: 0.097254153 | X31: 0.00095347209
B32: 45991 | C32: 26186.45 | D32: 26325.8 | E32: 26325.8 | F32: 25891 | G32: 1.23B | H32: -0.0006 | K32: 45991 | L32: 384.5 | M32: 390.65 | N32: 393 | O32: 380.55 | P32: 19.73 | Q32: -0.0144 | U32: Total | V32: 103 | W32: 0.15229556
B33: 45984 | C33: 26202.95 | D33: 26122.8 | E33: 26310.45 | F33: 25842.95 | G33: 1.44B | H33: 0.0052 | K33: 45984 | L33: 390.1 | M33: 390 | N33: 399.95 | O33: 379 | P33: 26.15 | Q33: 0.008
B34: 45977 | C34: 26068.15 | D34: 25948.2 | E34: 26246.65 | F34: 25856.2 | G34: 1.29B | H34: 0.0061 | K34: 45977 | L34: 387 | M34: 388.5 | N34: 394 | O34: 384.2 | P34: 21.96 | Q34: -0.0036 | V34: Coefficients | W34: Standard Error | X34: t Stat | Y34: P-value | Z34: Lower 95% | AA34: Upper 95% | AB34: Lower 95.0% | AC34: Upper 95.0%
B35: 45970 | C35: 25910.05 | D35: 25503.5 | E35: 26010.7 | F35: 25449.25 | G35: 1.76B | H35: 0.0164 | K35: 45970 | L35: 388.4 | M35: 393.2 | N35: 397.9 | O35: 385 | P35: 24.91 | Q35: -0.0122 | U35: Intercept | V35: -0.00056736425 | W35: 0.003028511 | X35: -0.18734099 | Y35: 0.85176544 | Z35: -0.0065744014 | AA35: 0.0054396729 | AB35: -0.0065744014 | AC35: 0.0054396729
B36: 45963 | C36: 25492.3 | D36: 25696.85 | E36: 25803.1 | F36: 25318.45 | G36: 1.01B | H36: -0.0089 | K36: 45963 | L36: 393.2 | M36: 403.85 | N36: 409.5 | O36: 386 | P36: 20 | Q36: -0.0289 | U36: X Variable 1 | V36: 1.2649327 | W36: 0.1664856 | X36: 7.5978507 | Y36: 1.5022671e-11 | Z36: 0.93470932 | AA36: 1.5951561 | AB36: 0.93470932 | AC36: 1.5951561
B37: 45956 | C37: 25722.1 | D37: 25843.2 | E37: 26097.85 | F37: 25711.2 | G37: 1.58B | H37: -0.0028 | K37: 45956 | L37: 404.9 | M37: 396.9 | N37: 413.25 | O37: 395.65 | P37: 26.55 | Q37: 0.0203
B38: 45949 | C38: 25795.15 | D38: 25824.6 | E38: 26104.2 | F38: 25718.2 | G38: 1.08B | H38: 0.0033 | K38: 45949 | L38: 396.85 | M38: 398.3 | N38: 403.85 | O38: 394 | P38: 15.11 | Q38: -0.0024
B39: 45942 | C39: 25709.85 | D39: 25177.3 | E39: 25781.5 | F39: 25060.55 | G39: 1.61B | H39: 0.0168 | K39: 45942 | L39: 397.8 | M39: 388 | N39: 402.8 | O39: 385.25 | P39: 24.54 | Q39: 0.0197
B40: 45935 | C40: 25285.35 | D40: 24916.55 | E40: 25330.75 | F40: 24881.65 | G40: 1.30B | H40: 0.0157 | K40: 45935 | L40: 390.1 | M40: 394.9 | N40: 397.5 | O40: 381.5 | P40: 27.89 | Q40: -0.0122
B41: 45928 | C41: 24894.25 | D41: 24728.55 | E41: 24904.8 | F41: 24587.7 | G41: 1.37B | H41: 0.0097 | K41: 45928 | L41: 394.9 | M41: 384.25 | N41: 395.5 | O41: 383.25 | P41: 13.68 | Q41: 0.0289
B42: 45921 | C42: 24654.7 | D42: 25238.1 | E42: 25331.7 | F42: 24629.45 | G42: 1.43B | H42: -0.0265 | K42: 45921 | L42: 383.8 | M42: 396 | N42: 399.9 | O42: 382.2 | P42: 17.12 | Q42: -0.0315
B43: 45914 | C43: 25327.05 | D43: 25118.9 | E43: 25448.95 | F43: 25048.75 | G43: 1.35B | H43: 0.0085 | K43: 45914 | L43: 396.3 | M43: 386 | N43: 399.8 | O43: 385.5 | P43: 27.58 | Q43: 0.026
B44: 45907 | C44: 25114 | D44: 24802.6 | E44: 25139.45 | F44: 24751.55 | G44: 1.13B | H44: 0.0151 | K44: 45907 | L44: 386.25 | M44: 385.8 | N44: 390.95 | O44: 381.15 | P44: 16.83 | Q44: 0.0012
B45: 45900 | C45: 24741 | D45: 24432.7 | E45: 24980.75 | F45: 24432.7 | G45: 1.37B | H45: 0.0129 | K45: 45900 | L45: 385.8 | M45: 374.15 | N45: 392 | O45: 374.15 | P45: 15.63 | Q45: 0.0311
B46: 45893 | C46: 24426.85 | D46: 24949.15 | E46: 25021.55 | F46: 24404.7 | G46: 1.62B | H46: -0.0178 | K46: 45893 | L46: 374.15 | M46: 386.05 | N46: 388.4 | O46: 368.5 | P46: 21.28 | Q46: -0.0297
B47: 45886 | C47: 24870.1 | D47: 24938.2 | E47: 25153.65 | F47: 24852.85 | G47: 1.34B | H47: 0.0097 | K47: 45886 | L47: 385.6 | M47: 389 | N47: 392.45 | O47: 384.7 | P47: 14.4 | Q47: 0.0008
B48: 45879 | C48: 24631.3 | D48: 24371.5 | E48: 24702.6 | F48: 24347.45 | G48: 984.32M | H48: 0.011 | K48: 45879 | L48: 385.3 | M48: 380 | N48: 388.95 | O48: 377.5 | P48: 12.32 | Q48: 0.0172
... B107: 45466 | C107: 24010.6 | D107: 23382.3 | E107: 24174 | F107: 23350 | G107: 1.70B | H107: 0.0217 | K107: 45466 | L107: 440.6 | M107: 436 | N107: 444.45 | O107: 426.5 | P107: 54.4 | Q107: 0.0043
G108: Return | H108: =SUM(H4:H107) -> 0.0389 | P108: Return | Q108: =SUM(Q4:Q107) -> -0.0098

Sheet Value at Risk (VaR)
B3: 2 Year Weekly return
B5: Nifty 50 | K5: Tata Power Ltd. | S5: P/L (Historical) | U5: Calculation of Value at Risk - Tata power Ltd. & Nifty 50 (Historical)
B6: Date | C6: Price | D6: Open | E6: High | F6: Low | G6: Vol. | H6: Change % | K6: Date | L6: Price | M6: Open | N6: High | O6: Low | P6: Vol. | Q6: Change %
B7: 46187 | C7: 24013.1 | D7: 23984.85 | E7: 24189.25 | F7: 23817.8 | G7: 1.87B | H7: 0.0165 | K7: 46187 | L7: 402.35 | M7: 397.75 | N7: 405.6 | O7: 395.55 | P7: 32.80M | Q7: 0.0224 | S7: =(($V$9*H7)+($V$10*Q7)) -> 0.01886 | U7: Total portfolio
B8: 46180 | C8: 23622.9 | D8: 23080.7 | E8: 23645.35 | F8: 23070.15 | G8: 1.87B | H8: 0.011 | K8: 46180 | L8: 393.55 | M8: 404.05 | N8: 409.1 | O8: 388 | P8: 23.94M | Q8: -0.0382 | S8: =(($V$9*H8)+($V$10*Q8)) -> -0.00868 | U8: Portfolio Value | V8: 50000
B9: 46173 | C9: 23366.7 | D9: 23654.5 | E9: 23733.7 | F9: 23151.5 | G9: 2.16B | H9: -0.0077 | K9: 46173 | L9: 409.2 | M9: 421.7 | N9: 423.75 | O9: 406.55 | P9: 20.90M | Q9: -0.0275 | S9: =(($V$9*H9)+($V$10*Q9)) -> -0.01562 | U9: Weight of Nifty 50 | V9: 0.6
B10: 46166 | C10: 23547.75 | D10: 23940.25 | E10: 24089.8 | F10: 23484.75 | G10: 2.47B | H10: -0.0072 | K10: 46166 | L10: 420.75 | M10: 411.25 | N10: 434 | O10: 409.4 | P10: 27.34M | Q10: 0.029 | S10: =(($V$9*H10)+($V$10*Q10)) -> 0.00728 | U10: Weight of Tata Power Ltd. | V10: =1-V9 -> 0.4
B11: 46159 | C11: 23719.3 | D11: 23482.2 | E11: 23859.9 | F11: 23317.1 | G11: 1.86B | H11: 0.0032 | K11: 46159 | L11: 408.9 | M11: 404.6 | N11: 418.5 | O11: 395.95 | P11: 27.27M | Q11: 0.0047 | S11: =(($V$9*H11)+($V$10*Q11)) -> 0.0038 | U11: Confidence Interval | V11: 0.95
B12: 46152 | C12: 23643.5 | D12: 23970.1 | E12: 23997.45 | F12: 23262.55 | G12: 2.09B | H12: -0.022 | K12: 46152 | L12: 407 | M12: 434 | N12: 437.95 | O12: 390.8 | P12: 42.08M | Q12: -0.0665 | S12: =(($V$9*H12)+($V$10*Q12)) -> -0.0398 | U12: Days | V12: 30
B13: 46145 | C13: 24176.15 | D13: 24063.55 | E13: 24482.1 | F13: 23882.05 | G13: 1.99B | H13: 0.0074 | K13: 46145 | L13: 436 | M13: 445.5 | N13: 448 | O13: 434.7 | P13: 25.50M | Q13: -0.0192 | S13: =(($V$9*H13)+($V$10*Q13)) -> -0.00324 | U13: VaR | V13: =_xlfn.PERCENTILE.INC(S6:S109,(1-V11))*(52^0.5)*(V12/252) -> -0.037233326
B14: 46138 | C14: 23997.55 | D14: 23945.45 | E14: 24334.7 | F14: 23796.85 | G14: 2.02B | H14: 0.0042 | K14: 46138 | L14: 444.55 | M14: 436.6 | N14: 464.9 | O14: 435.2 | P14: 46.09M | Q14: 0.022 | S14: =(($V$9*H14)+($V$10*Q14)) -> 0.01132 | V14: =_xlfn.PERCENTILE.INC(S7:S110,(1-V11))*V8*(52^0.5)*(V12/252) -> -1858.9192
B15: 46131 | C15: 23897.95 | D15: 24391.5 | E15: 24601.7 | F15: 23813.65 | G15: 2.19B | H15: -0.0187 | K15: 46131 | L15: 435 | M15: 427.5 | N15: 440.8 | O15: 424.45 | P15: 42.75M | Q15: 0.0173 | S15: =(($V$9*H15)+($V$10*Q15)) -> -0.0043
B16: 46124 | C16: 24353.55 | D16: 23589.6 | E16: 24400.95 | F16: 23555.6 | G16: 1.96B | H16: 0.0126 | K16: 46124 | L16: 427.6 | M16: 394.95 | N16: 432 | O16: 390.25 | P16: 59.70M | Q16: 0.0707 | S16: =(($V$9*H16)+($V$10*Q16)) -> 0.03584
B17: 46117 | C17: 24050.6 | D17: 22780.3 | E17: 24074.05 | F17: 22542.95 | G17: 2.49B | H17: 0.0589 | K17: 46117 | L17: 399.35 | M17: 385.05 | N17: 401.35 | O17: 378.45 | P17: 33.04M | Q17: 0.0373 | S17: =(($V$9*H17)+($V$10*Q17)) -> 0.05026
B18: 46110 | C18: 22713.1 | D18: 22549.65 | E18: 22941.3 | F18: 22182.55 | G18: 1.71B | H18: -0.0047 | K18: 46110 | L18: 385 | M18: 381 | N18: 390.9 | O18: 368 | P18: 25.05M | Q18: -0.0018 | S18: =(($V$9*H18)+($V$10*Q18)) -> -0.00354 | U18: Calculation of Value at Risk - Tata power Ltd. & Nifty 50 (Parametric )
B19: 46103 | C19: 22819.6 | D19: 22824.35 | E19: 23465.35 | F19: 22471.25 | G19: 2.21B | H19: -0.0128 | K19: 46103 | L19: 385.7 | M19: 402.7 | N19: 403.3 | O19: 373 | P19: 41.80M | Q19: -0.0415 | S19: =(($V$9*H19)+($V$10*Q19)) -> -0.02428
B20: 46096 | C20: 23114.5 | D20: 23116.1 | E20: 23862.25 | F20: 22930.35 | G20: 2.60B | H20: -0.0016 | K20: 46096 | L20: 402.4 | M20: 395.55 | N20: 418.45 | O20: 385 | P20: 60.74M | Q20: 0.0189 | S20: =(($V$9*H20)+($V$10*Q20)) -> 0.0066 | U20: Nifty 50 | X20: Total portfolio | AA20: Value at Risk (VaR)
B21: 46089 | C21: 23151.1 | D21: 23868.05 | E21: 24303.8 | F21: 23112 | G21: 2.40B | H21: -0.0531 | K21: 46089 | L21: 394.95 | M21: 366.5 | N21: 407.35 | O21: 365.15 | P21: 56.50M | Q21: 0.0518 | S21: =(($V$9*H21)+($V$10*Q21)) -> -0.01114 | U21: Expected Return | V21: =MEDIAN(H7:H110)*52 -> 0.1326 | X21: Portfolio Value | Y21: 50000 | AA21: Days | AB21: 5
B22: 46082 | C22: 24450.45 | D22: 24659.25 | E22: 24989.35 | F22: 24305.4 | G22: 2.06B | H22: -0.0289 | K22: 46082 | L22: 375.5 | M22: 356 | N22: 385.25 | O22: 356 | P22: 21.08M | Q22: -0.0054 | S22: =(($V$9*H22)+($V$10*Q22)) -> -0.0195 | U22: St. dev. nifty | V22: =_xlfn.STDEV.S(H7:H110)*(52^0.5) -> 0.1317833 | X22: Weight of Nifty 50 | Y22: 0.6 | AA22: Expected return | AB22: =(Days/252)*Portfolio_Value*((Expected_Return*Weight_of_Nifty_50)+(V25*Weight_of_Tata_Power_Ltd.)) -> 98.769841
B23: 46075 | C23: 25178.65 | D23: 25678.4 | E23: 25771.45 | F23: 25141.3 | G23: 2.01B | H23: -0.0154 | K23: 46075 | L23: 377.55 | M23: 379 | N23: 385.4 | O23: 372.5 | P23: 15.75M | Q23: -0.0012 | S23: =(($V$9*H23)+($V$10*Q23)) -> -0.00972 | X23: Weight of Tata Power Ltd. | Y23: =1-Y22 -> 0.4 | AA23: Confidence Interval | AB23: 0.95
B24: 46068 | C24: 25571.25 | D24: 25423.6 | E24: 25885.3 | F24: 25372.7 | G24: 1.52B | H24: 0.0039 | K24: 46068 | L24: 378 | M24: 372 | N24: 384.25 | O24: 368.3 | P24: 15.88M | Q24: 0.0104 | S24: =(($V$9*H24)+($V$10*Q24)) -> 0.0065 | U24: =K5 -> Tata Power Ltd. | AA24: Z.score | AB24: =_xlfn.NORM.S.INV(AB23) -> 1.6448536
B25: 46061 | C25: 25471.1 | D25: 25888.7 | E25: 26009.4 | F25: 25444.3 | G25: 2.02B | H25: -0.0087 | K25: 46061 | L25: 374.1 | M25: 367 | N25: 381.5 | O25: 365.1 | P25: 18.70M | Q25: 0.0223 | S25: =(($V$9*H25)+($V$10*Q25)) -> 0.0037 | U25: Expected Return | V25: 0.05 | X25: Portfolio Variance | Y25: =Weight_of_Nifty_50^2*St._dev._nifty^2+Weight_of_Tata_Power_Ltd.^2*St._dev.^2+2*Weight_of_Nifty_50*Weight_of_Tata_Power_Ltd.*Covariance -> 0.018756775
B26: 46054 | C26: 25693.7 | D26: 25333.75 | E26: 26341.2 | F26: 24571.75 | G26: 2.61B | H26: 0.0147 | K26: 46054 | L26: 365.95 | M26: 367.7 | N26: 372.25 | O26: 348.4 | P26: 22.76M | Q26: -0.001 | S26: =(($V$9*H26)+($V$10*Q26)) -> 0.00842 | U26: St. dev. | V26: =_xlfn.STDEV.S(Q7:Q110)*(52^0.5) -> 0.27728519 | X26: Portfolio St. dev. | Y26: =Y25^0.5 -> 0.13695538
B27: 46047 | C27: 25320.65 | D27: 25063.35 | E27: 25458.15 | F27: 24932.55 | G27: 2.28B | H27: 0.0109 | K27: 46047 | L27: 366.3 | M27: 345.7 | N27: 367.5 | O27: 342.5 | P27: 21.13M | Q27: 0.061 | S27: =(($V$9*H27)+($V$10*Q27)) -> 0.03094 | U27: Covariance | V27: =_xlfn.COVARIANCE.S(H7:H110,Q7:Q110) -> 0.00042245928 | AA27: VaR | AB27: =AB22-(Portfolio_Value*Portfolio_St._dev.)*Z.score*SQRT(Days/252) -> -1487.8069
B28: 46040 | C28: 25048.65 | D28: 25653.1 | E28: 25653.3 | F28: 24919.8 | G28: 2.13B | H28: -0.0251 | K28: 46040 | L28: 345.25 | M28: 366.1 | N28: 368.7 | O28: 344.1 | P28: 16.05M | Q28: -0.057 | S28: =(($V$9*H28)+($V$10*Q28)) -> -0.03786
B29: 46033 | C29: 25694.35 | D29: 25669.05 | E29: 25899.8 | F29: 25473.4 | G29: 1.44B | H29: 0.0004 | K29: 46033 | L29: 366.1 | M29: 364.8 | N29: 372.35 | O29: 360.1 | P29: 15.64M | Q29: 0.0036 | S29: =(($V$9*H29)+($V$10*Q29)) -> 0.00168
B30: 46026 | C30: 25683.3 | D30: 26333.7 | E30: 26373.2 | F30: 25623 | G30: 1.74B | H30: -0.0245 | K30: 46026 | L30: 364.8 | M30: 392.5 | N30: 393 | O30: 362.95 | P30: 21.46M | Q30: -0.072 | S30: =(($V$9*H30)+($V$10*Q30)) -> -0.0435 | U30: Calculation of Value at Risk - Tata power Ltd. & Nifty 50 (Monte Carlo )
B31: 46019 | C31: 26328.55 | D31: 26063.35 | E31: 26340 | F31: 25878 | G31: 1.66B | H31: 0.011 | K31: 46019 | L31: 393.1 | M31: 379 | N31: 393.65 | O31: 372.7 | P31: 20.97M | Q31: 0.0357 | S31: =(($V$9*H31)+($V$10*Q31)) -> 0.02088
B32: 46012 | C32: 26042.3 | D32: 26055.85 | E32: 26236.4 | F32: 26008.6 | G32: 800.63M | H32: 0.0029 | K32: 46012 | L32: 379.55 | M32: 381 | N32: 383.7 | O32: 378.1 | P32: 13.29M | Q32: -0.0026 | S32: =(($V$9*H32)+($V$10*Q32)) -> 0.0007 | U32: Nifty 50 | X32: Total portfolio | AA32: Value at Risk (VaR)
B33: 46005 | C33: 25966.4 | D33: 25930.05 | E33: 26047.15 | F33: 25726.3 | G33: 1.23B | H33: -0.0031 | K33: 46005 | L33: 380.55 | M33: 380 | N33: 383.3 | O33: 373 | P33: 15.42M | Q33: -0.0037 | S33: =(($V$9*H33)+($V$10*Q33)) -> -0.00334 | U33: Expected Return | V33: =Expected_Return -> 0.1326 | X33: Portfolio Value | Y33: 50000 | AA33: Days | AB33: 5
B34: 45998 | C34: 26046.95 | D34: 26159.8 | E34: 26178.7 | F34: 25693.25 | G34: 1.23B | H34: -0.0053 | K34: 45998 | L34: 381.95 | M34: 383.2 | N34: 385.25 | O34: 369.8 | P34: 25.51M | Q34: -0.0066 | S34: =(($V$9*H34)+($V$10*Q34)) -> -0.00582 | U34: St. dev. nifty | V34: =_xlfn.STDEV.S(H19:H122)*(52^0.5) -> 0.1320498 | X34: Weight of Nifty 50 | Y34: 0.6 | AA34: Expected return | AB34: =(AB33/252)*Y33*((V33*Y34)+(V37*Y35)) -> 98.769841
B35: 45991 | C35: 26186.45 | D35: 26325.8 | E35: 26325.8 | F35: 25891 | G35: 1.23B | H35: -0.0006 | K35: 45991 | L35: 384.5 | M35: 390.65 | N35: 393 | O35: 380.55 | P35: 19.73M | Q35: -0.0144 | S35: =(($V$9*H35)+($V$10*Q35)) -> -0.00612 | X35: Weight of Tata Power Ltd. | Y35: =1-Y34 -> 0.4 | AA35: Z.score | AB35: =_xlfn.NORM.S.INV(RAND()) -> 0.3487874
B36: 45984 | C36: 26202.95 | D36: 26122.8 | E36: 26310.45 | F36: 25842.95 | G36: 1.44B | H36: 0.0052 | K36: 45984 | L36: 390.1 | M36: 390 | N36: 399.95 | O36: 379 | P36: 26.15M | Q36: 0.008 | S36: =(($V$9*H36)+($V$10*Q36)) -> 0.00632 | U36: =U24 -> Tata Power Ltd.
B37: 45977 | C37: 26068.15 | D37: 25948.2 | E37: 26246.65 | F37: 25856.2 | G37: 1.29B | H37: 0.0061 | K37: 45977 | L37: 387 | M37: 388.5 | N37: 394 | O37: 384.2 | P37: 21.96M | Q37: -0.0036 | S37: =(($V$9*H37)+($V$10*Q37)) -> 0.00222 | U37: Expected Return | V37: 0.05 | X37: Portfolio Variance | Y37: =Weight_of_Nifty_50^2*St._dev._nifty^2+Weight_of_Tata_Power_Ltd.^2*St._dev.^2+2*Weight_of_Nifty_50*Weight_of_Tata_Power_Ltd.*Covariance -> 0.018756775 | AA37: Scenario VaR | AB37: =AB34-(Y33*Y38)*AB35*(AB33/252)^0.5 -> -237.66007
B38: 45970 | C38: 25910.05 | D38: 25503.5 | E38: 26010.7 | F38: 25449.25 | G38: 1.76B | H38: 0.0164 | K38: 45970 | L38: 388.4 | M38: 393.2 | N38: 397.9 | O38: 385 | P38: 24.91M | Q38: -0.0122 | S38: =(($V$9*H38)+($V$10*Q38)) -> 0.00496 | U38: St. dev. | V38: =_xlfn.STDEV.S(Q19:Q122)*(52^0.5) -> 0.27806034 | X38: Portfolio St. dev. | Y38: =Y37^0.5 -> 0.13695538
B39: 45963 | C39: 25492.3 | D39: 25696.85 | E39: 25803.1 | F39: 25318.45 | G39: 1.01B | H39: -0.0089 | K39: 45963 | L39: 393.2 | M39: 403.85 | N39: 409.5 | O39: 386 | P39: 20.00M | Q39: -0.0289 | S39: =(($V$9*H39)+($V$10*Q39)) -> -0.0169 | U39: Covariance | V39: =_xlfn.COVARIANCE.S(H19:H122,Q19:Q122) -> 0.00042383922 | AA39: Confidence Interval | AB39: 0.95
B40: 45956 | C40: 25722.1 | D40: 25843.2 | E40: 26097.85 | F40: 25711.2 | G40: 1.58B | H40: -0.0028 | K40: 45956 | L40: 404.9 | M40: 396.9 | N40: 413.25 | O40: 395.65 | P40: 26.55M | Q40: 0.0203 | S40: =(($V$9*H40)+($V$10*Q40)) -> 0.00644 | AA40: Monte Carlo VaR | AB40: =_xlfn.PERCENTILE.INC(V43:V10042,(1-AB39)) -> -1487.7937
B41: 45949 | C41: 25795.15 | D41: 25824.6 | E41: 26104.2 | F41: 25718.2 | G41: 1.08B | H41: 0.0033 | K41: 45949 | L41: 396.85 | M41: 398.3 | N41: 403.85 | O41: 394 | P41: 15.11M | Q41: -0.0024 | S41: =(($V$9*H41)+($V$10*Q41)) -> 0.00102 | U41: Monte Carlo 10000 Simulation
B42: 45942 | C42: 25709.85 | D42: 25177.3 | E42: 25781.5 | F42: 25060.55 | G42: 1.61B | H42: 0.0168 | K42: 45942 | L42: 397.8 | M42: 388 | N42: 402.8 | O42: 385.25 | P42: 24.54M | Q42: 0.0197 | S42: =(($V$9*H42)+($V$10*Q42)) -> 0.01796 | U42: Simulation | V42: =AB37 -> -237.66007
B43: 45935 | C43: 25285.35 | D43: 24916.55 | E43: 25330.75 | F43: 24881.65 | G43: 1.30B | H43: 0.0157 | K43: 45935 | L43: 390.1 | M43: 394.9 | N43: 397.5 | O43: 381.5 | P43: 27.89M | Q43: -0.0122 | S43: =(($V$9*H43)+($V$10*Q43)) -> 0.00454 | U43: 1 | V43: 329.16963
B44: 45928 | C44: 24894.25 | D44: 24728.55 | E44: 24904.8 | F44: 24587.7 | G44: 1.37B | H44: 0.0097 | K44: 45928 | L44: 394.9 | M44: 384.25 | N44: 395.5 | O44: 383.25 | P44: 13.68M | Q44: 0.0289 | S44: =(($V$9*H44)+($V$10*Q44)) -> 0.01738 | U44: 2 | V44: 90.355603
B45: 45921 | C45: 24654.7 | D45: 25238.1 | E45: 25331.7 | F45: 24629.45 | G45: 1.43B | H45: -0.0265 | K45: 45921 | L45: 383.8 | M45: 396 | N45: 399.9 | O45: 382.2 | P45: 17.12M | Q45: -0.0315 | S45: =(($V$9*H45)+($V$10*Q45)) -> -0.0285 | U45: 3 | V45: 375.00255
B46: 45914 | C46: 25327.05 | D46: 25118.9 | E46: 25448.95 | F46: 25048.75 | G46: 1.35B | H46: 0.0085 | K46: 45914 | L46: 396.3 | M46: 386 | N46: 399.8 | O46: 385.5 | P46: 27.58M | Q46: 0.026 | S46: =(($V$9*H46)+($V$10*Q46)) -> 0.0155 | U46: 4 | V46: 226.0307
B47: 45907 | C47: 25114 | D47: 24802.6 | E47: 25139.45 | F47: 24751.55 | G47: 1.13B | H47: 0.0151 | K47: 45907 | L47: 386.25 | M47: 385.8 | N47: 390.95 | O47: 381.15 | P47: 16.83M | Q47: 0.0012 | S47: =(($V$9*H47)+($V$10*Q47)) -> 0.00954 | U47: 5 | V47: -1131.6141
B48: 45900 | C48: 24741 | D48: 24432.7 | E48: 24980.75 | F48: 24432.7 | G48: 1.37B | H48: 0.0129 | K48: 45900 | L48: 385.8 | M48: 374.15 | N48: 392 | O48: 374.15 | P48: 15.63M | Q48: 0.0311 | S48: =(($V$9*H48)+($V$10*Q48)) -> 0.02018 | U48: 6 | V48: 2407.9616
B49: 45893 | C49: 24426.85 | D49: 24949.15 | E49: 25021.55 | F49: 24404.7 | G49: 1.62B | H49: -0.0178 | K49: 45893 | L49: 374.15 | M49: 386.05 | N49: 388.4 | O49: 368.5 | P49: 21.28M | Q49: -0.0297 | S49: =(($V$9*H49)+($V$10*Q49)) -> -0.02256 | U49: 7 | V49: 1980.2034
B50: 45886 | C50: 24870.1 | D50: 24938.2 | E50: 25153.65 | F50: 24852.85 | G50: 1.34B | H50: 0.0097 | K50: 45886 | L50: 385.6 | M50: 389 | N50: 392.45 | O50: 384.7 | P50: 14.40M | Q50: 0.0008 | S50: =(($V$9*H50)+($V$10*Q50)) -> 0.00614 | U50: 8 | V50: 886.64658
B51: 45879 | C51: 24631.3 | D51: 24371.5 | E51: 24702.6 | F51: 24347.45 | G51: 984.32M | H51: 0.011 | K51: 45879 | L51: 385.3 | M51: 380 | N51: 388.95 | O51: 377.5 | P51: 12.32M | Q51: 0.0172 | S51: =(($V$9*H51)+($V$10*Q51)) -> 0.01348 | U51: 9 | V51: -72.302763
B52: 45872 | C52: 24363.3 | D52: 24596.05 | E52: 24736.25 | F52: 24337.5 | G52: 1.67B | H52: -0.0082 | K52: 45872 | L52: 378.8 | M52: 390 | N52: 391.65 | O52: 376 | P52: 34.56M | Q52: -0.027 | S52: =(($V$9*H52)+($V$10*Q52)) -> -0.01572 | U52: 10 | V52: -1041.1232
B53: 45865 | C53: 24565.35 | D53: 24782.45 | E53: 24956.5 | F53: 24535.05 | G53: 1.40B | H53: -0.0109 | K53: 45865 | L53: 389.3 | M53: 394.1 | N53: 403.8 | O53: 388.2 | P53: 27.79M | Q53: -0.0153 | S53: =(($V$9*H53)+($V$10*Q53)) -> -0.01266 | U53: 11 | V53: 343.17527
B54: 45858 | C54: 24837 | D54: 24999 | E54: 25246.25 | F54: 24806.35 | G54: 1.68B | H54: -0.0053 | K54: 45858 | L54: 395.35 | M54: 404 | N54: 405 | O54: 394.3 | P54: 24.66M | Q54: -0.0308 | S54: =(($V$9*H54)+($V$10*Q54)) -> -0.0155 | U54: 12 | V54: 1901.6833
... B110: 45466 | C110: 24010.6 | D110: 23382.3 | E110: 24174 | F110: 23350 | G110: 1.70B | H110: 0.0217 | K110: 45466 | L110: 440.6 | M110: 436 | N110: 444.45 | O110: 426.5 | P110: 54.40M | Q110: 0.0043 | S110: =(($V$9*H110)+($V$10*Q110)) -> 0.01474 | U110: 68 | V110: 13.851284
H111: =SUM(H7:H110) -> 0.0389 | Q111: =SUM(Q7:Q110) -> -0.0098 | U111: 69 | V111: 0.53005519
U112: 70 | V112: -1065.6456
U113: 71 | V113: -1177.2911
U114: 72 | V114: -258.53848
U115: 73 | V115: 473.35789
U116: 74 | V116: 855.26602
U117: 75 | V117: 1662.9118
U118: 76 | V118: -432.75007
U119: 77 | V119: 385.00937
U120: 78 | V120: 119.30872
U121: 79 | V121: -0.73750307
U122: 80 | V122: 1091.7479
U123: 81 | V123: 1514.5475
... U10042: 10000 | V10042: 1689.5159

Sheet Valuation Drivers
B21: Data from - | C21: https://pages.stern.nyu.edu/~adamodar/New_Home_Page/datafile/ctryprem.html
B22: Country | C22: Moody's rating | D22: Adj. Default Spread | E22: Country Risk Premium | F22: Equity Risk Premium | G22: Corporate Tax Rate | H22: Sovereign CDS | I22: ERP based on sovereign CDS
B23: India | C23: Baa3 | D23: 0.0187 | E23: 0.0285 | F23: 0.0708 | G23: 0.3 | H23: 0.0066 | I23: 0.0523
B24: United States | C24: Aa1 | D24: 0.0023 | E24: 0.0023 | F24: 0.0446 | G24: 0.25 | H24: 0.003 | I24: 0.0469
B26: Risk Free Rate | C26: 0.068
B27: Indian Market Return | C27: ='Beta Regression Historical Data'!$H$108 -> 0.0389
B28: US treasury 10 y bond | C28: 0.045
B29: Beta | C29: ='Beta Regression Historical Data'!T7 -> 1.2649327
B30: Tax | C30: =G23 -> 0.3
B31: ERP india - rating | C31: =F23 -> 0.0708
B32: ERP India - returns | C32: =C27-C26 -> -0.0291
B34: Note:-
B35: ERP (Returns-based) is negative due to volatility in India's short/medium-term historical equity returns and is not used in this model. ERP (Rating-based) derived from India's sovereign default spread is used instead, consistent with Damodaran's guidance that rating-based ERP is more stable for emerging markets than trailing historical returns.

Sheet WACC
B3: Weighted Average Cost of Capital
I5: Debt/ | J5: Debt/ | K5: Levered | L5: Unlevered
B6: Name of the Comparable company | F6: Total Debt | G6: Total Equity | H6: Tax Rate 1 | I6: Equity | J6: Capital | K6: Beta 2 | L6: Beta 3
B7: Adani Power | F7: 54670.29 | G7: 4421403.2 | H7: =$L$37 -> 0.3 | I7: =F7/G7 -> 0.012364919 | J7: =F7/(F7+G7) -> 0.012213895 | K7: 0.16 | L7: =K7/(1+(1-H7)*I7) -> 0.15862701
B8: NTPC | F8: 271004.58 | G8: 341372.32 | H8: =$L$37 -> 0.3 | I8: =F8/G8 -> 0.79386805 | J8: =F8/(F8+G8) -> 0.4425454 | K8: 0.46 | L8: =K8/(1+(1-H8)*I8) -> 0.29568538
B9: Power Grid Corpn | F9: 148070.6 | G9: 264044.03 | H9: =$L$37 -> 0.3 | I9: =F9/G9 -> 0.56077995 | J9: =F9/(F9+G9) -> 0.35929469 | K9: 0.39 | L9: =K9/(1+(1-H9)*I9) -> 0.28006257
B10: Adani Green | F10: 103545 | G10: 251379.19 | H10: =$L$37 -> 0.3 | I10: =F10/G10 -> 0.4119076 | J10: =F10/(F10+G10) -> 0.29173836 | K10: 0.78 | L10: =K10/(1+(1-H10)*I10) -> 0.60543244
B11: Adani Energy Sol | F11: 49176.43 | G11: 181132.01 | H11: =$L$37 -> 0.3 | I11: =F11/G11 -> 0.27149497 | J11: =F11/(F11+G11) -> 0.21352422 | K11: 1.32 | L11: =K11/(1+(1-H11)*I11) -> 1.1092004
G13: Average | H13: =AVERAGE(H7:H11) -> 0.3 | I13: =AVERAGE(I7:I11) -> 0.4100831 | J13: =AVERAGE(J7:J11) -> 0.26386331 | K13: =AVERAGE(K7:K11) -> 0.622 | L13: =AVERAGE(L7:L11) -> 0.48980156
G14: Median | H14: =MEDIAN(H7:H11) -> 0.3 | I14: =MEDIAN(I7:I11) -> 0.4119076 | J14: =MEDIAN(J7:J11) -> 0.29173836 | K14: =MEDIAN(K7:K11) -> 0.46 | L14: =MEDIAN(L7:L11) -> 0.29568538
G15: MAX | H15: =MAX(H7:H11) -> 0.3 | I15: =MAX(I7:I11) -> 0.79386805 | J15: =MAX(J7:J11) -> 0.4425454 | K15: =MAX(K7:K11) -> 1.32 | L15: =MAX(L7:L11) -> 1.1092004
G16: MIN | H16: =MIN(H7:H11) -> 0.3 | I16: =MIN(I7:I11) -> 0.012364919 | J16: =MIN(J7:J11) -> 0.012213895 | K16: =MIN(K7:K11) -> 0.16 | L16: =MIN(L7:L11) -> 0.15862701
I18: Debt/ | J18: Debt/ | K18: Levered | L18: Unlevered
B19: Name of the Comp | F19: Total Debt | G19: Total Equity | H19: Tax Rate 1 | I19: Equity | J19: Capital | K19: Beta 2 | L19: Beta 3
B21: Tata Power Co. | F21: 76141.27 | G21: 128564.49 | H21: =L37 -> 0.3 | I21: =F21/G21 -> 0.59224184 | J21: =F21/(G21+F21) -> 0.3719547 | K21: =L33 -> 1.2649327 | L21: =K21/(1+(1-H21)*I21) -> 0.89421757
B24: Cost of Debt | G24: Cost of Equity
B26: Pre Tax Cost of Debt | E26: ='Historical Financial Statements'!$L$30/'Historical Financial Statements'!$L$61 -> 0.069040202 | G26: Risk Free Rate | L26: ='Valuation Drivers'!C26 -> 0.068
B27: Tax | E27: 0.3 | G27: Equity Risk Premium | L27: ='Valuation Drivers'!C31 -> 0.0708
B28: Post Tax Cost of Debt | E28: =E26*(1-E27) -> 0.048328141 | G28: Levered Beta 4 | L28: =L38 -> 1.2312688
G29: Cost of Equity | L29: =L26+(L27*L28) -> 0.15517383
B32: Capital Structure | G32: Levered Beta
G33: Beta (Market) | L33: ='Valuation Drivers'!C29 -> 1.2649327
D34: Current | E34: Target | G34: Current Debt/Equity | L34: =I21 -> 0.59224184
B35: Total Debt | C35: =F21 -> 76141.27 | D35: =C35/C37 -> 0.3719547 | E35: =E37-E36 -> 0.35 | G35: Unlevered Beta | L35: =L21 -> 0.89421757
B36: Market Capitalization | C36: =G21 -> 128564.49 | D36: =C36/C37 -> 0.6280453 | E36: 0.65 | G36: Target Debt/Equity | L36: =E39 -> 0.53846154
B37: Total Capital | C37: =C36+C35 -> 204705.76 | D37: =SUM(D35:D36) -> 1 | E37: =D37 -> 1 | G37: Tax Rate | L37: ='Valuation Drivers'!C30 -> 0.3
G38: Levered Beta | L38: =L35*(1+(1-L37)*L36) -> 1.2312688
B39: Debt/Equity | D39: =D35/D36 -> 0.59224184 | E39: =E35/E36 -> 0.53846154
G40: Weighted Average Cost of Capital
K42: Total Cost | L42: Total Weight
G43: Debt | K43: =E28 -> 0.048328141 | L43: =E35 -> 0.35
G44: Equity | K44: =L29 -> 0.15517383 | L44: =E36 -> 0.65
G45: WACC | L45: =SUMPRODUCT(K43:K44,L43:L44) -> 0.11777784
B50: Target based on observed 10-year trend in market-value debt/equity, extrapolated forward

Sheet DCF Assumptions
B2: DCF Assumptions
B4: Calculation of ROIC | D4: ='Historical Financial Statements'!C3 -> 42825 | E4: ='Historical Financial Statements'!D3 -> 43190 | F4: ='Historical Financial Statements'!E3 -> 43555 | G4: ='Historical Financial Statements'!F3 -> 43921 | H4: ='Historical Financial Statements'!G3 -> 44286 | I4: ='Historical Financial Statements'!H3 -> 44651 | J4: ='Historical Financial Statements'!I3 -> 45016 | K4: ='Historical Financial Statements'!J3 -> 45382 | ... M4: ='Historical Financial Statements'!L3 -> 46112
B6: Current Assets
B7: Inventories | D7: ='Historical Financial Statements'!C74 -> 1600 | E7: ='Historical Financial Statements'!D74 -> 1623 | F7: ='Historical Financial Statements'!E74 -> 1706 | G7: ='Historical Financial Statements'!F74 -> 1752 | H7: ='Historical Financial Statements'!G74 -> 1886 | I7: ='Historical Financial Statements'!H74 -> 4232 | J7: ='Historical Financial Statements'!I74 -> 3943 | K7: ='Historical Financial Statements'!J74 -> 4420 | ... M7: ='Historical Financial Statements'!L74 -> 5108
B8: Trade receivables | D8: ='Historical Financial Statements'!C75 -> 3832 | E8: ='Historical Financial Statements'!D75 -> 2789 | F8: ='Historical Financial Statements'!E75 -> 4445 | G8: ='Historical Financial Statements'!F75 -> 4426 | H8: ='Historical Financial Statements'!G75 -> 5200 | I8: ='Historical Financial Statements'!H75 -> 5980 | J8: ='Historical Financial Statements'!I75 -> 6952 | K8: ='Historical Financial Statements'!J75 -> 7402 | ... M8: ='Historical Financial Statements'!L75 -> 4424
B9: Loans n Advances | D9: ='Historical Financial Statements'!C76 -> 395 | E9: ='Historical Financial Statements'!D76 -> 490 | F9: ='Historical Financial Statements'!E76 -> 501 | G9: ='Historical Financial Statements'!F76 -> 552 | H9: ='Historical Financial Statements'!G76 -> 609 | I9: ='Historical Financial Statements'!H76 -> 887 | J9: ='Historical Financial Statements'!I76 -> 1079 | K9: ='Historical Financial Statements'!J76 -> 1134 | ... M9: ='Historical Financial Statements'!L76 -> 461
B10: Other asset items | D10: ='Historical Financial Statements'!C77 -> 15402 | E10: ='Historical Financial Statements'!D77 -> 17066 | F10: ='Historical Financial Statements'!E77 -> 16211 | G10: ='Historical Financial Statements'!F77 -> 17037 | H10: ='Historical Financial Statements'!G77 -> 16491 | I10: ='Historical Financial Statements'!H77 -> 18627 | J10: ='Historical Financial Statements'!I77 -> 21123 | K10: ='Historical Financial Statements'!J77 -> 21861 | ... M10: ='Historical Financial Statements'!L77 -> 32465
B11: Total Current Assets | D11: =SUM(D7:D10) -> 21229 | E11: =SUM(E7:E10) -> 21968 | F11: =SUM(F7:F10) -> 22863 | G11: =SUM(G7:G10) -> 23767 | H11: =SUM(H7:H10) -> 24186 | I11: =SUM(I7:I10) -> 29726 | J11: =SUM(J7:J10) -> 33097 | K11: =SUM(K7:K10) -> 34817 | ... M11: =SUM(M7:M10) -> 42458
B13: Current Liabilities
B14: Trade Payables | D14: ='Historical Financial Statements'!C66 -> 5529 | E14: ='Historical Financial Statements'!D66 -> 5610 | F14: ='Historical Financial Statements'!E66 -> 5481 | G14: ='Historical Financial Statements'!F66 -> 5095 | H14: ='Historical Financial Statements'!G66 -> 7146 | I14: ='Historical Financial Statements'!H66 -> 10460 | J14: ='Historical Financial Statements'!I66 -> 7407 | K14: ='Historical Financial Statements'!J66 -> 14093 | ... M14: ='Historical Financial Statements'!L66 -> 10786
B15: Advance from Customers | D15: ='Historical Financial Statements'!C67 -> 413 | E15: ='Historical Financial Statements'!D67 -> 559 | F15: ='Historical Financial Statements'!E67 -> 485 | G15: ='Historical Financial Statements'!F67 -> 782 | H15: ='Historical Financial Statements'!G67 -> 1209 | I15: ='Historical Financial Statements'!H67 -> 1180 | J15: ='Historical Financial Statements'!I67 -> 2458 | K15: ='Historical Financial Statements'!J67 -> 2197 | ... M15: ='Historical Financial Statements'!L67 -> 1580
B16: Other liability items | D16: ='Historical Financial Statements'!C68 -> 12989 | E16: ='Historical Financial Statements'!D68 -> 8718 | F16: ='Historical Financial Statements'!E68 -> 9129 | G16: ='Historical Financial Statements'!F68 -> 9962 | H16: ='Historical Financial Statements'!G68 -> 18342 | I16: ='Historical Financial Statements'!H68 -> 23687 | J16: ='Historical Financial Statements'!I68 -> 31104 | K16: ='Historical Financial Statements'!J68 -> 30742 | ... M16: ='Historical Financial Statements'!L68 -> 38518
B17: Total Current Liabilities | D17: =SUM(D14:D16) -> 18931 | E17: =SUM(E14:E16) -> 14887 | F17: =SUM(F14:F16) -> 15095 | G17: =SUM(G14:G16) -> 15839 | H17: =SUM(H14:H16) -> 26697 | I17: =SUM(I14:I16) -> 35327 | J17: =SUM(J14:J16) -> 40969 | K17: =SUM(K14:K16) -> 47032 | ... M17: =SUM(M14:M16) -> 50884
A19: # | B19: Net Working Capital | D19: =D11-D17 -> 2298 | E19: =E11-E17 -> 7081 | F19: =F11-F17 -> 7768 | G19: =G11-G17 -> 7928 | H19: =H11-H17 -> -2511 | I19: =I11-I17 -> -5601 | J19: =J11-J17 -> -7872 | K19: =K11-K17 -> -12215 | ... M19: =M11-M17 -> -8426
B22: NON Current Assets
B23: Land | D23: ='Historical Financial Statements'!C82 -> 1079 | E23: ='Historical Financial Statements'!D82 -> 974 | F23: ='Historical Financial Statements'!E82 -> 1032 | G23: ='Historical Financial Statements'!F82 -> 2071 | H23: ='Historical Financial Statements'!G82 -> 2186 | I23: ='Historical Financial Statements'!H82 -> 2284 | J23: ='Historical Financial Statements'!I82 -> 2672 | K23: ='Historical Financial Statements'!J82 -> 3352 | ... M23: ='Historical Financial Statements'!L82 -> 4798
B24: Building | D24: ='Historical Financial Statements'!C83 -> 2792 | E24: ='Historical Financial Statements'!D83 -> 2906 | F24: ='Historical Financial Statements'!E83 -> 2938 | G24: ='Historical Financial Statements'!F83 -> 3058 | H24: ='Historical Financial Statements'!G83 -> 3826 | I24: ='Historical Financial Statements'!H83 -> 4043 | J24: ='Historical Financial Statements'!I83 -> 4432 | K24: ='Historical Financial Statements'!J83 -> 4503 | ... M24: ='Historical Financial Statements'!L83 -> 6228
B25: Plant Machinery | D25: ='Historical Financial Statements'!C84 -> 44014 | E25: ='Historical Financial Statements'!D84 -> 43914 | F25: ='Historical Financial Statements'!E84 -> 44924 | G25: ='Historical Financial Statements'!F84 -> 47425 | H25: ='Historical Financial Statements'!G84 -> 48607 | I25: ='Historical Financial Statements'!H84 -> 52664 | J25: ='Historical Financial Statements'!I84 -> 55799 | K25: ='Historical Financial Statements'!J84 -> 59919 | ... M25: ='Historical Financial Statements'!L84 -> 74140
B26: Equipments | D26: ='Historical Financial Statements'!C85 -> 5317 | E26: ='Historical Financial Statements'!D85 -> 5812 | F26: ='Historical Financial Statements'!E85 -> 6364 | G26: ='Historical Financial Statements'!F85 -> 6967 | H26: ='Historical Financial Statements'!G85 -> 11790 | I26: ='Historical Financial Statements'!H85 -> 15200 | J26: ='Historical Financial Statements'!I85 -> 18485 | K26: ='Historical Financial Statements'!J85 -> 22097 | ... M26: ='Historical Financial Statements'!L85 -> 32524
B27: Furniture n fittings | D27: ='Historical Financial Statements'!C86 -> 137 | E27: ='Historical Financial Statements'!D86 -> 122 | F27: ='Historical Financial Statements'!E86 -> 120 | G27: ='Historical Financial Statements'!F86 -> 118 | H27: ='Historical Financial Statements'!G86 -> 134 | I27: ='Historical Financial Statements'!H86 -> 144 | J27: ='Historical Financial Statements'!I86 -> 167 | K27: ='Historical Financial Statements'!J86 -> 187 | ... M27: ='Historical Financial Statements'!L86 -> 212
B28: Railway sidings | D28: ='Historical Financial Statements'!C87 -> 96 | E28: ='Historical Financial Statements'!D87 -> 99 | F28: ='Historical Financial Statements'!E87 -> 103 | G28: ='Historical Financial Statements'!F87 -> 104 | H28: ='Historical Financial Statements'!G87 -> 0 | I28: ='Historical Financial Statements'!H87 -> 0 | J28: ='Historical Financial Statements'!I87 -> 0 | K28: ='Historical Financial Statements'!J87 -> 0 | ... M28: ='Historical Financial Statements'!L87 -> 0
B29: Vehicles | D29: ='Historical Financial Statements'!C88 -> 220 | E29: ='Historical Financial Statements'!D88 -> 250 | F29: ='Historical Financial Statements'!E88 -> 245 | G29: ='Historical Financial Statements'!F88 -> 235 | H29: ='Historical Financial Statements'!G88 -> 228 | I29: ='Historical Financial Statements'!H88 -> 225 | J29: ='Historical Financial Statements'!I88 -> 247 | K29: ='Historical Financial Statements'!J88 -> 300 | ... M29: ='Historical Financial Statements'!L88 -> 353
B30: Intangible Assets | D30: ='Historical Financial Statements'!C89 -> 1768 | E30: ='Historical Financial Statements'!D89 -> 1666 | F30: ='Historical Financial Statements'!E89 -> 1654 | G30: ='Historical Financial Statements'!F89 -> 1646 | H30: ='Historical Financial Statements'!G89 -> 1800 | I30: ='Historical Financial Statements'!H89 -> 1864 | J30: ='Historical Financial Statements'!I89 -> 1865 | K30: ='Historical Financial Statements'!J89 -> 1903 | ... M30: ='Historical Financial Statements'!L89 -> 1698
B31: Other fixed assets | D31: ='Historical Financial Statements'!C90 -> 4211 | E31: ='Historical Financial Statements'!D90 -> 4265 | F31: ='Historical Financial Statements'!E90 -> 4233 | G31: ='Historical Financial Statements'!F90 -> 5441 | H31: ='Historical Financial Statements'!G90 -> 5584 | I31: ='Historical Financial Statements'!H90 -> 5876 | J31: ='Historical Financial Statements'!I90 -> 6229 | K31: ='Historical Financial Statements'!J90 -> 6519 | ... M31: ='Historical Financial Statements'!L90 -> 6959
B32: Gross Block | D32: =SUM(D23:D31) -> 59634 | E32: =SUM(E23:E31) -> 60008 | F32: =SUM(F23:F31) -> 61613 | G32: =SUM(G23:G31) -> 67065 | H32: =SUM(H23:H31) -> 74155 | I32: =SUM(I23:I31) -> 82300 | J32: =SUM(J23:J31) -> 89896 | K32: =SUM(K23:K31) -> 98780 | ... M32: =SUM(M23:M31) -> 126912
B33: Accumulated Depreciation | D33: =-'Historical Financial Statements'!C92 -> -13040 | E33: =-'Historical Financial Statements'!D92 -> -15352 | F33: =-'Historical Financial Statements'!E92 -> -17308 | G33: =-'Historical Financial Statements'!F92 -> -19398 | H33: =-'Historical Financial Statements'!G92 -> -21976 | I33: =-'Historical Financial Statements'!H92 -> -24911 | J33: =-'Historical Financial Statements'!I92 -> -28150 | K33: =-'Historical Financial Statements'!J92 -> -31571 | ... M33: =-'Historical Financial Statements'!L92 -> -39620
A34: # | B34: Fixed Assetcs net Block | D34: =SUM(D32:D33) -> 46594 | E34: =SUM(E32:E33) -> 44656 | F34: =SUM(F32:F33) -> 44305 | G34: =SUM(G32:G33) -> 47667 | H34: =SUM(H32:H33) -> 52179 | I34: =SUM(I32:I33) -> 57389 | J34: =SUM(J32:J33) -> 61746 | K34: =SUM(K32:K33) -> 67209 | ... M34: =SUM(M32:M33) -> 87292
A36: # | B36: Invested Capital | D36: =D34+D19 -> 48892 | E36: =E34+E19 -> 51737 | F36: =F34+F19 -> 52073 | G36: =G34+G19 -> 55595 | H36: =H34+H19 -> 49668 | I36: =I34+I19 -> 51788 | J36: =J34+J19 -> 53874 | K36: =K34+K19 -> 54994 | ... M36: =M34+M19 -> 78866
B37: NOPAT | D37: =D49 -> 2895.935 | E37: =E49 -> 2882.6 | F37: =F49 -> 3167.199 | G37: =G49 -> 3823.526 | H37: =H49 -> 3114.153 | I37: =I49 -> 3306.464 | J37: =J49 -> 3564.939 | K37: =K49 -> 5301.646 | ... M37: =M49 -> 6216.854
A39: # | B39: ROIC | D39: =D37/D36 -> 0.059231265 | E39: =E37/E36 -> 0.055716412 | F39: =F37/F36 -> 0.060822288 | G39: =G37/G36 -> 0.068774638 | H39: =H37/H36 -> 0.062699384 | I39: =I37/I36 -> 0.063846142 | J39: =J37/J36 -> 0.06617179 | K39: =K37/K36 -> 0.09640408 | ... M39: =M37/M36 -> 0.078828063
B42: Calculation of Reinvestment Rate | D42: =D4 -> 42825 | E42: =E4 -> 43190 | F42: =F4 -> 43555 | G42: =G4 -> 43921 | H42: =H4 -> 44286 | I42: =I4 -> 44651 | J42: =J4 -> 45016 | K42: =K4 -> 45382 | ... M42: =M4 -> 46112
B44: Net Capx | D44: =-SUM('Historical Financial Statements'!C115:C116) -> 3306 | E44: =-SUM('Historical Financial Statements'!D115:D116) -> 3504 | F44: =-SUM('Historical Financial Statements'!E115:E116) -> 3533 | G44: =-SUM('Historical Financial Statements'!F115:F116) -> 2190 | H44: =-SUM('Historical Financial Statements'!G115:G116) -> 1787 | I44: =-SUM('Historical Financial Statements'!H115:H116) -> 7233 | J44: =-SUM('Historical Financial Statements'!I115:I116) -> 7606 | K44: =-SUM('Historical Financial Statements'!J115:J116) -> 13095 | ... M44: =-SUM('Historical Financial Statements'!L115:L116) -> 0
B45: Change in Working Capital (NON Cash) | E45: =E19-D19 -> 4783 | F45: =F19-E19 -> 687 | G45: =G19-F19 -> 160 | H45: =H19-G19 -> -10439 | I45: =I19-H19 -> -3090 | J45: =J19-I19 -> -2271 | K45: =K19-J19 -> -4343 | L45: =L19-K19 -> -1433 | M45: =M19-L19 -> 5222
B47: EBIT | D47: ='Historical Financial Statements'!C24 -> 4137.05 | E47: ='Historical Financial Statements'!D24 -> 4118 | F47: ='Historical Financial Statements'!E24 -> 4524.57 | G47: ='Historical Financial Statements'!F24 -> 5462.18 | H47: ='Historical Financial Statements'!G24 -> 4448.79 | I47: ='Historical Financial Statements'!H24 -> 4723.52 | J47: ='Historical Financial Statements'!I24 -> 5092.77 | K47: ='Historical Financial Statements'!J24 -> 7573.78 | ... M47: ='Historical Financial Statements'!L24 -> 8881.22
B48: Marginal Tax Rate | D48: ='Valuation Drivers'!$C$30 -> 0.3 | E48: ='Valuation Drivers'!$C$30 -> 0.3 | F48: ='Valuation Drivers'!$C$30 -> 0.3 | G48: ='Valuation Drivers'!$C$30 -> 0.3 | H48: ='Valuation Drivers'!$C$30 -> 0.3 | I48: ='Valuation Drivers'!$C$30 -> 0.3 | J48: ='Valuation Drivers'!$C$30 -> 0.3 | K48: ='Valuation Drivers'!$C$30 -> 0.3 | ... M48: ='Valuation Drivers'!$C$30 -> 0.3
A49: # | B49: EBIT (1-tax) (NOPAT) | D49: =D47*(1-D48) -> 2895.935 | E49: =E47*(1-E48) -> 2882.6 | F49: =F47*(1-F48) -> 3167.199 | G49: =G47*(1-G48) -> 3823.526 | H49: =H47*(1-H48) -> 3114.153 | I49: =I47*(1-I48) -> 3306.464 | J49: =J47*(1-J48) -> 3564.939 | K49: =K47*(1-K48) -> 5301.646 | ... M49: =M47*(1-M48) -> 6216.854
B51: Reinvestment | E51: =SUM(E44:E45) -> 8287 | F51: =SUM(F44:F45) -> 4220 | G51: =SUM(G44:G45) -> 2350 | H51: =SUM(H44:H45) -> -8652 | I51: =SUM(I44:I45) -> 4143 | J51: =SUM(J44:J45) -> 5335 | K51: =SUM(K44:K45) -> 8752 | L51: =SUM(L44:L45) -> 15605 | M51: =SUM(M44:M45) -> 5222
A52: # | B52: Reinvestment Rate | E52: =E51/E49 -> 2.8748352 | F52: =F51/F49 -> 1.3324076 | G52: =G51/G49 -> 0.61461593 | H52: =H51/H49 -> -2.7782835 | I52: =I51/I49 -> 1.2530002 | J52: =J51/J49 -> 1.4965193 | K52: =K51/K49 -> 1.6508081 | L52: =L51/L49 -> 2.1377925 | M52: =M51/M49 -> 0.83997469
L53: 4 year average | M53: =AVERAGE(J52:M52) -> 1.5312736
L54: 4 year Median | M54: =MEDIAN(J52:M52) -> 1.5736637
A57: # | B57: Intrinsic Growth Rate | E57: =E52*E39 -> 0.1601755 | F57: =F52*E39 -> 0.07423697 | G57: =G52*F39 -> 0.037382347 | H57: =H52*G39 -> -0.19107544 | I57: =I52*H39 -> 0.07856234 | J57: =J52*I39 -> 0.095546983 | K57: =K52*J39 -> 0.10923692 | L57: =L52*K39 -> 0.20609192 | M57: =M52*L39 -> 0.09472959
L58: 4 year average | M58: =AVERAGE(J57:M57) -> 0.12640135
L59: 4 year Median | M59: =MEDIAN(J57:M57) -> 0.10239195
B61: Note:-
B62: Reinvestment rate anchor (157% 4-year median) reflects Tata Power's active renewable capex buildout, funded substantially by debt/equity issuance rather than retained NOPAT. This is a materially higher and more volatile reinvestment rate than the pre-2021 period, and is a primary driver of the suppressed near-term FCFF in this DCF. ROIC used in the terminal growth calculation (g = ROIC × Reinvestment Rate) also varies significantly year to year (5.6%–11.3%) during this transition period and should be read as illustrative of a business still scaling its renewable asset base, not a fully stabilized steady-state return.

Sheet DCF Model
F2: Forecaust
B4: Calculation of PV of FCFF | D4: ='DCF Assumptions'!M4 -> 46112 | F4: =D4+365 -> 46477 | G4: =F4+365 -> 46842 | H4: =G4+365 -> 47207 | I4: =H4+365 -> 47572 | J4: =I4+365 -> 47937 | K4: =J4+365 -> 48302
B7: EBIT | D7: ='DCF Assumptions'!M47 -> 8881.22 | F7: =$D$7*(1+$D$33) -> 9790.5855 | G7: =F7*(1+$D$33) -> 10793.063 | H7: =G7*(1+$D$33) -> 11898.185 | I7: =H7*(1+$D$33) -> 13116.464 | J7: =I7*(1+$D$33) -> 14459.484 | K7: =J7*(1+$D$33) -> 15940.019
B9: Tax Rate | D9: ='DCF Assumptions'!M48 -> 0.3 | F9: =D9 -> 0.3 | G9: =F9 -> 0.3 | H9: =G9 -> 0.3 | I9: =H9 -> 0.3 | J9: =I9 -> 0.3 | K9: =J9 -> 0.3
B11: EBIT(1-T)(NOPAT) | D11: =D7*(1-D9) -> 6216.854 | F11: =F7*(1-F9) -> 6853.4098 | G11: =G7*(1-G9) -> 7555.1439 | H11: =H7*(1-H9) -> 8328.7298 | I11: =I7*(1-I9) -> 9181.5247 | J11: =J7*(1-J9) -> 10121.639 | K11: =K7*(1-K9) -> 11158.013
B13: Less- Reinvestment Rate | C13: 2 | D13: =D21 -> 0.83997469 | F13: =F16 -> 0.79997469 | G13: =G16 -> 0.69997469 | H13: =H16 -> 0.59997469 | I13: =I16 -> 0.55997469 | J13: =J16 -> 0.55997469 | K13: =K16 -> 0.55997469
B14: Reinvestment Rate (Scenario)
B16: Selected Case | D16: =CHOOSE($C$13,D19,D21,D23) -> 0.83997469 | F16: =CHOOSE($C$13,F19,F21,F23) -> 0.79997469 | G16: =CHOOSE($C$13,G19,G21,G23) -> 0.69997469 | H16: =CHOOSE($C$13,H19,H21,H23) -> 0.59997469 | I16: =CHOOSE($C$13,I19,I21,I23) -> 0.55997469 | J16: =CHOOSE($C$13,J19,J21,J23) -> 0.55997469 | K16: =CHOOSE($C$13,K19,K21,K23) -> 0.55997469
B19: Best Case | F19: 0.4 | G19: =F19 -> 0.4 | H19: =G19 -> 0.4 | I19: =H19 -> 0.4 | J19: =I19 -> 0.4 | K19: =J19 -> 0.4
B21: Base Case | D21: ='DCF Assumptions'!M52 -> 0.83997469 | F21: =D21 -0.04 -> 0.79997469 | G21: =F21-0.1 -> 0.69997469 | H21: =G21-0.1 -> 0.59997469 | I21: =H21-0.04 -> 0.55997469 | J21: =I21 -> 0.55997469 | K21: =J21 -> 0.55997469
B23: Worst Case | F23: =F21+0.15 -> 0.94997469 | G23: =G21+0.15 -> 0.84997469 | H23: =H21+0.2 -> 0.79997469 | I23: =I21+0.2 -> 0.75997469 | J23: =J21+0.2 -> 0.75997469 | K23: =K21+0.2 -> 0.75997469
B26: Free Cash Flow to Firm (FCFF) | D26: =D11*(1-D13) -> 994.854 | F26: =F11*(1-F13) -> 1370.8554 | G26: =G11*(1-G13) -> 2266.7344 | H26: =H11*(1-H13) -> 3331.7027 | I26: =I11*(1-I13) -> 4040.1033 | J26: =J11*(1-J13) -> 4453.7773 | K26: =K11*(1-K13) -> 4909.8083
B28: Mid Year Convention | F28: 0.5 | G28: =F28+1 -> 1.5 | H28: =G28+1 -> 2.5 | I28: =H28+1 -> 3.5 | J28: =I28+1 -> 4.5 | K28: =J28+1 -> 5.5
B29: Discounting Factor | F29: =1/(1+$D$35)^F28 -> 0.94584997 | G29: =1/(1+$D$35)^G28 -> 0.84618779 | H29: =1/(1+$D$35)^H28 -> 0.75702681 | I29: =1/(1+$D$35)^I28 -> 0.67726053 | J29: =1/(1+$D$35)^J28 -> 0.60589905 | K29: =1/(1+$D$35)^K28 -> 0.54205677
B31: PV of FCFF | F31: =F26*F29 -> 1296.6236 | G31: =G26*G29 -> 1918.083 | H31: =H26*H29 -> 2522.1883 | I31: =I26*I29 -> 2736.2025 | J31: =J26*J29 -> 2698.5395 | K31: =K26*K29 -> 2661.3948
B33: Expected Growth | D33: ='DCF Assumptions'!$M$59 -> 0.10239195
B34: Terminal Growth | D34: ='Valuation Drivers'!C28 -> 0.045
B35: WACC | D35: =WACC!L45 -> 0.11777784
B37: Calculation of Terminal Value | G37: Sensitivity Analysis (in Rs.)
B39: FCFF(n+1) | D39: =K26*(1+D41) -> 5130.7497 | G39: =D57 -> 19.169964 | H39: 0.085510848 | I39: 0.10551085 | J39: 0.12551085 | K39: 0.14551085
B40: WACC | D40: =D35 -> 0.11777784 | G40: 0.025 | H40: 40.661896 | I40: 5.6138435 | J40: -15.486241 | K40: -29.582779
B41: Terminal growth Rate | D41: =D34 -> 0.045 | G41: 0.035 | H41: 70.242971 | I41: 21.833825 | J41: -5.1815783 | K41: -22.41861
B42: Terminal Value | D42: =D39/(D40-D41) -> 70498.79 | G42: 0.045 | H42: 114.42807 | I42: 43.414822 | J42: 7.6829043 | K42: -13.828889
G43: 0.055 | H43: 187.57671 | I43: 73.540913 | J43: 24.196324 | K43: -3.3411155
G44: 0.065 | H44: 332.05212 | I44: 118.5401 | J44: 46.167747 | K44: 9.7519652
B46: Calculation of EQUITY PRICE
B48: PV of FCFF | D48: =SUM(F31:K31) -> 13833.032
B49: PV of Terminal Value | D49: =D42*K29 -> 38214.347
B50: Value of Operating Assets | D50: =SUM(D48:D49) -> 52047.378
B52: Add- Cash | D52: ='Historical Financial Statements'!L78 -> 13644
B53: Less- Debt | D53: ='Historical Financial Statements'!L61 -> 76141
B54: Add- Investments | D54: ='Historical Financial Statements'!L95 -> 16575
B55: Value of Equity | D55: =D50+D52-D53+D54 -> 6125.3785
B56: No. of Shares | D56: ='Historical Financial Statements'!L42 -> 319.53
B57: Equity Value per Share (in Rs.) | D57: =D55/D56 -> 19.169964
B59: Share Price (in Rs.) | D59: ='Beta Regression Historical Data'!$L$4 -> 402.35
B61: Discount/Premium (%) | D61: =-(D59-D57)/D59 -> -0.95235501
B63: NOTE :-
B64: ="DCF-derived equity value (₹"&ROUND(D57,2)&"/share) is materially below market price (₹"&D59&"/share, "&ROUND(D61*100,2)&"% discount). Primary driver: reinvestment rate assumption ("&ROUND(D13*100,2)&"%→"&ROUND(K13*100,2)&"%of NOPAT) suppresses near-term FCFF."&" Secondary factor: as a consolidated single entity model, this DCF does not separately value Tata Power Renewable Energy Ltd (TPREL), which is not separately listed "&"the market may be pricing in growth-option value not captured here. A sum of the parts valuation was outside this project's scope." -> DCF-derived equity value (₹19.17/share) is materially below market price (₹402.35/share, -95.24% discount). Primary driver: reinvestment rate assumption (84%→56%of NOPAT) suppresses near-term FCFF. Secondary factor: as a consolidated single entity model, this DCF does not separately value Tata Power Renewable Energy Ltd (TPREL), which is not separately listed the market may be pricing in growth-option value not captured here. A sum of the parts valuation was outside this project's scope.

Sheet Peer Multiples Valuation
B5: Comparable company Valuation(in Rs.)
E7: Market Data | M7: Market Data | Q7: Valuation
B8: S.No. | C8: Company Ticker | D8: Ticker | E8: Share Price (in Rs.) | F8: Share Outstanding | G8: Equity Value | H8: Net Debt | I8: Cash equivalent | J8: Enterprise Value | M8: Revenue | N8: EBIDTA | O8: Net Income | Q8: EV/Revenue | R8: EV/EBITDA | S8: P/E
B10: 1 | C10: Adani Power | E10: 229.27 | F10: 1928.47 | G10: =F10*E10*10 -> 4421403.2 | H10: 54670.29 | I10: 6926.32 | J10: =G10+H10-I10 -> 4469147.1 | M10: 54240.52 | N10: 23691.493 | O10: 12971.08 | Q10: =$J10/M10 -> 82.394991 | R10: =$J10/N10 -> 188.63932 | S10: =G10/O10 -> 340.86623
B11: 2 | C11: NTPC | E11: 352.05 | F11: 969.67 | G11: =F11*E11 -> 341372.32 | H11: 271004.58 | I11: 8003.78 | J11: =G11+H11-I11 -> 604373.12 | M11: 187384.63 | N11: 58882.395 | O11: 27545.76 | Q11: =$J11/M11 -> 3.2253079 | R11: =$J11/N11 -> 10.264072 | S11: =G11/O11 -> 12.392917
B12: 3 | C12: Power Grid Corpn | E12: 283.9 | F12: 930.06 | G12: =F12*E12 -> 264044.03 | H12: 148070.6 | I12: 8920.41 | J12: =G12+H12-I12 -> 403194.22 | M12: 46732.87 | N12: 36828.832 | O12: 15927.95 | Q12: =$J12/M12 -> 8.6276367 | R12: =$J12/N12 -> 10.947787 | S12: =G12/O12 -> 16.577402
B13: 4 | C13: Adani Green | E13: 1526.1 | F13: 164.72 | G13: =F13*E13 -> 251379.19 | H13: 103545 | I13: 2766 | J13: =G13+H13-I13 -> 352158.19 | M13: 12928 | N13: 12188.331 | O13: 1987 | Q13: =$J13/M13 -> 27.239959 | R13: =$J13/N13 -> 28.893062 | S13: =G13/O13 -> 126.51192
B14: 5 | C14: Adani Energy Sol | E14: 1507.8 | F14: 120.13 | G14: =F14*E14 -> 181132.01 | H14: 49176.43 | I14: 3947.34 | J14: =G14+H14-I14 -> 226361.1 | M14: 27588.03 | N14: 8820.6987 | O14: 2392.75 | Q14: =$J14/M14 -> 8.2050478 | R14: =$J14/N14 -> 25.662491 | S14: =G14/O14 -> 75.700351
B15: 6 | C15: Tata Power Co. | E15: ='Beta Regression Historical Data'!L4 -> 402.35 | F15: 319.53 | G15: =F15*E15 -> 128562.9 | H15: 76141.27 | I15: 13644 | J15: =G15+H15-I15 -> 191060.17 | M15: 62428.59 | N15: 18105.01 | O15: 5117.56 | Q15: =$J15/M15 -> 3.0604594 | R15: =$J15/N15 -> 10.552889 | S15: =G15/O15 -> 25.121913
B16: 7 | C16: JSW Energy | E16: 573.5 | F16: 183.35 | G16: =F16*E16 -> 105151.22 | H16: 76945.78 | I16: 5765.22 | J16: =G16+H16-I16 -> 176331.79 | M16: 18901.13 | N16: 11282.342 | O16: 2762.41 | Q16: =$J16/M16 -> 9.3291663 | R16: =$J16/N16 -> 15.629005 | S16: =G16/O16 -> 38.065032
B17: 8 | C17: NTPC Green Ene. | E17: 95.72 | F17: 842.63 | G17: =F17*E17 -> 80656.544 | H17: 31716.14 | I17: 617.5 | J17: =G17+H17-I17 -> 111755.18 | M17: 2858.42 | N17: 2686.4137 | O17: 521.35 | Q17: =$J17/M17 -> 39.096838 | R17: =$J17/N17 -> 41.60014 | S17: =G17/O17 -> 154.70709
B18: 9 | C18: NHPC Ltd | E18: 79.4 | F18: 1004.5 | G18: =F18*E18 -> 79757.3 | H18: 52326.69 | I18: 3651.04 | J18: =G18+H18-I18 -> 128432.95 | M18: 11615.29 | N18: 7500.5105 | O18: 4220.46 | Q18: =$J18/M18 -> 11.057231 | R18: =$J18/N18 -> 17.123228 | S18: =G18/O18 -> 18.897774
B19: 10 | C19: Torrent Power | E19: 1413.7 | F19: 50.39 | G19: =F19*E19 -> 71236.343 | H19: 13970.56 | I19: 831.43 | J19: =G19+H19-I19 -> 84375.473 | M19: 28966.31 | N19: 5921.258 | O19: 2469.36 | Q19: =$J19/M19 -> 2.912883 | R19: =$J19/N19 -> 14.249586 | S19: =G19/O19 -> 28.8481
B20: 11 | C20: NLC India | E20: 320.1 | F20: 138.66 | G20: =F20*E20 -> 44385.066 | H20: 27891.78 | I20: 842.22 | J20: =G20+H20-I20 -> 71434.626 | M20: 17489.53 | N20: 7560.3395 | O20: 3769.46 | Q20: =$J20/M20 -> 4.0844223 | R20: =$J20/N20 -> 9.4486002 | S20: =G20/O20 -> 11.774914
B21: 12 | C21: SJVN | E21: 72.09 | F21: 392.98 | G21: =F21*E21 -> 28329.928 | H21: 32278.49 | I21: 2522.52 | J21: =G21+H21-I21 -> 58085.898 | M21: 4528.29 | N21: 3637.9603 | O21: 641.85 | Q21: =$J21/M21 -> 12.827336 | R21: =$J21/N21 -> 15.966611 | S21: =G21/O21 -> 44.137927
B22: 13 | C22: ACME Solar Hold. | E22: 357.2 | F22: 70.69 | G22: =F22*E22 -> 25250.468 | H22: 19896.29 | I22: 6158.09 | J22: =G22+H22-I22 -> 38988.668 | M22: 2023.38 | N22: 2623.2863 | O22: 497.89 | Q22: =$J22/M22 -> 19.269078 | R22: =$J22/N22 -> 14.862528 | S22: =G22/O22 -> 50.714953
B23: 14 | C23: CESC | E23: 168.03 | F23: 132.56 | G23: =F23*E23 -> 22274.057 | H23: 21671 | I23: 5572 | J23: =G23+H23-I23 -> 38373.057 | M23: 18570 | N23: 5392.0315 | O23: 1618 | Q23: =$J23/M23 -> 2.0664005 | R23: =$J23/N23 -> 7.1166232 | S23: =G23/O23 -> 13.766413
B24: 15 | C24: IndiGrid Trust | E24: 176.15 | F24: 95.26 | G24: =F24*E24 -> 16780.049 | H24: 21359.14 | I24: 350.35 | J24: =G24+H24-I24 -> 37788.839 | M24: 4768.38 | N24: 3014.9557 | O24: 399 | Q24: =$J24/M24 -> 7.9248799 | R24: =$J24/N24 -> 12.533796 | S24: =G24/O24 -> 42.055261
B25: 16 | C25: Nava | E25: 607.15 | F25: 28.33 | G25: =F25*E25 -> 17200.559 | H25: 2226.41 | I25: 2114.85 | J25: =G25+H25-I25 -> 17312.12 | M25: 4290.92 | N25: 2137.1804 | O25: 1038.52 | Q25: =$J25/M25 -> 4.0345939 | R25: =$J25/N25 -> 8.1004485 | S25: =G25/O25 -> 16.562569
B26: 17 | C26: Clean Max Enviro | E26: 1352.1 | F26: 11.72 | G26: =F26*E26 -> 15846.612 | H26: 12684.32 | I26: 2287.96 | J26: =G26+H26-I26 -> 26242.972 | M26: 1912.87 | N26: 1414.5232 | O26: 85.57 | Q26: =$J26/M26 -> 13.719161 | R26: =$J26/N26 -> 18.552522 | S26: =G26/O26 -> 185.18887
B27: 18 | C27: JP Power Ven. | E27: 17.94 | F27: 685.35 | G27: =F27*E27 -> 12295.179 | H27: 3391.08 | I27: 2008.85 | J27: =G27+H27-I27 -> 13677.409 | M27: 5563.46 | N27: 1830.3686 | O27: 450.63 | Q27: =$J27/M27 -> 2.4584358 | R27: =$J27/N27 -> 7.4724888 | S27: =G27/O27 -> 27.284422
... B33: 24 | C33: Sustainable Ener | E33: 123 | F33: 32.4 | G33: =F33*E33 -> 3985.2 | H33: 3281.43 | I33: 75.35 | J33: =G33+H33-I33 -> 7191.28 | M33: 728.32 | N33: 677.85728 | O33: 133.98 | Q33: =$J33/M33 -> 9.8737917 | R33: =$J33/N33 -> 10.608841 | S33: =G33/O33 -> 29.744738
C35: High | E35: =MAX(E10:E33) -> 1526.1 | F35: =MAX(F10:F33) -> 1928.47 | G35: =MAX(G10:G33) -> 4421403.2 | H35: =MAX(H10:H33) -> 271004.58 | I35: =MAX(I10:I33) -> 13644 | J35: =MAX(J10:J33) -> 4469147.1 | M35: =MAX(M10:M33) -> 187384.63 | N35: =MAX(N10:N33) -> 58882.395 | O35: =MAX(O10:O33) -> 27545.76 | Q35: =MAX(Q10:Q33) -> 82.394991 | R35: =MAX(R10:R33) -> 188.63932 | S35: =MAX(S10:S33) -> 340.86623
C36: 75th Percentile | E36: =QUARTILE(E$11:E$33,3) -> 487.925 | F36: =QUARTILE(F$11:F$33,3) -> 464.995 | G36: =QUARTILE(G$11:G$33,3) -> 92903.884 | H36: =QUARTILE(H$11:H$33,3) -> 50751.56 | I36: =QUARTILE(I$11:I$33,3) -> 4759.67 | J36: =QUARTILE(J$11:J$33,3) -> 152382.37 | M36: =QUARTILE(M$11:M$33,3) -> 18735.565 | N36: =QUARTILE(N$11:N$33,3) -> 8190.5191 | O36: =QUARTILE(O$11:O$33,3) -> 2615.885 | Q36: =QUARTILE(Q$11:Q$33,3) -> 10.465512 | R36: =QUARTILE(R$11:R$33,3) -> 15.797808 | S36: =QUARTILE(S$11:S$33,3) -> 47.42644
C37: Average | E37: =AVERAGE(E10:E33) -> 435.02333 | F37: =AVERAGE(F10:F33) -> 369.03667 | G37: =AVERAGE(G10:G33) -> 256063.2 | H37: =AVERAGE(H10:H33) -> 43565.871 | I37: =AVERAGE(I10:I33) -> 3542.4342 | J37: =AVERAGE(J10:J33) -> 296086.64 | M37: =AVERAGE(M10:M33) -> 22690.287 | N37: =AVERAGE(N10:N33) -> 9270.4443 | O37: =AVERAGE(O10:O33) -> 3639.8025 | Q37: =AVERAGE(Q10:Q33) -> 11.949177 | R37: =AVERAGE(R10:R33) -> 20.921564 | S37: =AVERAGE(S10:S33) -> 58.221926
C38: Median | E38: =MEDIAN(E10:E33) -> 256.585 | F38: =MEDIAN(F10:F33) -> 135.61 | G38: =MEDIAN(G10:G33) -> 26790.198 | H38: =MEDIAN(H10:H33) -> 21515.07 | I38: =MEDIAN(I10:I33) -> 2405.24 | J38: =MEDIAN(J10:J33) -> 48537.283 | M38: =MEDIAN(M10:M33) -> 9473.575 | N38: =MEDIAN(N10:N33) -> 3326.458 | O38: =MEDIAN(O10:O33) -> 975.195 | Q38: =MEDIAN(Q10:Q33) -> 7.0996028 | R38: =MEDIAN(R10:R33) -> 11.397235 | S38: =MEDIAN(S10:S33) -> 28.066261
C39: 25th Percentile | E39: =QUARTILE(E$11:E$33,1) -> 97.66 | F39: =QUARTILE(F$11:F$33,1) -> 60.54 | G39: =QUARTILE(G$11:G$33,1) -> 10415.035 | H39: =QUARTILE(H$11:H$33,1) -> 4453.83 | I39: =QUARTILE(I$11:I$33,1) -> 836.825 | J39: =QUARTILE(J$11:J$33,1) -> 15494.764 | M39: =QUARTILE(M$11:M$33,1) -> 2924.89 | N39: =QUARTILE(N$11:N$33,1) -> 1983.7745 | O39: =QUARTILE(O$11:O$33,1) -> 503.565 | Q39: =QUARTILE(Q$11:Q$33,1) -> 2.9866712 | R39: =QUARTILE(R$11:R$33,1) -> 8.1775552 | S39: =QUARTILE(S$11:S$33,1) -> 14.622484
C40: Low | E40: =MIN(E10:E33) -> 9.12 | F40: =MIN(F10:F33) -> 11.72 | G40: =MIN(G10:G33) -> 3985.2 | H40: =MIN(H10:H33) -> 1063.56 | I40: =MIN(I10:I33) -> 75.35 | J40: =MIN(J10:J33) -> 4687.5112 | M40: =MIN(M10:M33) -> 728.32 | N40: =MIN(N10:N33) -> 677.85728 | O40: =MIN(O10:O33) -> 52.44 | Q40: =MIN(Q10:Q33) -> 0.35631714 | R40: =MIN(R10:R33) -> 2.1562436 | S40: =MIN(S10:S33) -> 7.500669
B42: ='DuPont ROE Analysis'!B2 & " Comparable Valuation" -> TATA POWER COMPANY LTD Comparable Valuation | P42: EV/Revenue | Q42: EV/EBITDA | R42: P/E | S42: ='Reg-Based Relative Valuation'!K7 -> Regression P/E
B44: Implied Enterprise Value | P44: =Q38*M15 -> 443218.19 | Q44: =R38*N15 -> 206347.06 | R44: =R47+R45-R46 -> 206128.04 | S44: =S47+S45-S46 -> 269114.95
B45: Net Debt | P45: =$H$15 -> 76141.27 | Q45: =$H$15 -> 76141.27 | R45: =$H$15 -> 76141.27 | S45: =$H$15 -> 76141.27
B46: Cash Equivalent | P46: =$I$15 -> 13644 | Q46: =$I$15 -> 13644 | R46: =$I$15 -> 13644 | S46: =$I$15 -> 13644
B47: Implied Market Value | P47: =P44-P45+P46 -> 380720.92 | Q47: =Q44-Q45+Q46 -> 143849.79 | R47: =S38*O15 -> 143630.77 | S47: ='Reg-Based Relative Valuation'!K13*'Peer Multiples Valuation'!O15 -> 206617.68
B48: Share Outstanding | P48: =$F$15 -> 319.53 | Q48: =$F$15 -> 319.53 | R48: =$F$15 -> 319.53 | S48: =$F$15 -> 319.53
B49: Implied Value per Share (in Rs.) | P49: =P47/P48 -> 1191.5029 | Q49: =Q47/Q48 -> 450.19183 | R49: =R47/R48 -> 449.50638 | S49: =S47/S48 -> 646.62999

Sheet Reg-Based Relative Valuation
B5: Comparable company Regression-Based Valuation
B7: S.No. | C7: Company Ticker | D7: Ticker | E7: Share Price | F7: P/E | G7: ROE % | H7: Dividend Payout % | I7: Growth % | J7: Beta(Risk) | K7: Regression P/E
B8: 1 | C8: Adani Power | E8: 229.27 | F8: 34.086623 | G8: 0.2107 | H8: 0 | I8: =G8*H8 -> 0 | J8: 0.16 | K8: =$N$26+($N$27*G8)+($N$28*H8)+($N$29*I8)+($N$30*J8) -> 46.756024
B9: 2 | C9: NTPC | E9: 352.05 | F9: 12.392917 | G9: 0.1397 | H9: 0.3226 | I9: =G9*H9 -> 0.04506722 | J9: 0.46 | K9: =$N$26+($N$27*G9)+($N$28*H9)+($N$29*I9)+($N$30*J9) -> 35.957473
B10: 3 | C10: Power Grid Corpn | E10: 283.9 | F10: 16.577402 | G10: 0.1649 | H10: 0.7883 | I10: =G10*H10 -> 0.12999067 | J10: 0.39 | K10: =$N$26+($N$27*G10)+($N$28*H10)+($N$29*I10)+($N$30*J10) -> 15.056977 | M10: SUMMARY OUTPUT
B11: 4 | C11: Adani Green | E11: 1526.1 | F11: 126.51192 | G11: 0.114 | H11: 0 | I11: =G11*H11 -> 0 | J11: 0.78 | K11: =$N$26+($N$27*G11)+($N$28*H11)+($N$29*I11)+($N$30*J11) -> 44.920422
B12: 5 | C12: Adani Energy Sol | E12: 1507.8 | F12: 75.700351 | G12: 0.0944 | H12: 0 | I12: =G12*H12 -> 0 | J12: 1.32 | K12: =$N$26+($N$27*G12)+($N$28*H12)+($N$29*I12)+($N$30*J12) -> 43.772297 | M12: Regression Statistics
B13: 6 | C13: Tata Power Co. | E13: ='Beta Regression Historical Data'!L4 -> 402.35 | F13: 24.285244 | G13: 0.1021 | H13: 0.2132 | I13: =G13*H13 -> 0.02176772 | J13: =WACC!$K$21 -> 1.2649327 | K13: =$N$26+($N$27*G13)+($N$28*H13)+($N$29*I13)+($N$30*J13) -> 40.374257 | M13: Multiple R | N13: 0.24163415
B14: 7 | C14: JSW Energy | E14: 573.5 | F14: 38.065032 | G14: 0.0751 | H14: 0.1569 | I14: =G14*H14 -> 0.01178319 | J14: 0.61 | K14: =$N$26+($N$27*G14)+($N$28*H14)+($N$29*I14)+($N$30*J14) -> 43.875056 | M14: R Square | N14: 0.058387064
B15: 8 | C15: NTPC Green Ene. | E15: 95.72 | F15: 154.70709 | G15: 0.0929 | H15: 0.4295 | I15: =G15*H15 -> 0.03990055 | J15: 0.46 | K15: =$N$26+($N$27*G15)+($N$28*H15)+($N$29*I15)+($N$30*J15) -> 39.632363 | M15: Adjusted R Square | N15: -0.15086025
B16: 9 | C16: NHPC Ltd | E16: 79.4 | F16: 18.897774 | G16: 0.0279 | H16: 0 | I16: =G16*H16 -> 0 | J16: 0.58 | K16: =$N$26+($N$27*G16)+($N$28*H16)+($N$29*I16)+($N$30*J16) -> 44.694642 | M16: Standard Error | N16: 41.361384
B17: 10 | C17: Torrent Power | E17: 1413.7 | F17: 28.8481 | G17: 0.1317 | H17: 0.4171 | I17: =G17*H17 -> 0.05493207 | J17: 0.54 | K17: =$N$26+($N$27*G17)+($N$28*H17)+($N$29*I17)+($N$30*J17) -> 34.098329 | M17: Observations | N17: 23
B18: 11 | C18: NLC India | E18: 320.1 | F18: 11.774914 | G18: 0.175 | H18: 0.1516 | I18: =G18*H18 -> 0.02653 | J18: 0.69 | K18: =$N$26+($N$27*G18)+($N$28*H18)+($N$29*I18)+($N$30*J18) -> 39.011814
B19: 12 | C19: SJVN | E19: 72.09 | F19: 44.137927 | G19: 0.0452 | H19: 0.9181 | I19: =G19*H19 -> 0.04149812 | J19: 0.67 | K19: =$N$26+($N$27*G19)+($N$28*H19)+($N$29*I19)+($N$30*J19) -> 48.126743 | M19: ANOVA
B20: 13 | C20: ACME Solar Hold. | E20: 357.2 | F20: 50.714953 | G20: 0.1038 | H20: 0.0243 | I20: =G20*H20 -> 0.00252234 | J20: -0.11 | K20: =$N$26+($N$27*G20)+($N$28*H20)+($N$29*I20)+($N$30*J20) -> 46.096282 | N20: df | O20: SS | P20: MS | Q20: F | R20: Significance F
B21: 14 | C21: CESC | E21: 168.03 | F21: 13.766413 | G21: 0.1257 | H21: 0.5175 | I21: =G21*H21 -> 0.06504975 | J21: 0.51 | K21: =$N$26+($N$27*G21)+($N$28*H21)+($N$29*I21)+($N$30*J21) -> 32.486513 | M21: Regression | N21: 4 | O21: 1909.4437 | P21: 477.36093 | Q21: 0.27903375 | R21: 0.88768582
B22: 15 | C22: IndiGrid Trust | E22: 176.15 | F22: 42.055261 | G22: 0.0702 | H22: 4.1573 | I22: =G22*H22 -> 0.29184246 | J22: 0.19 | K22: =$N$26+($N$27*G22)+($N$28*H22)+($N$29*I22)+($N$30*J22) -> 24.098377 | M22: Residual | N22: 18 | O22: 30793.754 | P22: 1710.7641
B23: 16 | C23: Nava | E23: 607.15 | F23: 16.562569 | G23: 0.0963 | H23: 0.1979 | I23: =G23*H23 -> 0.01905777 | J23: 1.2 | K23: =$N$26+($N$27*G23)+($N$28*H23)+($N$29*I23)+($N$30*J23) -> 41.123365 | M23: Total | N23: 22 | O23: 32703.198
B24: 18 | C24: JP Power Ven. | E24: 17.94 | F24: 27.284422 | G24: 0.036 | H24: 0 | I24: =G24*H24 -> 0 | J24: 1.24 | K24: =$N$26+($N$27*G24)+($N$28*H24)+($N$29*I24)+($N$30*J24) -> 43.514908
B25: 19 | C25: Powergrid Infra. | E25: 93.79 | F25: 9.3597662 | G25: 0.1195 | H25: 1.1975 | I25: =G25*H25 -> 0.14310125 | J25: 0.17 | K25: =$N$26+($N$27*G25)+($N$28*H25)+($N$29*I25)+($N$30*J25) -> 18.640369 | N25: Coefficients | O25: Standard Error | P25: t Stat | Q25: P-value | R25: Lower 95% | S25: Upper 95% | T25: Lower 95.0% | U25: Upper 95.0%
B26: 20 | C26: KPI Green Energy | E26: 398.7 | F26: 15.478554 | G26: 0.1739 | H26: 0.0435 | I26: =G26*H26 -> 0.00756465 | J26: 1.19 | K26: =$N$26+($N$27*G26)+($N$28*H26)+($N$29*I26)+($N$30*J26) -> 42.721536 | M26: Intercept | N26: 45.586463 | O26: 27.464937 | P26: 1.6598059 | Q26: 0.11427433 | R26: -12.115228 | S26: 103.28815 | T26: -12.115228 | U26: 103.28815
B27: 21 | C27: GMR Urban | E27: 99.6 | F27: 12.67539 | G27: -0.1434 | H27: 0 | I27: =G27*H27 -> 0 | J27: 0.86 | K27: =$N$26+($N$27*G27)+($N$28*H27)+($N$29*I27)+($N$30*J27) -> 42.97568 | M27: ROE % | N27: 6.9731843 | O27: 136.53866 | P27: 0.051071133 | Q27: 0.95983132 | R27: -279.8839 | S27: 293.83027 | T27: -279.8839 | U27: 293.83027
B28: 22 | C28: PTC India | E28: 181.8 | F28: 7.500669 | G28: 0.1033 | H28: 0.4154 | I28: =G28*H28 -> 0.04291082 | J28: 0.85 | K28: =$N$26+($N$27*G28)+($N$28*H28)+($N$29*I28)+($N$30*J28) -> 37.609071 | M28: Dividend Payout % | N28: 20.046904 | O28: 26.622251 | P28: 0.75301312 | Q28: 0.46117797 | R28: -35.884369 | S28: 75.978177 | T28: -35.884369 | U28: 75.978177
B29: 23 | C29: RattanIndia Pow. | E29: 9.12 | F29: 93.393043 | G29: 0.0114 | H29: 0 | I29: =G29*H29 -> 0 | J29: 1.42 | K29: =$N$26+($N$27*G29)+($N$28*H29)+($N$29*I29)+($N$30*J29) -> 43.006217 | M29: Growth % | N29: -359.6554 | O29: 395.1054 | P29: -0.91027711 | Q29: 0.37470532 | R29: -1189.741 | S29: 470.43024 | T29: -1189.741 | U29: 470.43024
B30: 24 | C30: Sustainable Ener | E30: 123 | F30: 29.744738 | G30: 0.0445 | H30: 2.5876 | I30: =G30*H30 -> 0.1151482 | J30: 1.05 | K30: =$N$26+($N$27*G30)+($N$28*H30)+($N$29*I30)+($N$30*J30) -> 54.389758 | M30: Beta(Risk) | N30: -1.8730563 | O30: 25.162794 | P30: -0.07443753 | Q30: 0.94148326 | R30: -54.738125 | S30: 50.992013 | T30: -54.738125 | U30: 50.992013
B32: NOTE :-
B33: This regression (P/E against ROE, Dividend Payout, Growth, and Beta) yields a low R² (0.058) and statistically insignificant coefficients (all p-values > 0.37), meaning it does not reliably explain cross-sectional P/E variation for this peer set. This section is retained to demonstrate multi-variable regression methodology, statistical output interpretation (R², t-stats, p-values, F-significance), and the ability to identify when a model fails to meet statistical thresholds — a key analytical skill in its own right. The output of this regression is excluded from the valuation conclusion and should not be used to inform any investment decision.
B34: Source | C34: screener

Sheet Reports->

Sheet Football Field Analysis
C4: Football Field Analysis - Data
E5: OpenLow | F5: Low | G5: OpenHigh | H5: High
C6: Comps | E6: 449.50638 | F6: 449.50638 | G6: 1191.5029 | H6: 1191.5029
C7: DCF Bear | E7: =F7 -> -29.582779 | F7: ='DCF Model'!K40 -> -29.582779 | G7: =H7 -> 9.7519652 | H7: ='DCF Model'!K44 -> 9.7519652
C8: DCF Base | E8: =F8 -> -15.486241 | F8: ='DCF Model'!J40 -> -15.486241 | G8: =H8 -> 46.167747 | H8: ='DCF Model'!J44 -> 46.167747
C9: DCF Bull | E9: =F9 -> 40.661896 | F9: ='DCF Model'!H40 -> 40.661896 | G9: =H9 -> 332.05212 | H9: ='DCF Model'!H44 -> 332.05212
C10: 52W H/L | E10: =F10 -> 342.35 | F10: 342.35 | G10: =H10 -> 464.9 | H10: 464.9

Sheet DuPont ROE Analysis
B2: ='Data Sheet'!B1 -> TATA POWER COMPANY LTD
B3: =CONCATENATE("(",VLOOKUP(B2,'Peer Company Database'!B2:E5443,3,FALSE),"|","BSE CODE - ", VLOOKUP(B2,'Peer Company Database'!B2:E5443,2,FALSE),")") -> (TATAPOWER|BSE CODE - 500400)
B4: =_xlfn.CONCAT("INR "&ROUND('Beta Regression Historical Data'!L4,2)) -> INR 402.35
B5: 52 Week (HIGH - INR 464.90 & LOW - INR 342.35 )
B7: About the Company
B8: Tata Power is India's largest integrated electricity company and a key subsidiary of the Tata Group.Its operations span the entire power value chain, including energy generation, transmission, and distribution.The company manages a massive diversified generation capacity exceeding 14,700 megawatts across the nation.It is rapidly shifting away from fossil fuels, aiming for 70% clean energy capacity by 2030.Their renewable portfolio includes massive utility-scale investments in solar, wind, and hydroelectric power plants.They are building India's largest public and residential electric vehicle charging networks to support green transit.
B9: Financial Summary
B23: Return on Equity (ROE)
C24: ='DCF Assumptions'!D4 -> 42825 | D24: ='DCF Assumptions'!E4 -> 43190 | E24: ='DCF Assumptions'!F4 -> 43555 | F24: ='DCF Assumptions'!G4 -> 43921 | G24: ='DCF Assumptions'!H4 -> 44286 | H24: ='DCF Assumptions'!I4 -> 44651 | I24: ='DCF Assumptions'!J4 -> 45016 | J24: ='DCF Assumptions'!K4 -> 45382 | ... L24: ='DCF Assumptions'!M4 -> 46112
